Workbook
Name Segment_Category: #N/A
Name Segment_Channel_clean: #N/A
Name Segment_Region: #N/A

Sheet Project_Brief
A1: Excel Portfolio Project #1 — Northstar Retail Sales Analysis
A4: Business Scenario
A5: You are a junior data analyst at Northstar Retail Canada. Management wants a 2025 performance review showing sales, profit, customers, products, channels, returns and performance versus monthly targets. The raw export is intentionally messy. Your job is to clean it, validate it, analyze it and build an executive Excel dashboard.
A9: Your Build — Do NOT skip steps
A10: Stage | B10: What you should build | C10: Core Excel concepts
A11: 1. Audit | B11: Check row count, blanks, duplicate Order_IDs, inconsistent categories, key quality. | C11: COUNTIF/COUNTIFS, filters, conditional formatting
A12: 2. Clean | B12: Create a new Cleaned_Data sheet. Normalize spaces/text and standardize categories. | C12: TRIM, CLEAN, SUBSTITUTE, UPPER/LOWER/PROPER, IF
A13: 3. Parse | B13: Extract Customer Name, City and Segment from Customer_Info. | C13: FIND, MID, LEFT, RIGHT, LEN — including finding the 2nd comma
A14: 4. Enrich | B14: Bring Product, Category, Unit Cost, Region and customer segment into Cleaned_Data. | C14: XLOOKUP; then redo one lookup with INDEX+MATCH
A15: 5. Calculate | B15: Create Gross Sales, Discount Amount, Net Sales, Total Cost, Profit, Profit Margin. | C15: Arithmetic, IF/IFERROR, absolute/relative references
A16: 6. Date fields | B16: Create Month, Month Number, Quarter and Year. | C16: YEAR, MONTH, TEXT, date logic
A17: 7. Analyze | B17: Answer the business questions below using PivotTables and/or SUMIFS/COUNTIFS. | C17: PivotTables, SUMIFS, COUNTIFS, aggregation
A18: 8. Dashboard | B18: Build one-page dashboard with KPIs + charts + filters/slicers. | C18: PivotCharts, charts, KPI design, formatting
A19: 9. QA | B19: Reconcile dashboard totals to cleaned transactions and document assumptions. | C19: Data validation, error checks, reconciliation
A20: 10. GitHub | B20: Publish workbook + README + screenshots + key findings. | C20: Portfolio storytelling
A22: Business Questions Your Analysis Must Answer
A23: 1 | B23: What were total Net Sales, Profit, Profit Margin and unique Orders in 2025?
A24: 2 | B24: Which months beat or missed sales and profit targets?
A25: 3 | B25: Which product categories and products generated the most sales and profit?
A26: 4 | B26: Which regions and customer segments are most valuable?
A27: 5 | B27: How do Online, Retail Store and Marketplace channels compare?
A28: 6 | B28: Which products have high sales but weak profit margin?
A29: 7 | B29: Do larger discounts appear to improve revenue at the expense of margin?
A30: 8 | B30: Which channels/regions have the highest return rate?
A31: 9 | B31: What are the top 10 customers by Net Sales?
A32: 10 | B32: What 3 actions would you recommend to management based on your analysis?
A34: Final GitHub Deliverables
A35: File | B35: Purpose
A36: Northstar_Retail_Analysis.xlsx | B36: Your completed cleaned data, analysis and dashboard.
A37: README.md | B37: Business problem, cleaning steps, analysis, findings and recommendations.
A38: dashboard.png | B38: Screenshot of your final dashboard for the repo landing page.
A39: Optional: cleaned_sales.csv | B39: Cleaned dataset for future SQL/Python reuse.

Sheet Raw_Sales
A1: Order_ID | B1: Order_Date | C1: Customer_ID | D1: Product_ID | E1: Customer_Info | F1: Store_Raw | G1: Salesperson | H1: Channel_Raw | I1: Quantity | J1: Unit_Price | K1: Discount_Pct | L1: Payment_Method_Raw | M1: Delivery_Days | N1: Return_Status | O1: Channel_clean | P1: Store_clean | Q1: Payment_Method_clean | R1: Customer_ID_clean | S1: Customer_Name | T1: Customer_City | U1: Customer_Segment | V1: Product_Name | W1: Category | X1: Unit_Cost | Y1: Gross_Sales | Z1: Discount_Amount | AA1: Net_Sales | AB1: Total_Cost | AC1: Profit | AD1: Profit_Margin | AE1: Return_Flag | AF1: Year | AG1: Month_Number | AH1: Month | AI1: Quarter | AJ1: Month_Start | AK1: Region
A2: ORD-2025-00123 | B2: 45661 | C2: C0064 | D2: P1002 | E2: Amine Khan , Edmonton , Consumer | F2: Vancouver West | G2: M. Wilson | H2: Retail Store | I2: 1 | J2: 38.4 | K2: 0.15 | L2: Credit Card | M2: 4 | N2: No | O2: =SUBSTITUTE(PROPER(TRIM(RawSalesTable[[#This Row],[Channel_Raw]])), "Market Place", "Marketplace") -> Retail Store | P2: =TRIM(RawSalesTable[[#This Row],[Store_Raw]]) -> Vancouver West | Q2: =IF(TRIM(RawSalesTable[[#This Row],[Payment_Method_Raw]])="","Non renseigné",SUBSTITUTE(TRIM(RawSalesTable[[#This Row],[Payment_Method_Raw]]),"CC","Credit Card")) -> Credit Card | R2: =UPPER(PROPER(RawSalesTable[[#This Row],[Customer_ID]])) -> C0064 | S2: =TRIM(LEFT(RawSalesTable[[#This Row],[Customer_Info]],FIND(",",RawSalesTable[[#This Row],[Customer_Info]]) -1)) -> Amine Khan | T2: =TRIM(MID(RawSalesTable[[#This Row],[Customer_Info]],FIND(",",RawSalesTable[[#This Row],[Customer_Info]])+1,FIND(",",RawSalesTable[[#This Row],[Customer_Info]],FIND(",",RawSalesTable[[#This Row],[Customer_Info]])+1)-FIND(",",RawSalesTable[[#This Row],[Customer_Info]])-1)) -> Edmonton | U2: =TRIM(RIGHT(RawSalesTable[[#This Row],[Customer_Info]], LEN(RawSalesTable[[#This Row],[Customer_Info]])-FIND(",",RawSalesTable[[#This Row],[Customer_Info]],FIND(",",RawSalesTable[[#This Row],[Customer_Info]])+1))) -> Consumer | V2: =VLOOKUP(RawSalesTable[[#This Row],[Product_ID]],ProductsTable[],2,FALSE) -> Keyboard | W2: =VLOOKUP(RawSalesTable[[#This Row],[Product_ID]],ProductsTable[],3,FALSE) -> Electronics | X2: =VLOOKUP(RawSalesTable[[#This Row],[Product_ID]],ProductsTable[],5,FALSE) -> 23.5 | Y2: =RawSalesTable[[#This Row],[Quantity]]*RawSalesTable[[#This Row],[Unit_Price]] -> 38.4 | Z2: =RawSalesTable[[#This Row],[Gross_Sales]]*RawSalesTable[[#This Row],[Discount_Pct]] -> 5.76 | AA2: =RawSalesTable[[#This Row],[Gross_Sales]]-RawSalesTable[[#This Row],[Discount_Amount]] -> 32.64 | AB2: =RawSalesTable[[#This Row],[Unit_Cost]]*RawSalesTable[[#This Row],[Quantity]] -> 23.5 | AC2: =RawSalesTable[[#This Row],[Net_Sales]]-RawSalesTable[[#This Row],[Total_Cost]] -> 9.14 | AD2: =RawSalesTable[[#This Row],[Profit]]/RawSalesTable[[#This Row],[Net_Sales]] -> 0.28002451 | AE2: =IF(RawSalesTable[[#This Row],[Return_Status]]="Yes",1,0) -> 0 | AF2: =YEAR(RawSalesTable[[#This Row],[Order_Date]]) -> 2025 | AG2: =MONTH(RawSalesTable[[#This Row],[Order_Date]]) -> 1 | AH2: =TEXT(RawSalesTable[[#This Row],[Order_Date]],"mmmm") -> janvier | AI2: =IF(RawSalesTable[[#This Row],[Month_Number]]<=3,"Q1",IF(RawSalesTable[[#This Row],[Month_Number]]<=6,"Q2",IF(RawSalesTable[[#This Row],[Month_Number]]<=9,"Q3","Q4"))) -> Q1 | AJ2: =DATE(YEAR(RawSalesTable[[#This Row],[Order_Date]]),MONTH(RawSalesTable[[#This Row],[Order_Date]]),1) -> 45658 | AK2: =VLOOKUP(RawSalesTable[[#This Row],[Customer_ID_clean]],CustomersTable[],4,FALSE) -> Alberta
A3: ORD-2025-00167 | B3: 45913 | C3: C0106 | D3: P1009 | E3: Liam Gagnon, Ottawa, Small Business | F3: Vancouver West | G3: M. Wilson | H3: Retail Store | I3: 3 | J3: 305.98 | K3: 0.15 | L3: Credit Card | M3: 0 | N3: No | O3: =SUBSTITUTE(PROPER(TRIM(RawSalesTable[[#This Row],[Channel_Raw]])), "Market Place", "Marketplace") -> Retail Store | P3: =TRIM(RawSalesTable[[#This Row],[Store_Raw]]) -> Vancouver West | Q3: =IF(TRIM(RawSalesTable[[#This Row],[Payment_Method_Raw]])="","Non renseigné",SUBSTITUTE(TRIM(RawSalesTable[[#This Row],[Payment_Method_Raw]]),"CC","Credit Card")) -> Credit Card | R3: =UPPER(PROPER(RawSalesTable[[#This Row],[Customer_ID]])) -> C0106 | S3: =TRIM(LEFT(RawSalesTable[[#This Row],[Customer_Info]],FIND(",",RawSalesTable[[#This Row],[Customer_Info]]) -1)) -> Liam Gagnon | T3: =TRIM(MID(RawSalesTable[[#This Row],[Customer_Info]],FIND(",",RawSalesTable[[#This Row],[Customer_Info]])+1,FIND(",",RawSalesTable[[#This Row],[Customer_Info]],FIND(",",RawSalesTable[[#This Row],[Customer_Info]])+1)-FIND(",",RawSalesTable[[#This Row],[Customer_Info]])-1)) -> Ottawa | U3: =TRIM(RIGHT(RawSalesTable[[#This Row],[Customer_Info]], LEN(RawSalesTable[[#This Row],[Customer_Info]])-FIND(",",RawSalesTable[[#This Row],[Customer_Info]],FIND(",",RawSalesTable[[#This Row],[Customer_Info]])+1))) -> Small Business | V3: =VLOOKUP(RawSalesTable[[#This Row],[Product_ID]],ProductsTable[],2,FALSE) -> Notebook | W3: =VLOOKUP(RawSalesTable[[#This Row],[Product_ID]],ProductsTable[],3,FALSE) -> Office | X3: =VLOOKUP(RawSalesTable[[#This Row],[Product_ID]],ProductsTable[],5,FALSE) -> 176.13 | Y3: =RawSalesTable[[#This Row],[Quantity]]*RawSalesTable[[#This Row],[Unit_Price]] -> 917.94 | Z3: =RawSalesTable[[#This Row],[Gross_Sales]]*RawSalesTable[[#This Row],[Discount_Pct]] -> 137.691 | AA3: =RawSalesTable[[#This Row],[Gross_Sales]]-RawSalesTable[[#This Row],[Discount_Amount]] -> 780.249 | AB3: =RawSalesTable[[#This Row],[Unit_Cost]]*RawSalesTable[[#This Row],[Quantity]] -> 528.39 | AC3: =RawSalesTable[[#This Row],[Net_Sales]]-RawSalesTable[[#This Row],[Total_Cost]] -> 251.859 | AD3: =RawSalesTable[[#This Row],[Profit]]/RawSalesTable[[#This Row],[Net_Sales]] -> 0.32279311 | AE3: =IF(RawSalesTable[[#This Row],[Return_Status]]="Yes",1,0) -> 0 | AF3: =YEAR(RawSalesTable[[#This Row],[Order_Date]]) -> 2025 | AG3: =MONTH(RawSalesTable[[#This Row],[Order_Date]]) -> 9 | AH3: =TEXT(RawSalesTable[[#This Row],[Order_Date]],"mmmm") -> septembre | AI3: =IF(RawSalesTable[[#This Row],[Month_Number]]<=3,"Q1",IF(RawSalesTable[[#This Row],[Month_Number]]<=6,"Q2",IF(RawSalesTable[[#This Row],[Month_Number]]<=9,"Q3","Q4"))) -> Q3 | AJ3: =DATE(YEAR(RawSalesTable[[#This Row],[Order_Date]]),MONTH(RawSalesTable[[#This Row],[Order_Date]]),1) -> 45901 | AK3: =VLOOKUP(RawSalesTable[[#This Row],[Customer_ID_clean]],CustomersTable[],4,FALSE) -> Ontario
A4: ORD-2025-00244 | B4: 45923 | C4: C0068 | D4: P1031 | E4: Yasmine Martin, Calgary, Consumer | F4: Calgary North | G4: L. Chen | H4: Marketplace | I4: 3 | J4: 251.49 | K4: 0.15 | L4: Debit Card | M4: 6 | N4: No | O4: =SUBSTITUTE(PROPER(TRIM(RawSalesTable[[#This Row],[Channel_Raw]])), "Market Place", "Marketplace") -> Marketplace | P4: =TRIM(RawSalesTable[[#This Row],[Store_Raw]]) -> Calgary North | Q4: =IF(TRIM(RawSalesTable[[#This Row],[Payment_Method_Raw]])="","Non renseigné",SUBSTITUTE(TRIM(RawSalesTable[[#This Row],[Payment_Method_Raw]]),"CC","Credit Card")) -> Debit Card | R4: =UPPER(PROPER(RawSalesTable[[#This Row],[Customer_ID]])) -> C0068 | S4: =TRIM(LEFT(RawSalesTable[[#This Row],[Customer_Info]],FIND(",",RawSalesTable[[#This Row],[Customer_Info]]) -1)) -> Yasmine Martin | T4: =TRIM(MID(RawSalesTable[[#This Row],[Customer_Info]],FIND(",",RawSalesTable[[#This Row],[Customer_Info]])+1,FIND(",",RawSalesTable[[#This Row],[Customer_Info]],FIND(",",RawSalesTable[[#This Row],[Customer_Info]])+1)-FIND(",",RawSalesTable[[#This Row],[Customer_Info]])-1)) -> Calgary | U4: =TRIM(RIGHT(RawSalesTable[[#This Row],[Customer_Info]], LEN(RawSalesTable[[#This Row],[Customer_Info]])-FIND(",",RawSalesTable[[#This Row],[Customer_Info]],FIND(",",RawSalesTable[[#This Row],[Customer_Info]])+1))) -> Consumer | V4: =VLOOKUP(RawSalesTable[[#This Row],[Product_ID]],ProductsTable[],2,FALSE) -> Dumbbell Set | W4: =VLOOKUP(RawSalesTable[[#This Row],[Product_ID]],ProductsTable[],3,FALSE) -> Fitness | X4: =VLOOKUP(RawSalesTable[[#This Row],[Product_ID]],ProductsTable[],5,FALSE) -> 131.73 | Y4: =RawSalesTable[[#This Row],[Quantity]]*RawSalesTable[[#This Row],[Unit_Price]] -> 754.47 | Z4: =RawSalesTable[[#This Row],[Gross_Sales]]*RawSalesTable[[#This Row],[Discount_Pct]] -> 113.1705 | AA4: =RawSalesTable[[#This Row],[Gross_Sales]]-RawSalesTable[[#This Row],[Discount_Amount]] -> 641.2995 | AB4: =RawSalesTable[[#This Row],[Unit_Cost]]*RawSalesTable[[#This Row],[Quantity]] -> 395.19 | AC4: =RawSalesTable[[#This Row],[Net_Sales]]-RawSalesTable[[#This Row],[Total_Cost]] -> 246.1095 | AD4: =RawSalesTable[[#This Row],[Profit]]/RawSalesTable[[#This Row],[Net_Sales]] -> 0.38376687 | AE4: =IF(RawSalesTable[[#This Row],[Return_Status]]="Yes",1,0) -> 0 | AF4: =YEAR(RawSalesTable[[#This Row],[Order_Date]]) -> 2025 | AG4: =MONTH(RawSalesTable[[#This Row],[Order_Date]]) -> 9 | AH4: =TEXT(RawSalesTable[[#This Row],[Order_Date]],"mmmm") -> septembre | AI4: =IF(RawSalesTable[[#This Row],[Month_Number]]<=3,"Q1",IF(RawSalesTable[[#This Row],[Month_Number]]<=6,"Q2",IF(RawSalesTable[[#This Row],[Month_Number]]<=9,"Q3","Q4"))) -> Q3 | AJ4: =DATE(YEAR(RawSalesTable[[#This Row],[Order_Date]]),MONTH(RawSalesTable[[#This Row],[Order_Date]]),1) -> 45901 | AK4: =VLOOKUP(RawSalesTable[[#This Row],[Customer_ID_clean]],CustomersTable[],4,FALSE) -> Alberta
A5: ORD-2025-00278 | B5: 45758 | C5: C0041 | D5: P1022 | E5: Amine Chen , Halifax , Small Business | F5: Montreal Central | G5: J. Tremblay | H5: Retail Store | I5: 2 | J5: 405.16 | K5: 0 | L5: Credit Card | M5: 1 | N5: No | O5: =SUBSTITUTE(PROPER(TRIM(RawSalesTable[[#This Row],[Channel_Raw]])), "Market Place", "Marketplace") -> Retail Store | P5: =TRIM(RawSalesTable[[#This Row],[Store_Raw]]) -> Montreal Central | Q5: =IF(TRIM(RawSalesTable[[#This Row],[Payment_Method_Raw]])="","Non renseigné",SUBSTITUTE(TRIM(RawSalesTable[[#This Row],[Payment_Method_Raw]]),"CC","Credit Card")) -> Credit Card | R5: =UPPER(PROPER(RawSalesTable[[#This Row],[Customer_ID]])) -> C0041 | S5: =TRIM(LEFT(RawSalesTable[[#This Row],[Customer_Info]],FIND(",",RawSalesTable[[#This Row],[Customer_Info]]) -1)) -> Amine Chen | T5: =TRIM(MID(RawSalesTable[[#This Row],[Customer_Info]],FIND(",",RawSalesTable[[#This Row],[Customer_Info]])+1,FIND(",",RawSalesTable[[#This Row],[Customer_Info]],FIND(",",RawSalesTable[[#This Row],[Customer_Info]])+1)-FIND(",",RawSalesTable[[#This Row],[Customer_Info]])-1)) -> Halifax | U5: =TRIM(RIGHT(RawSalesTable[[#This Row],[Customer_Info]], LEN(RawSalesTable[[#This Row],[Customer_Info]])-FIND(",",RawSalesTable[[#This Row],[Customer_Info]],FIND(",",RawSalesTable[[#This Row],[Customer_Info]])+1))) -> Small Business | V5: =VLOOKUP(RawSalesTable[[#This Row],[Product_ID]],ProductsTable[],2,FALSE) -> Humidifier | W5: =VLOOKUP(RawSalesTable[[#This Row],[Product_ID]],ProductsTable[],3,FALSE) -> Home | X5: =VLOOKUP(RawSalesTable[[#This Row],[Product_ID]],ProductsTable[],5,FALSE) -> 239.67 | Y5: =RawSalesTable[[#This Row],[Quantity]]*RawSalesTable[[#This Row],[Unit_Price]] -> 810.32 | Z5: =RawSalesTable[[#This Row],[Gross_Sales]]*RawSalesTable[[#This Row],[Discount_Pct]] -> 0 | AA5: =RawSalesTable[[#This Row],[Gross_Sales]]-RawSalesTable[[#This Row],[Discount_Amount]] -> 810.32 | AB5: =RawSalesTable[[#This Row],[Unit_Cost]]*RawSalesTable[[#This Row],[Quantity]] -> 479.34 | AC5: =RawSalesTable[[#This Row],[Net_Sales]]-RawSalesTable[[#This Row],[Total_Cost]] -> 330.98 | AD5: =RawSalesTable[[#This Row],[Profit]]/RawSalesTable[[#This Row],[Net_Sales]] -> 0.40845592 | AE5: =IF(RawSalesTable[[#This Row],[Return_Status]]="Yes",1,0) -> 0 | AF5: =YEAR(RawSalesTable[[#This Row],[Order_Date]]) -> 2025 | AG5: =MONTH(RawSalesTable[[#This Row],[Order_Date]]) -> 4 | AH5: =TEXT(RawSalesTable[[#This Row],[Order_Date]],"mmmm") -> avril | AI5: =IF(RawSalesTable[[#This Row],[Month_Number]]<=3,"Q1",IF(RawSalesTable[[#This Row],[Month_Number]]<=6,"Q2",IF(RawSalesTable[[#This Row],[Month_Number]]<=9,"Q3","Q4"))) -> Q2 | AJ5: =DATE(YEAR(RawSalesTable[[#This Row],[Order_Date]]),MONTH(RawSalesTable[[#This Row],[Order_Date]]),1) -> 45748 | AK5: =VLOOKUP(RawSalesTable[[#This Row],[Customer_ID_clean]],CustomersTable[],4,FALSE) -> Nova Scotia
A6: ORD-2025-00308 | B6: 45995 | C6: C0091 | D6: P1039 | E6: Leo Taylor, Victoria, Small Business | F6: Montreal Central | G6: A. Morgan | H6: Online | I6: 1 | J6: 341.39 | K6: 0 | M6: 4 | N6: No | O6: =SUBSTITUTE(PROPER(TRIM(RawSalesTable[[#This Row],[Channel_Raw]])), "Market Place", "Marketplace") -> Online | P6: =TRIM(RawSalesTable[[#This Row],[Store_Raw]]) -> Montreal Central | Q6: =IF(TRIM(RawSalesTable[[#This Row],[Payment_Method_Raw]])="","Non renseigné",SUBSTITUTE(TRIM(RawSalesTable[[#This Row],[Payment_Method_Raw]]),"CC","Credit Card")) -> Non renseigné | R6: =UPPER(PROPER(RawSalesTable[[#This Row],[Customer_ID]])) -> C0091 | S6: =TRIM(LEFT(RawSalesTable[[#This Row],[Customer_Info]],FIND(",",RawSalesTable[[#This Row],[Customer_Info]]) -1)) -> Leo Taylor | T6: =TRIM(MID(RawSalesTable[[#This Row],[Customer_Info]],FIND(",",RawSalesTable[[#This Row],[Customer_Info]])+1,FIND(",",RawSalesTable[[#This Row],[Customer_Info]],FIND(",",RawSalesTable[[#This Row],[Customer_Info]])+1)-FIND(",",RawSalesTable[[#This Row],[Customer_Info]])-1)) -> Victoria | U6: =TRIM(RIGHT(RawSalesTable[[#This Row],[Customer_Info]], LEN(RawSalesTable[[#This Row],[Customer_Info]])-FIND(",",RawSalesTable[[#This Row],[Customer_Info]],FIND(",",RawSalesTable[[#This Row],[Customer_Info]])+1))) -> Small Business | V6: =VLOOKUP(RawSalesTable[[#This Row],[Product_ID]],ProductsTable[],2,FALSE) -> Travel Adapter | W6: =VLOOKUP(RawSalesTable[[#This Row],[Product_ID]],ProductsTable[],3,FALSE) -> Accessories | X6: =VLOOKUP(RawSalesTable[[#This Row],[Product_ID]],ProductsTable[],5,FALSE) -> 229.86 | Y6: =RawSalesTable[[#This Row],[Quantity]]*RawSalesTable[[#This Row],[Unit_Price]] -> 341.39 | Z6: =RawSalesTable[[#This Row],[Gross_Sales]]*RawSalesTable[[#This Row],[Discount_Pct]] -> 0 | AA6: =RawSalesTable[[#This Row],[Gross_Sales]]-RawSalesTable[[#This Row],[Discount_Amount]] -> 341.39 | AB6: =RawSalesTable[[#This Row],[Unit_Cost]]*RawSalesTable[[#This Row],[Quantity]] -> 229.86 | AC6: =RawSalesTable[[#This Row],[Net_Sales]]-RawSalesTable[[#This Row],[Total_Cost]] -> 111.53 | AD6: =RawSalesTable[[#This Row],[Profit]]/RawSalesTable[[#This Row],[Net_Sales]] -> 0.32669381 | AE6: =IF(RawSalesTable[[#This Row],[Return_Status]]="Yes",1,0) -> 0 | AF6: =YEAR(RawSalesTable[[#This Row],[Order_Date]]) -> 2025 | AG6: =MONTH(RawSalesTable[[#This Row],[Order_Date]]) -> 12 | AH6: =TEXT(RawSalesTable[[#This Row],[Order_Date]],"mmmm") -> décembre | AI6: =IF(RawSalesTable[[#This Row],[Month_Number]]<=3,"Q1",IF(RawSalesTable[[#This Row],[Month_Number]]<=6,"Q2",IF(RawSalesTable[[#This Row],[Month_Number]]<=9,"Q3","Q4"))) -> Q4 | AJ6: =DATE(YEAR(RawSalesTable[[#This Row],[Order_Date]]),MONTH(RawSalesTable[[#This Row],[Order_Date]]),1) -> 45992 | AK6: =VLOOKUP(RawSalesTable[[#This Row],[Customer_ID_clean]],CustomersTable[],4,FALSE) -> British Columbia
A7: ORD-2025-00464 | B7: 45781 | C7: C0047 | D7: P1038 | E7: Amine King, Victoria, Consumer | F7: Montreal Central | G7: E. Roy | H7: Retail Store | I7: 1 | J7: 273.39 | K7: 0.1 | L7: PayPal | M7: 3 | N7: No | O7: =SUBSTITUTE(PROPER(TRIM(RawSalesTable[[#This Row],[Channel_Raw]])), "Market Place", "Marketplace") -> Retail Store | P7: =TRIM(RawSalesTable[[#This Row],[Store_Raw]]) -> Montreal Central | Q7: =IF(TRIM(RawSalesTable[[#This Row],[Payment_Method_Raw]])="","Non renseigné",SUBSTITUTE(TRIM(RawSalesTable[[#This Row],[Payment_Method_Raw]]),"CC","Credit Card")) -> PayPal | R7: =UPPER(PROPER(RawSalesTable[[#This Row],[Customer_ID]])) -> C0047 | S7: =TRIM(LEFT(RawSalesTable[[#This Row],[Customer_Info]],FIND(",",RawSalesTable[[#This Row],[Customer_Info]]) -1)) -> Amine King | T7: =TRIM(MID(RawSalesTable[[#This Row],[Customer_Info]],FIND(",",RawSalesTable[[#This Row],[Customer_Info]])+1,FIND(",",RawSalesTable[[#This Row],[Customer_Info]],FIND(",",RawSalesTable[[#This Row],[Customer_Info]])+1)-FIND(",",RawSalesTable[[#This Row],[Customer_Info]])-1)) -> Victoria | U7: =TRIM(RIGHT(RawSalesTable[[#This Row],[Customer_Info]], LEN(RawSalesTable[[#This Row],[Customer_Info]])-FIND(",",RawSalesTable[[#This Row],[Customer_Info]],FIND(",",RawSalesTable[[#This Row],[Customer_Info]])+1))) -> Consumer | V7: =VLOOKUP(RawSalesTable[[#This Row],[Product_ID]],ProductsTable[],2,FALSE) -> Water Bottle | W7: =VLOOKUP(RawSalesTable[[#This Row],[Product_ID]],ProductsTable[],3,FALSE) -> Accessories | X7: =VLOOKUP(RawSalesTable[[#This Row],[Product_ID]],ProductsTable[],5,FALSE) -> 119.16 | Y7: =RawSalesTable[[#This Row],[Quantity]]*RawSalesTable[[#This Row],[Unit_Price]] -> 273.39 | Z7: =RawSalesTable[[#This Row],[Gross_Sales]]*RawSalesTable[[#This Row],[Discount_Pct]] -> 27.339 | AA7: =RawSalesTable[[#This Row],[Gross_Sales]]-RawSalesTable[[#This Row],[Discount_Amount]] -> 246.051 | AB7: =RawSalesTable[[#This Row],[Unit_Cost]]*RawSalesTable[[#This Row],[Quantity]] -> 119.16 | AC7: =RawSalesTable[[#This Row],[Net_Sales]]-RawSalesTable[[#This Row],[Total_Cost]] -> 126.891 | AD7: =RawSalesTable[[#This Row],[Profit]]/RawSalesTable[[#This Row],[Net_Sales]] -> 0.51571016 | AE7: =IF(RawSalesTable[[#This Row],[Return_Status]]="Yes",1,0) -> 0 | AF7: =YEAR(RawSalesTable[[#This Row],[Order_Date]]) -> 2025 | AG7: =MONTH(RawSalesTable[[#This Row],[Order_Date]]) -> 5 | AH7: =TEXT(RawSalesTable[[#This Row],[Order_Date]],"mmmm") -> mai | AI7: =IF(RawSalesTable[[#This Row],[Month_Number]]<=3,"Q1",IF(RawSalesTable[[#This Row],[Month_Number]]<=6,"Q2",IF(RawSalesTable[[#This Row],[Month_Number]]<=9,"Q3","Q4"))) -> Q2 | AJ7: =DATE(YEAR(RawSalesTable[[#This Row],[Order_Date]]),MONTH(RawSalesTable[[#This Row],[Order_Date]]),1) -> 45778 | AK7: =VLOOKUP(RawSalesTable[[#This Row],[Customer_ID_clean]],CustomersTable[],4,FALSE) -> British Columbia
A8: ORD-2025-00521 | B8: 45993 | C8: C0059 | D8: P1022 | E8: Lucas Chen, Vancouver, Corporate | F8: Online Fulfillment | G8: A. Morgan | H8: Online | I8: 2 | J8: 416.28 | K8: 0 | L8: PayPal | M8: 9 | N8: No | O8: =SUBSTITUTE(PROPER(TRIM(RawSalesTable[[#This Row],[Channel_Raw]])), "Market Place", "Marketplace") -> Online | P8: =TRIM(RawSalesTable[[#This Row],[Store_Raw]]) -> Online Fulfillment | Q8: =IF(TRIM(RawSalesTable[[#This Row],[Payment_Method_Raw]])="","Non renseigné",SUBSTITUTE(TRIM(RawSalesTable[[#This Row],[Payment_Method_Raw]]),"CC","Credit Card")) -> PayPal | R8: =UPPER(PROPER(RawSalesTable[[#This Row],[Customer_ID]])) -> C0059 | S8: =TRIM(LEFT(RawSalesTable[[#This Row],[Customer_Info]],FIND(",",RawSalesTable[[#This Row],[Customer_Info]]) -1)) -> Lucas Chen | T8: =TRIM(MID(RawSalesTable[[#This Row],[Customer_Info]],FIND(",",RawSalesTable[[#This Row],[Customer_Info]])+1,FIND(",",RawSalesTable[[#This Row],[Customer_Info]],FIND(",",RawSalesTable[[#This Row],[Customer_Info]])+1)-FIND(",",RawSalesTable[[#This Row],[Customer_Info]])-1)) -> Vancouver | U8: =TRIM(RIGHT(RawSalesTable[[#This Row],[Customer_Info]], LEN(RawSalesTable[[#This Row],[Customer_Info]])-FIND(",",RawSalesTable[[#This Row],[Customer_Info]],FIND(",",RawSalesTable[[#This Row],[Customer_Info]])+1))) -> Corporate | V8: =VLOOKUP(RawSalesTable[[#This Row],[Product_ID]],ProductsTable[],2,FALSE) -> Humidifier | W8: =VLOOKUP(RawSalesTable[[#This Row],[Product_ID]],ProductsTable[],3,FALSE) -> Home | X8: =VLOOKUP(RawSalesTable[[#This Row],[Product_ID]],ProductsTable[],5,FALSE) -> 239.67 | Y8: =RawSalesTable[[#This Row],[Quantity]]*RawSalesTable[[#This Row],[Unit_Price]] -> 832.56 | Z8: =RawSalesTable[[#This Row],[Gross_Sales]]*RawSalesTable[[#This Row],[Discount_Pct]] -> 0 | AA8: =RawSalesTable[[#This Row],[Gross_Sales]]-RawSalesTable[[#This Row],[Discount_Amount]] -> 832.56 | AB8: =RawSalesTable[[#This Row],[Unit_Cost]]*RawSalesTable[[#This Row],[Quantity]] -> 479.34 | AC8: =RawSalesTable[[#This Row],[Net_Sales]]-RawSalesTable[[#This Row],[Total_Cost]] -> 353.22 | AD8: =RawSalesTable[[#This Row],[Profit]]/RawSalesTable[[#This Row],[Net_Sales]] -> 0.42425771 | AE8: =IF(RawSalesTable[[#This Row],[Return_Status]]="Yes",1,0) -> 0 | AF8: =YEAR(RawSalesTable[[#This Row],[Order_Date]]) -> 2025 | AG8: =MONTH(RawSalesTable[[#This Row],[Order_Date]]) -> 12 | AH8: =TEXT(RawSalesTable[[#This Row],[Order_Date]],"mmmm") -> décembre | AI8: =IF(RawSalesTable[[#This Row],[Month_Number]]<=3,"Q1",IF(RawSalesTable[[#This Row],[Month_Number]]<=6,"Q2",IF(RawSalesTable[[#This Row],[Month_Number]]<=9,"Q3","Q4"))) -> Q4 | AJ8: =DATE(YEAR(RawSalesTable[[#This Row],[Order_Date]]),MONTH(RawSalesTable[[#This Row],[Order_Date]]),1) -> 45992 | AK8: =VLOOKUP(RawSalesTable[[#This Row],[Customer_ID_clean]],CustomersTable[],4,FALSE) -> British Columbia
A9: ORD-2025-00536 | B9: 45669 | C9: C0051 | D9: P1037 | E9: Daniel Brown, Vancouver, Small Business | F9: Vancouver West | G9: J. Tremblay | H9: Online | I9: 2 | J9: 370.98 | K9: 0.15 | L9: Credit Card | M9: 5 | N9: No | O9: =SUBSTITUTE(PROPER(TRIM(RawSalesTable[[#This Row],[Channel_Raw]])), "Market Place", "Marketplace") -> Online | P9: =TRIM(RawSalesTable[[#This Row],[Store_Raw]]) -> Vancouver West | Q9: =IF(TRIM(RawSalesTable[[#This Row],[Payment_Method_Raw]])="","Non renseigné",SUBSTITUTE(TRIM(RawSalesTable[[#This Row],[Payment_Method_Raw]]),"CC","Credit Card")) -> Credit Card | R9: =UPPER(PROPER(RawSalesTable[[#This Row],[Customer_ID]])) -> C0051 | S9: =TRIM(LEFT(RawSalesTable[[#This Row],[Customer_Info]],FIND(",",RawSalesTable[[#This Row],[Customer_Info]]) -1)) -> Daniel Brown | T9: =TRIM(MID(RawSalesTable[[#This Row],[Customer_Info]],FIND(",",RawSalesTable[[#This Row],[Customer_Info]])+1,FIND(",",RawSalesTable[[#This Row],[Customer_Info]],FIND(",",RawSalesTable[[#This Row],[Customer_Info]])+1)-FIND(",",RawSalesTable[[#This Row],[Customer_Info]])-1)) -> Vancouver | U9: =TRIM(RIGHT(RawSalesTable[[#This Row],[Customer_Info]], LEN(RawSalesTable[[#This Row],[Customer_Info]])-FIND(",",RawSalesTable[[#This Row],[Customer_Info]],FIND(",",RawSalesTable[[#This Row],[Customer_Info]])+1))) -> Small Business | V9: =VLOOKUP(RawSalesTable[[#This Row],[Product_ID]],ProductsTable[],2,FALSE) -> Cable Set | W9: =VLOOKUP(RawSalesTable[[#This Row],[Product_ID]],ProductsTable[],3,FALSE) -> Accessories | X9: =VLOOKUP(RawSalesTable[[#This Row],[Product_ID]],ProductsTable[],5,FALSE) -> 200.16 | Y9: =RawSalesTable[[#This Row],[Quantity]]*RawSalesTable[[#This Row],[Unit_Price]] -> 741.96 | Z9: =RawSalesTable[[#This Row],[Gross_Sales]]*RawSalesTable[[#This Row],[Discount_Pct]] -> 111.294 | AA9: =RawSalesTable[[#This Row],[Gross_Sales]]-RawSalesTable[[#This Row],[Discount_Amount]] -> 630.666 | AB9: =RawSalesTable[[#This Row],[Unit_Cost]]*RawSalesTable[[#This Row],[Quantity]] -> 400.32 | AC9: =RawSalesTable[[#This Row],[Net_Sales]]-RawSalesTable[[#This Row],[Total_Cost]] -> 230.346 | AD9: =RawSalesTable[[#This Row],[Profit]]/RawSalesTable[[#This Row],[Net_Sales]] -> 0.36524246 | AE9: =IF(RawSalesTable[[#This Row],[Return_Status]]="Yes",1,0) -> 0 | AF9: =YEAR(RawSalesTable[[#This Row],[Order_Date]]) -> 2025 | AG9: =MONTH(RawSalesTable[[#This Row],[Order_Date]]) -> 1 | AH9: =TEXT(RawSalesTable[[#This Row],[Order_Date]],"mmmm") -> janvier | AI9: =IF(RawSalesTable[[#This Row],[Month_Number]]<=3,"Q1",IF(RawSalesTable[[#This Row],[Month_Number]]<=6,"Q2",IF(RawSalesTable[[#This Row],[Month_Number]]<=9,"Q3","Q4"))) -> Q1 | AJ9: =DATE(YEAR(RawSalesTable[[#This Row],[Order_Date]]),MONTH(RawSalesTable[[#This Row],[Order_Date]]),1) -> 45658 | AK9: =VLOOKUP(RawSalesTable[[#This Row],[Customer_ID_clean]],CustomersTable[],4,FALSE) -> British Columbia
A10: ORD-2025-00552 | B10: 45684 | C10: C0105 | D10: P1005 | E10: Liam Martin , Calgary , Consumer | F10: Online Fulfillment | G10: S. Patel | H10: Marketplace | I10: 1 | J10: 250.61 | K10: 0 | L10: Debit Card | M10: 2 | N10: No | O10: =SUBSTITUTE(PROPER(TRIM(RawSalesTable[[#This Row],[Channel_Raw]])), "Market Place", "Marketplace") -> Marketplace | P10: =TRIM(RawSalesTable[[#This Row],[Store_Raw]]) -> Online Fulfillment | Q10: =IF(TRIM(RawSalesTable[[#This Row],[Payment_Method_Raw]])="","Non renseigné",SUBSTITUTE(TRIM(RawSalesTable[[#This Row],[Payment_Method_Raw]]),"CC","Credit Card")) -> Debit Card | R10: =UPPER(PROPER(RawSalesTable[[#This Row],[Customer_ID]])) -> C0105 | S10: =TRIM(LEFT(RawSalesTable[[#This Row],[Customer_Info]],FIND(",",RawSalesTable[[#This Row],[Customer_Info]]) -1)) -> Liam Martin | T10: =TRIM(MID(RawSalesTable[[#This Row],[Customer_Info]],FIND(",",RawSalesTable[[#This Row],[Customer_Info]])+1,FIND(",",RawSalesTable[[#This Row],[Customer_Info]],FIND(",",RawSalesTable[[#This Row],[Customer_Info]])+1)-FIND(",",RawSalesTable[[#This Row],[Customer_Info]])-1)) -> Calgary | U10: =TRIM(RIGHT(RawSalesTable[[#This Row],[Customer_Info]], LEN(RawSalesTable[[#This Row],[Customer_Info]])-FIND(",",RawSalesTable[[#This Row],[Customer_Info]],FIND(",",RawSalesTable[[#This Row],[Customer_Info]])+1))) -> Consumer | V10: =VLOOKUP(RawSalesTable[[#This Row],[Product_ID]],ProductsTable[],2,FALSE) -> Portable SSD | W10: =VLOOKUP(RawSalesTable[[#This Row],[Product_ID]],ProductsTable[],3,FALSE) -> Electronics | X10: =VLOOKUP(RawSalesTable[[#This Row],[Product_ID]],ProductsTable[],5,FALSE) -> 131.19 | Y10: =RawSalesTable[[#This Row],[Quantity]]*RawSalesTable[[#This Row],[Unit_Price]] -> 250.61 | Z10: =RawSalesTable[[#This Row],[Gross_Sales]]*RawSalesTable[[#This Row],[Discount_Pct]] -> 0 | AA10: =RawSalesTable[[#This Row],[Gross_Sales]]-RawSalesTable[[#This Row],[Discount_Amount]] -> 250.61 | AB10: =RawSalesTable[[#This Row],[Unit_Cost]]*RawSalesTable[[#This Row],[Quantity]] -> 131.19 | AC10: =RawSalesTable[[#This Row],[Net_Sales]]-RawSalesTable[[#This Row],[Total_Cost]] -> 119.42 | AD10: =RawSalesTable[[#This Row],[Profit]]/RawSalesTable[[#This Row],[Net_Sales]] -> 0.4765173 | AE10: =IF(RawSalesTable[[#This Row],[Return_Status]]="Yes",1,0) -> 0 | AF10: =YEAR(RawSalesTable[[#This Row],[Order_Date]]) -> 2025 | AG10: =MONTH(RawSalesTable[[#This Row],[Order_Date]]) -> 1 | AH10: =TEXT(RawSalesTable[[#This Row],[Order_Date]],"mmmm") -> janvier | AI10: =IF(RawSalesTable[[#This Row],[Month_Number]]<=3,"Q1",IF(RawSalesTable[[#This Row],[Month_Number]]<=6,"Q2",IF(RawSalesTable[[#This Row],[Month_Number]]<=9,"Q3","Q4"))) -> Q1 | AJ10: =DATE(YEAR(RawSalesTable[[#This Row],[Order_Date]]),MONTH(RawSalesTable[[#This Row],[Order_Date]]),1) -> 45658 | AK10: =VLOOKUP(RawSalesTable[[#This Row],[Customer_ID_clean]],CustomersTable[],4,FALSE) -> Alberta
A11: ORD-2025-00572 | B11: 45746 | C11: C0032 | D11: P1021 | E11: Nora Bennett, Surrey, Consumer | F11: Online Fulfillment | G11: E. Roy | H11: Online | I11: 1 | J11: 298.7 | K11: 0 | L11: Debit Card | M11: 6 | N11: No | O11: =SUBSTITUTE(PROPER(TRIM(RawSalesTable[[#This Row],[Channel_Raw]])), "Market Place", "Marketplace") -> Online | P11: =TRIM(RawSalesTable[[#This Row],[Store_Raw]]) -> Online Fulfillment | Q11: =IF(TRIM(RawSalesTable[[#This Row],[Payment_Method_Raw]])="","Non renseigné",SUBSTITUTE(TRIM(RawSalesTable[[#This Row],[Payment_Method_Raw]]),"CC","Credit Card")) -> Debit Card | R11: =UPPER(PROPER(RawSalesTable[[#This Row],[Customer_ID]])) -> C0032 | S11: =TRIM(LEFT(RawSalesTable[[#This Row],[Customer_Info]],FIND(",",RawSalesTable[[#This Row],[Customer_Info]]) -1)) -> Nora Bennett | T11: =TRIM(MID(RawSalesTable[[#This Row],[Customer_Info]],FIND(",",RawSalesTable[[#This Row],[Customer_Info]])+1,FIND(",",RawSalesTable[[#This Row],[Customer_Info]],FIND(",",RawSalesTable[[#This Row],[Customer_Info]])+1)-FIND(",",RawSalesTable[[#This Row],[Customer_Info]])-1)) -> Surrey | U11: =TRIM(RIGHT(RawSalesTable[[#This Row],[Customer_Info]], LEN(RawSalesTable[[#This Row],[Customer_Info]])-FIND(",",RawSalesTable[[#This Row],[Customer_Info]],FIND(",",RawSalesTable[[#This Row],[Customer_Info]])+1))) -> Consumer | V11: =VLOOKUP(RawSalesTable[[#This Row],[Product_ID]],ProductsTable[],2,FALSE) -> Kettle | W11: =VLOOKUP(RawSalesTable[[#This Row],[Product_ID]],ProductsTable[],3,FALSE) -> Home | X11: =VLOOKUP(RawSalesTable[[#This Row],[Product_ID]],ProductsTable[],5,FALSE) -> 139.86 | Y11: =RawSalesTable[[#This Row],[Quantity]]*RawSalesTable[[#This Row],[Unit_Price]] -> 298.7 | Z11: =RawSalesTable[[#This Row],[Gross_Sales]]*RawSalesTable[[#This Row],[Discount_Pct]] -> 0 | AA11: =RawSalesTable[[#This Row],[Gross_Sales]]-RawSalesTable[[#This Row],[Discount_Amount]] -> 298.7 | AB11: =RawSalesTable[[#This Row],[Unit_Cost]]*RawSalesTable[[#This Row],[Quantity]] -> 139.86 | AC11: =RawSalesTable[[#This Row],[Net_Sales]]-RawSalesTable[[#This Row],[Total_Cost]] -> 158.84 | AD11: =RawSalesTable[[#This Row],[Profit]]/RawSalesTable[[#This Row],[Net_Sales]] -> 0.53177101 | AE11: =IF(RawSalesTable[[#This Row],[Return_Status]]="Yes",1,0) -> 0 | AF11: =YEAR(RawSalesTable[[#This Row],[Order_Date]]) -> 2025 | AG11: =MONTH(RawSalesTable[[#This Row],[Order_Date]]) -> 3 | AH11: =TEXT(RawSalesTable[[#This Row],[Order_Date]],"mmmm") -> mars | AI11: =IF(RawSalesTable[[#This Row],[Month_Number]]<=3,"Q1",IF(RawSalesTable[[#This Row],[Month_Number]]<=6,"Q2",IF(RawSalesTable[[#This Row],[Month_Number]]<=9,"Q3","Q4"))) -> Q1 | AJ11: =DATE(YEAR(RawSalesTable[[#This Row],[Order_Date]]),MONTH(RawSalesTable[[#This Row],[Order_Date]]),1) -> 45717 | AK11: =VLOOKUP(RawSalesTable[[#This Row],[Customer_ID_clean]],CustomersTable[],4,FALSE) -> British Columbia
A12: ORD-2025-00643 | B12: 46005 | C12: C0102 | D12: P1001 | E12: Adam Roy , Edmonton , Corporate | F12: Montreal Central | G12: N. Brown | H12: Online | I12: 1 | J12: 379.66 | K12: 0 | L12: PayPal | M12: 5 | N12: No | O12: =SUBSTITUTE(PROPER(TRIM(RawSalesTable[[#This Row],[Channel_Raw]])), "Market Place", "Marketplace") -> Online | P12: =TRIM(RawSalesTable[[#This Row],[Store_Raw]]) -> Montreal Central | Q12: =IF(TRIM(RawSalesTable[[#This Row],[Payment_Method_Raw]])="","Non renseigné",SUBSTITUTE(TRIM(RawSalesTable[[#This Row],[Payment_Method_Raw]]),"CC","Credit Card")) -> PayPal | R12: =UPPER(PROPER(RawSalesTable[[#This Row],[Customer_ID]])) -> C0102 | S12: =TRIM(LEFT(RawSalesTable[[#This Row],[Customer_Info]],FIND(",",RawSalesTable[[#This Row],[Customer_Info]]) -1)) -> Adam Roy | T12: =TRIM(MID(RawSalesTable[[#This Row],[Customer_Info]],FIND(",",RawSalesTable[[#This Row],[Customer_Info]])+1,FIND(",",RawSalesTable[[#This Row],[Customer_Info]],FIND(",",RawSalesTable[[#This Row],[Customer_Info]])+1)-FIND(",",RawSalesTable[[#This Row],[Customer_Info]])-1)) -> Edmonton | U12: =TRIM(RIGHT(RawSalesTable[[#This Row],[Customer_Info]], LEN(RawSalesTable[[#This Row],[Customer_Info]])-FIND(",",RawSalesTable[[#This Row],[Customer_Info]],FIND(",",RawSalesTable[[#This Row],[Customer_Info]])+1))) -> Corporate | V12: =VLOOKUP(RawSalesTable[[#This Row],[Product_ID]],ProductsTable[],2,FALSE) -> Headphones | W12: =VLOOKUP(RawSalesTable[[#This Row],[Product_ID]],ProductsTable[],3,FALSE) -> Electronics | X12: =VLOOKUP(RawSalesTable[[#This Row],[Product_ID]],ProductsTable[],5,FALSE) -> 254.6 | Y12: =RawSalesTable[[#This Row],[Quantity]]*RawSalesTable[[#This Row],[Unit_Price]] -> 379.66 | Z12: =RawSalesTable[[#This Row],[Gross_Sales]]*RawSalesTable[[#This Row],[Discount_Pct]] -> 0 | AA12: =RawSalesTable[[#This Row],[Gross_Sales]]-RawSalesTable[[#This Row],[Discount_Amount]] -> 379.66 | AB12: =RawSalesTable[[#This Row],[Unit_Cost]]*RawSalesTable[[#This Row],[Quantity]] -> 254.6 | AC12: =RawSalesTable[[#This Row],[Net_Sales]]-RawSalesTable[[#This Row],[Total_Cost]] -> 125.06 | AD12: =RawSalesTable[[#This Row],[Profit]]/RawSalesTable[[#This Row],[Net_Sales]] -> 0.32939999 | AE12: =IF(RawSalesTable[[#This Row],[Return_Status]]="Yes",1,0) -> 0 | AF12: =YEAR(RawSalesTable[[#This Row],[Order_Date]]) -> 2025 | AG12: =MONTH(RawSalesTable[[#This Row],[Order_Date]]) -> 12 | AH12: =TEXT(RawSalesTable[[#This Row],[Order_Date]],"mmmm") -> décembre | AI12: =IF(RawSalesTable[[#This Row],[Month_Number]]<=3,"Q1",IF(RawSalesTable[[#This Row],[Month_Number]]<=6,"Q2",IF(RawSalesTable[[#This Row],[Month_Number]]<=9,"Q3","Q4"))) -> Q4 | AJ12: =DATE(YEAR(RawSalesTable[[#This Row],[Order_Date]]),MONTH(RawSalesTable[[#This Row],[Order_Date]]),1) -> 45992 | AK12: =VLOOKUP(RawSalesTable[[#This Row],[Customer_ID_clean]],CustomersTable[],4,FALSE) -> Alberta
A13: ORD-2025-00711 | B13: 45750 | C13: C0006 | D13: P1003 | E13: Nora Wilson, Laval, Consumer | F13: Montreal Central | G13: M. Wilson | H13: Online | I13: 1 | J13: 153 | K13: 0 | L13: PayPal | M13: 6 | N13: No | O13: =SUBSTITUTE(PROPER(TRIM(RawSalesTable[[#This Row],[Channel_Raw]])), "Market Place", "Marketplace") -> Online | P13: =TRIM(RawSalesTable[[#This Row],[Store_Raw]]) -> Montreal Central | Q13: =IF(TRIM(RawSalesTable[[#This Row],[Payment_Method_Raw]])="","Non renseigné",SUBSTITUTE(TRIM(RawSalesTable[[#This Row],[Payment_Method_Raw]]),"CC","Credit Card")) -> PayPal | R13: =UPPER(PROPER(RawSalesTable[[#This Row],[Customer_ID]])) -> C0006 | S13: =TRIM(LEFT(RawSalesTable[[#This Row],[Customer_Info]],FIND(",",RawSalesTable[[#This Row],[Customer_Info]]) -1)) -> Nora Wilson | T13: =TRIM(MID(RawSalesTable[[#This Row],[Customer_Info]],FIND(",",RawSalesTable[[#This Row],[Customer_Info]])+1,FIND(",",RawSalesTable[[#This Row],[Customer_Info]],FIND(",",RawSalesTable[[#This Row],[Customer_Info]])+1)-FIND(",",RawSalesTable[[#This Row],[Customer_Info]])-1)) -> Laval | U13: =TRIM(RIGHT(RawSalesTable[[#This Row],[Customer_Info]], LEN(RawSalesTable[[#This Row],[Customer_Info]])-FIND(",",RawSalesTable[[#This Row],[Customer_Info]],FIND(",",RawSalesTable[[#This Row],[Customer_Info]])+1))) -> Consumer | V13: =VLOOKUP(RawSalesTable[[#This Row],[Product_ID]],ProductsTable[],2,FALSE) -> Mouse | W13: =VLOOKUP(RawSalesTable[[#This Row],[Product_ID]],ProductsTable[],3,FALSE) -> Electronics | X13: =VLOOKUP(RawSalesTable[[#This Row],[Product_ID]],ProductsTable[],5,FALSE) -> 106.4 | Y13: =RawSalesTable[[#This Row],[Quantity]]*RawSalesTable[[#This Row],[Unit_Price]] -> 153 | Z13: =RawSalesTable[[#This Row],[Gross_Sales]]*RawSalesTable[[#This Row],[Discount_Pct]] -> 0 | AA13: =RawSalesTable[[#This Row],[Gross_Sales]]-RawSalesTable[[#This Row],[Discount_Amount]] -> 153 | AB13: =RawSalesTable[[#This Row],[Unit_Cost]]*RawSalesTable[[#This Row],[Quantity]] -> 106.4 | AC13: =RawSalesTable[[#This Row],[Net_Sales]]-RawSalesTable[[#This Row],[Total_Cost]] -> 46.6 | AD13: =RawSalesTable[[#This Row],[Profit]]/RawSalesTable[[#This Row],[Net_Sales]] -> 0.30457516 | AE13: =IF(RawSalesTable[[#This Row],[Return_Status]]="Yes",1,0) -> 0 | AF13: =YEAR(RawSalesTable[[#This Row],[Order_Date]]) -> 2025 | AG13: =MONTH(RawSalesTable[[#This Row],[Order_Date]]) -> 4 | AH13: =TEXT(RawSalesTable[[#This Row],[Order_Date]],"mmmm") -> avril | AI13: =IF(RawSalesTable[[#This Row],[Month_Number]]<=3,"Q1",IF(RawSalesTable[[#This Row],[Month_Number]]<=6,"Q2",IF(RawSalesTable[[#This Row],[Month_Number]]<=9,"Q3","Q4"))) -> Q2 | AJ13: =DATE(YEAR(RawSalesTable[[#This Row],[Order_Date]]),MONTH(RawSalesTable[[#This Row],[Order_Date]]),1) -> 45748 | AK13: =VLOOKUP(RawSalesTable[[#This Row],[Customer_ID_clean]],CustomersTable[],4,FALSE) -> Quebec
A14: ORD-2025-00001 | B14: 45921 | C14: C0113 | D14: P1025 | E14: Olivia Johnson, Surrey, Consumer | F14: Online Fulfillment | G14: J. Tremblay | H14: Online | I14: 1 | J14: 321.89 | K14: 0 | L14: PayPal | M14: 1 | N14: No | O14: =SUBSTITUTE(PROPER(TRIM(RawSalesTable[[#This Row],[Channel_Raw]])), "Market Place", "Marketplace") -> Online | P14: =TRIM(RawSalesTable[[#This Row],[Store_Raw]]) -> Online Fulfillment | Q14: =IF(TRIM(RawSalesTable[[#This Row],[Payment_Method_Raw]])="","Non renseigné",SUBSTITUTE(TRIM(RawSalesTable[[#This Row],[Payment_Method_Raw]]),"CC","Credit Card")) -> PayPal | R14: =UPPER(PROPER(RawSalesTable[[#This Row],[Customer_ID]])) -> C0113 | S14: =TRIM(LEFT(RawSalesTable[[#This Row],[Customer_Info]],FIND(",",RawSalesTable[[#This Row],[Customer_Info]]) -1)) -> Olivia Johnson | T14: =TRIM(MID(RawSalesTable[[#This Row],[Customer_Info]],FIND(",",RawSalesTable[[#This Row],[Customer_Info]])+1,FIND(",",RawSalesTable[[#This Row],[Customer_Info]],FIND(",",RawSalesTable[[#This Row],[Customer_Info]])+1)-FIND(",",RawSalesTable[[#This Row],[Customer_Info]])-1)) -> Surrey | U14: =TRIM(RIGHT(RawSalesTable[[#This Row],[Customer_Info]], LEN(RawSalesTable[[#This Row],[Customer_Info]])-FIND(",",RawSalesTable[[#This Row],[Customer_Info]],FIND(",",RawSalesTable[[#This Row],[Customer_Info]])+1))) -> Consumer | V14: =VLOOKUP(RawSalesTable[[#This Row],[Product_ID]],ProductsTable[],2,FALSE) -> Yoga Mat | W14: =VLOOKUP(RawSalesTable[[#This Row],[Product_ID]],ProductsTable[],3,FALSE) -> Fitness | X14: =VLOOKUP(RawSalesTable[[#This Row],[Product_ID]],ProductsTable[],5,FALSE) -> 197.33 | Y14: =RawSalesTable[[#This Row],[Quantity]]*RawSalesTable[[#This Row],[Unit_Price]] -> 321.89 | Z14: =RawSalesTable[[#This Row],[Gross_Sales]]*RawSalesTable[[#This Row],[Discount_Pct]] -> 0 | AA14: =RawSalesTable[[#This Row],[Gross_Sales]]-RawSalesTable[[#This Row],[Discount_Amount]] -> 321.89 | AB14: =RawSalesTable[[#This Row],[Unit_Cost]]*RawSalesTable[[#This Row],[Quantity]] -> 197.33 | AC14: =RawSalesTable[[#This Row],[Net_Sales]]-RawSalesTable[[#This Row],[Total_Cost]] -> 124.56 | AD14: =RawSalesTable[[#This Row],[Profit]]/RawSalesTable[[#This Row],[Net_Sales]] -> 0.38696449 | AE14: =IF(RawSalesTable[[#This Row],[Return_Status]]="Yes",1,0) -> 0 | AF14: =YEAR(RawSalesTable[[#This Row],[Order_Date]]) -> 2025 | AG14: =MONTH(RawSalesTable[[#This Row],[Order_Date]]) -> 9 | AH14: =TEXT(RawSalesTable[[#This Row],[Order_Date]],"mmmm") -> septembre | AI14: =IF(RawSalesTable[[#This Row],[Month_Number]]<=3,"Q1",IF(RawSalesTable[[#This Row],[Month_Number]]<=6,"Q2",IF(RawSalesTable[[#This Row],[Month_Number]]<=9,"Q3","Q4"))) -> Q3 | AJ14: =DATE(YEAR(RawSalesTable[[#This Row],[Order_Date]]),MONTH(RawSalesTable[[#This Row],[Order_Date]]),1) -> 45901 | AK14: =VLOOKUP(RawSalesTable[[#This Row],[Customer_ID_clean]],CustomersTable[],4,FALSE) -> British Columbia
A15: ORD-2025-00002 | B15: 45801 | C15: C0084 | D15: P1033 | E15: Ryan Clark, Montreal, Corporate | F15: Online Fulfillment | G15: L. Chen | H15: Retail Store | I15: 4 | J15: 316.17 | K15: 0.15 | L15: Debit Card | M15: 3 | N15: No | O15: =SUBSTITUTE(PROPER(TRIM(RawSalesTable[[#This Row],[Channel_Raw]])), "Market Place", "Marketplace") -> Retail Store | P15: =TRIM(RawSalesTable[[#This Row],[Store_Raw]]) -> Online Fulfillment | Q15: =IF(TRIM(RawSalesTable[[#This Row],[Payment_Method_Raw]])="","Non renseigné",SUBSTITUTE(TRIM(RawSalesTable[[#This Row],[Payment_Method_Raw]]),"CC","Credit Card")) -> Debit Card | R15: =UPPER(PROPER(RawSalesTable[[#This Row],[Customer_ID]])) -> C0084 | S15: =TRIM(LEFT(RawSalesTable[[#This Row],[Customer_Info]],FIND(",",RawSalesTable[[#This Row],[Customer_Info]]) -1)) -> Ryan Clark | T15: =TRIM(MID(RawSalesTable[[#This Row],[Customer_Info]],FIND(",",RawSalesTable[[#This Row],[Customer_Info]])+1,FIND(",",RawSalesTable[[#This Row],[Customer_Info]],FIND(",",RawSalesTable[[#This Row],[Customer_Info]])+1)-FIND(",",RawSalesTable[[#This Row],[Customer_Info]])-1)) -> Montreal | U15: =TRIM(RIGHT(RawSalesTable[[#This Row],[Customer_Info]], LEN(RawSalesTable[[#This Row],[Customer_Info]])-FIND(",",RawSalesTable[[#This Row],[Customer_Info]],FIND(",",RawSalesTable[[#This Row],[Customer_Info]])+1))) -> Corporate | V15: =VLOOKUP(RawSalesTable[[#This Row],[Product_ID]],ProductsTable[],2,FALSE) -> Backpack | W15: =VLOOKUP(RawSalesTable[[#This Row],[Product_ID]],ProductsTable[],3,FALSE) -> Accessories | X15: =VLOOKUP(RawSalesTable[[#This Row],[Product_ID]],ProductsTable[],5,FALSE) -> 152.55 | Y15: =RawSalesTable[[#This Row],[Quantity]]*RawSalesTable[[#This Row],[Unit_Price]] -> 1264.68 | Z15: =RawSalesTable[[#This Row],[Gross_Sales]]*RawSalesTable[[#This Row],[Discount_Pct]] -> 189.702 | AA15: =RawSalesTable[[#This Row],[Gross_Sales]]-RawSalesTable[[#This Row],[Discount_Amount]] -> 1074.978 | AB15: =RawSalesTable[[#This Row],[Unit_Cost]]*RawSalesTable[[#This Row],[Quantity]] -> 610.2 | AC15: =RawSalesTable[[#This Row],[Net_Sales]]-RawSalesTable[[#This Row],[Total_Cost]] -> 464.778 | AD15: =RawSalesTable[[#This Row],[Profit]]/RawSalesTable[[#This Row],[Net_Sales]] -> 0.43236048 | AE15: =IF(RawSalesTable[[#This Row],[Return_Status]]="Yes",1,0) -> 0 | AF15: =YEAR(RawSalesTable[[#This Row],[Order_Date]]) -> 2025 | AG15: =MONTH(RawSalesTable[[#This Row],[Order_Date]]) -> 5 | AH15: =TEXT(RawSalesTable[[#This Row],[Order_Date]],"mmmm") -> mai | AI15: =IF(RawSalesTable[[#This Row],[Month_Number]]<=3,"Q1",IF(RawSalesTable[[#This Row],[Month_Number]]<=6,"Q2",IF(RawSalesTable[[#This Row],[Month_Number]]<=9,"Q3","Q4"))) -> Q2 | AJ15: =DATE(YEAR(RawSalesTable[[#This Row],[Order_Date]]),MONTH(RawSalesTable[[#This Row],[Order_Date]]),1) -> 45778 | AK15: =VLOOKUP(RawSalesTable[[#This Row],[Customer_ID_clean]],CustomersTable[],4,FALSE) -> Quebec
A16: ORD-2025-00003 | B16: 45694 | C16: C0003 | D16: P1021 | E16: Amelia Young, Ottawa, Corporate | F16: Vancouver West | G16: N. Brown | H16: Marketplace | I16: 2 | J16: 302.17 | K16: 0 | L16: Credit Card | M16: 7 | N16: No | O16: =SUBSTITUTE(PROPER(TRIM(RawSalesTable[[#This Row],[Channel_Raw]])), "Market Place", "Marketplace") -> Marketplace | P16: =TRIM(RawSalesTable[[#This Row],[Store_Raw]]) -> Vancouver West | Q16: =IF(TRIM(RawSalesTable[[#This Row],[Payment_Method_Raw]])="","Non renseigné",SUBSTITUTE(TRIM(RawSalesTable[[#This Row],[Payment_Method_Raw]]),"CC","Credit Card")) -> Credit Card | R16: =UPPER(PROPER(RawSalesTable[[#This Row],[Customer_ID]])) -> C0003 | S16: =TRIM(LEFT(RawSalesTable[[#This Row],[Customer_Info]],FIND(",",RawSalesTable[[#This Row],[Customer_Info]]) -1)) -> Amelia Young | T16: =TRIM(MID(RawSalesTable[[#This Row],[Customer_Info]],FIND(",",RawSalesTable[[#This Row],[Customer_Info]])+1,FIND(",",RawSalesTable[[#This Row],[Customer_Info]],FIND(",",RawSalesTable[[#This Row],[Customer_Info]])+1)-FIND(",",RawSalesTable[[#This Row],[Customer_Info]])-1)) -> Ottawa | U16: =TRIM(RIGHT(RawSalesTable[[#This Row],[Customer_Info]], LEN(RawSalesTable[[#This Row],[Customer_Info]])-FIND(",",RawSalesTable[[#This Row],[Customer_Info]],FIND(",",RawSalesTable[[#This Row],[Customer_Info]])+1))) -> Corporate | V16: =VLOOKUP(RawSalesTable[[#This Row],[Product_ID]],ProductsTable[],2,FALSE) -> Kettle | W16: =VLOOKUP(RawSalesTable[[#This Row],[Product_ID]],ProductsTable[],3,FALSE) -> Home | X16: =VLOOKUP(RawSalesTable[[#This Row],[Product_ID]],ProductsTable[],5,FALSE) -> 139.86 | Y16: =RawSalesTable[[#This Row],[Quantity]]*RawSalesTable[[#This Row],[Unit_Price]] -> 604.34 | Z16: =RawSalesTable[[#This Row],[Gross_Sales]]*RawSalesTable[[#This Row],[Discount_Pct]] -> 0 | AA16: =RawSalesTable[[#This Row],[Gross_Sales]]-RawSalesTable[[#This Row],[Discount_Amount]] -> 604.34 | AB16: =RawSalesTable[[#This Row],[Unit_Cost]]*RawSalesTable[[#This Row],[Quantity]] -> 279.72 | AC16: =RawSalesTable[[#This Row],[Net_Sales]]-RawSalesTable[[#This Row],[Total_Cost]] -> 324.62 | AD16: =RawSalesTable[[#This Row],[Profit]]/RawSalesTable[[#This Row],[Net_Sales]] -> 0.53714796 | AE16: =IF(RawSalesTable[[#This Row],[Return_Status]]="Yes",1,0) -> 0 | AF16: =YEAR(RawSalesTable[[#This Row],[Order_Date]]) -> 2025 | AG16: =MONTH(RawSalesTable[[#This Row],[Order_Date]]) -> 2 | AH16: =TEXT(RawSalesTable[[#This Row],[Order_Date]],"mmmm") -> février | AI16: =IF(RawSalesTable[[#This Row],[Month_Number]]<=3,"Q1",IF(RawSalesTable[[#This Row],[Month_Number]]<=6,"Q2",IF(RawSalesTable[[#This Row],[Month_Number]]<=9,"Q3","Q4"))) -> Q1 | AJ16: =DATE(YEAR(RawSalesTable[[#This Row],[Order_Date]]),MONTH(RawSalesTable[[#This Row],[Order_Date]]),1) -> 45689 | AK16: =VLOOKUP(RawSalesTable[[#This Row],[Customer_ID_clean]],CustomersTable[],4,FALSE) -> Ontario
A17: ORD-2025-00004 | B17: 45687 | C17: C0071 | D17: P1032 | E17: Ethan Lee, Surrey, Consumer | F17: Montreal Central | G17: J. Tremblay | H17: Online | I17: 1 | J17: 197.68 | K17: 0.1 | L17: PayPal | M17: 3 | N17: No | O17: =SUBSTITUTE(PROPER(TRIM(RawSalesTable[[#This Row],[Channel_Raw]])), "Market Place", "Marketplace") -> Online | P17: =TRIM(RawSalesTable[[#This Row],[Store_Raw]]) -> Montreal Central | Q17: =IF(TRIM(RawSalesTable[[#This Row],[Payment_Method_Raw]])="","Non renseigné",SUBSTITUTE(TRIM(RawSalesTable[[#This Row],[Payment_Method_Raw]]),"CC","Credit Card")) -> PayPal | R17: =UPPER(PROPER(RawSalesTable[[#This Row],[Customer_ID]])) -> C0071 | S17: =TRIM(LEFT(RawSalesTable[[#This Row],[Customer_Info]],FIND(",",RawSalesTable[[#This Row],[Customer_Info]]) -1)) -> Ethan Lee | T17: =TRIM(MID(RawSalesTable[[#This Row],[Customer_Info]],FIND(",",RawSalesTable[[#This Row],[Customer_Info]])+1,FIND(",",RawSalesTable[[#This Row],[Customer_Info]],FIND(",",RawSalesTable[[#This Row],[Customer_Info]])+1)-FIND(",",RawSalesTable[[#This Row],[Customer_Info]])-1)) -> Surrey | U17: =TRIM(RIGHT(RawSalesTable[[#This Row],[Customer_Info]], LEN(RawSalesTable[[#This Row],[Customer_Info]])-FIND(",",RawSalesTable[[#This Row],[Customer_Info]],FIND(",",RawSalesTable[[#This Row],[Customer_Info]])+1))) -> Consumer | V17: =VLOOKUP(RawSalesTable[[#This Row],[Product_ID]],ProductsTable[],2,FALSE) -> Gym Bag | W17: =VLOOKUP(RawSalesTable[[#This Row],[Product_ID]],ProductsTable[],3,FALSE) -> Fitness | X17: =VLOOKUP(RawSalesTable[[#This Row],[Product_ID]],ProductsTable[],5,FALSE) -> 132.72 | Y17: =RawSalesTable[[#This Row],[Quantity]]*RawSalesTable[[#This Row],[Unit_Price]] -> 197.68 | Z17: =RawSalesTable[[#This Row],[Gross_Sales]]*RawSalesTable[[#This Row],[Discount_Pct]] -> 19.768 | AA17: =RawSalesTable[[#This Row],[Gross_Sales]]-RawSalesTable[[#This Row],[Discount_Amount]] -> 177.912 | AB17: =RawSalesTable[[#This Row],[Unit_Cost]]*RawSalesTable[[#This Row],[Quantity]] -> 132.72 | AC17: =RawSalesTable[[#This Row],[Net_Sales]]-RawSalesTable[[#This Row],[Total_Cost]] -> 45.192 | AD17: =RawSalesTable[[#This Row],[Profit]]/RawSalesTable[[#This Row],[Net_Sales]] -> 0.25401322 | AE17: =IF(RawSalesTable[[#This Row],[Return_Status]]="Yes",1,0) -> 0 | AF17: =YEAR(RawSalesTable[[#This Row],[Order_Date]]) -> 2025 | AG17: =MONTH(RawSalesTable[[#This Row],[Order_Date]]) -> 1 | AH17: =TEXT(RawSalesTable[[#This Row],[Order_Date]],"mmmm") -> janvier | AI17: =IF(RawSalesTable[[#This Row],[Month_Number]]<=3,"Q1",IF(RawSalesTable[[#This Row],[Month_Number]]<=6,"Q2",IF(RawSalesTable[[#This Row],[Month_Number]]<=9,"Q3","Q4"))) -> Q1 | AJ17: =DATE(YEAR(RawSalesTable[[#This Row],[Order_Date]]),MONTH(RawSalesTable[[#This Row],[Order_Date]]),1) -> 45658 | AK17: =VLOOKUP(RawSalesTable[[#This Row],[Customer_ID_clean]],CustomersTable[],4,FALSE) -> British Columbia
A18: ORD-2025-00005 | B18: 45732 | C18: C0083 | D18: P1034 | E18: Amine King, Edmonton, Consumer | F18: Toronto Downtown | G18: A. Morgan | H18: Online | I18: 1 | J18: 151.79 | K18: 0 | L18: Credit Card | M18: 2 | N18: No | O18: =SUBSTITUTE(PROPER(TRIM(RawSalesTable[[#This Row],[Channel_Raw]])), "Market Place", "Marketplace") -> Online | P18: =TRIM(RawSalesTable[[#This Row],[Store_Raw]]) -> Toronto Downtown | Q18: =IF(TRIM(RawSalesTable[[#This Row],[Payment_Method_Raw]])="","Non renseigné",SUBSTITUTE(TRIM(RawSalesTable[[#This Row],[Payment_Method_Raw]]),"CC","Credit Card")) -> Credit Card | R18: =UPPER(PROPER(RawSalesTable[[#This Row],[Customer_ID]])) -> C0083 | S18: =TRIM(LEFT(RawSalesTable[[#This Row],[Customer_Info]],FIND(",",RawSalesTable[[#This Row],[Customer_Info]]) -1)) -> Amine King | T18: =TRIM(MID(RawSalesTable[[#This Row],[Customer_Info]],FIND(",",RawSalesTable[[#This Row],[Customer_Info]])+1,FIND(",",RawSalesTable[[#This Row],[Customer_Info]],FIND(",",RawSalesTable[[#This Row],[Customer_Info]])+1)-FIND(",",RawSalesTable[[#This Row],[Customer_Info]])-1)) -> Edmonton | U18: =TRIM(RIGHT(RawSalesTable[[#This Row],[Customer_Info]], LEN(RawSalesTable[[#This Row],[Customer_Info]])-FIND(",",RawSalesTable[[#This Row],[Customer_Info]],FIND(",",RawSalesTable[[#This Row],[Customer_Info]])+1))) -> Consumer | V18: =VLOOKUP(RawSalesTable[[#This Row],[Product_ID]],ProductsTable[],2,FALSE) -> Laptop Sleeve | W18: =VLOOKUP(RawSalesTable[[#This Row],[Product_ID]],ProductsTable[],3,FALSE) -> Accessories | X18: =VLOOKUP(RawSalesTable[[#This Row],[Product_ID]],ProductsTable[],5,FALSE) -> 78.95 | Y18: =RawSalesTable[[#This Row],[Quantity]]*RawSalesTable[[#This Row],[Unit_Price]] -> 151.79 | Z18: =RawSalesTable[[#This Row],[Gross_Sales]]*RawSalesTable[[#This Row],[Discount_Pct]] -> 0 | AA18: =RawSalesTable[[#This Row],[Gross_Sales]]-RawSalesTable[[#This Row],[Discount_Amount]] -> 151.79 | AB18: =RawSalesTable[[#This Row],[Unit_Cost]]*RawSalesTable[[#This Row],[Quantity]] -> 78.95 | AC18: =RawSalesTable[[#This Row],[Net_Sales]]-RawSalesTable[[#This Row],[Total_Cost]] -> 72.84 | AD18: =RawSalesTable[[#This Row],[Profit]]/RawSalesTable[[#This Row],[Net_Sales]] -> 0.47987351 | AE18: =IF(RawSalesTable[[#This Row],[Return_Status]]="Yes",1,0) -> 0 | AF18: =YEAR(RawSalesTable[[#This Row],[Order_Date]]) -> 2025 | AG18: =MONTH(RawSalesTable[[#This Row],[Order_Date]]) -> 3 | AH18: =TEXT(RawSalesTable[[#This Row],[Order_Date]],"mmmm") -> mars | AI18: =IF(RawSalesTable[[#This Row],[Month_Number]]<=3,"Q1",IF(RawSalesTable[[#This Row],[Month_Number]]<=6,"Q2",IF(RawSalesTable[[#This Row],[Month_Number]]<=9,"Q3","Q4"))) -> Q1 | AJ18: =DATE(YEAR(RawSalesTable[[#This Row],[Order_Date]]),MONTH(RawSalesTable[[#This Row],[Order_Date]]),1) -> 45717 | AK18: =VLOOKUP(RawSalesTable[[#This Row],[Customer_ID_clean]],CustomersTable[],4,FALSE) -> Alberta
... A81: ORD-2025-00068 | B81: 45968 | C81: C0080 | D81: P1005 | E81: Sarah Smith, Mississauga, Corporate | F81: Toronto Downtown | G81: L. Chen | H81: Retail Store | I81: 2 | J81: 251.66 | K81: 0.15 | L81: Credit Card | M81: 3 | N81: No | O81: =SUBSTITUTE(PROPER(TRIM(RawSalesTable[[#This Row],[Channel_Raw]])), "Market Place", "Marketplace") -> Retail Store | P81: =TRIM(RawSalesTable[[#This Row],[Store_Raw]]) -> Toronto Downtown | Q81: =IF(TRIM(RawSalesTable[[#This Row],[Payment_Method_Raw]])="","Non renseigné",SUBSTITUTE(TRIM(RawSalesTable[[#This Row],[Payment_Method_Raw]]),"CC","Credit Card")) -> Credit Card | R81: =UPPER(PROPER(RawSalesTable[[#This Row],[Customer_ID]])) -> C0080 | S81: =TRIM(LEFT(RawSalesTable[[#This Row],[Customer_Info]],FIND(",",RawSalesTable[[#This Row],[Customer_Info]]) -1)) -> Sarah Smith | T81: =TRIM(MID(RawSalesTable[[#This Row],[Customer_Info]],FIND(",",RawSalesTable[[#This Row],[Customer_Info]])+1,FIND(",",RawSalesTable[[#This Row],[Customer_Info]],FIND(",",RawSalesTable[[#This Row],[Customer_Info]])+1)-FIND(",",RawSalesTable[[#This Row],[Customer_Info]])-1)) -> Mississauga | U81: =TRIM(RIGHT(RawSalesTable[[#This Row],[Customer_Info]], LEN(RawSalesTable[[#This Row],[Customer_Info]])-FIND(",",RawSalesTable[[#This Row],[Customer_Info]],FIND(",",RawSalesTable[[#This Row],[Customer_Info]])+1))) -> Corporate | V81: =VLOOKUP(RawSalesTable[[#This Row],[Product_ID]],ProductsTable[],2,FALSE) -> Portable SSD | W81: =VLOOKUP(RawSalesTable[[#This Row],[Product_ID]],ProductsTable[],3,FALSE) -> Electronics | X81: =VLOOKUP(RawSalesTable[[#This Row],[Product_ID]],ProductsTable[],5,FALSE) -> 131.19 | Y81: =RawSalesTable[[#This Row],[Quantity]]*RawSalesTable[[#This Row],[Unit_Price]] -> 503.32 | Z81: =RawSalesTable[[#This Row],[Gross_Sales]]*RawSalesTable[[#This Row],[Discount_Pct]] -> 75.498 | AA81: =RawSalesTable[[#This Row],[Gross_Sales]]-RawSalesTable[[#This Row],[Discount_Amount]] -> 427.822 | AB81: =RawSalesTable[[#This Row],[Unit_Cost]]*RawSalesTable[[#This Row],[Quantity]] -> 262.38 | AC81: =RawSalesTable[[#This Row],[Net_Sales]]-RawSalesTable[[#This Row],[Total_Cost]] -> 165.442 | AD81: =RawSalesTable[[#This Row],[Profit]]/RawSalesTable[[#This Row],[Net_Sales]] -> 0.38670756 | AE81: =IF(RawSalesTable[[#This Row],[Return_Status]]="Yes",1,0) -> 0 | AF81: =YEAR(RawSalesTable[[#This Row],[Order_Date]]) -> 2025 | AG81: =MONTH(RawSalesTable[[#This Row],[Order_Date]]) -> 11 | AH81: =TEXT(RawSalesTable[[#This Row],[Order_Date]],"mmmm") -> novembre | AI81: =IF(RawSalesTable[[#This Row],[Month_Number]]<=3,"Q1",IF(RawSalesTable[[#This Row],[Month_Number]]<=6,"Q2",IF(RawSalesTable[[#This Row],[Month_Number]]<=9,"Q3","Q4"))) -> Q4 | AJ81: =DATE(YEAR(RawSalesTable[[#This Row],[Order_Date]]),MONTH(RawSalesTable[[#This Row],[Order_Date]]),1) -> 45962 | AK81: =VLOOKUP(RawSalesTable[[#This Row],[Customer_ID_clean]],CustomersTable[],4,FALSE) -> Ontario
A82: ORD-2025-00069 | B82: 45999 | C82: C0075 | D82: P1012 | E82: Amelia Wilson, Vancouver, Consumer | F82: Vancouver West | G82: E. Roy | H82: Retail Store | I82: 2 | J82: 84.65 | K82: 0 | M82: 1 | N82: No | O82: =SUBSTITUTE(PROPER(TRIM(RawSalesTable[[#This Row],[Channel_Raw]])), "Market Place", "Marketplace") -> Retail Store | P82: =TRIM(RawSalesTable[[#This Row],[Store_Raw]]) -> Vancouver West | Q82: =IF(TRIM(RawSalesTable[[#This Row],[Payment_Method_Raw]])="","Non renseigné",SUBSTITUTE(TRIM(RawSalesTable[[#This Row],[Payment_Method_Raw]]),"CC","Credit Card")) -> Non renseigné | R82: =UPPER(PROPER(RawSalesTable[[#This Row],[Customer_ID]])) -> C0075 | S82: =TRIM(LEFT(RawSalesTable[[#This Row],[Customer_Info]],FIND(",",RawSalesTable[[#This Row],[Customer_Info]]) -1)) -> Amelia Wilson | T82: =TRIM(MID(RawSalesTable[[#This Row],[Customer_Info]],FIND(",",RawSalesTable[[#This Row],[Customer_Info]])+1,FIND(",",RawSalesTable[[#This Row],[Customer_Info]],FIND(",",RawSalesTable[[#This Row],[Customer_Info]])+1)-FIND(",",RawSalesTable[[#This Row],[Customer_Info]])-1)) -> Vancouver | U82: =TRIM(RIGHT(RawSalesTable[[#This Row],[Customer_Info]], LEN(RawSalesTable[[#This Row],[Customer_Info]])-FIND(",",RawSalesTable[[#This Row],[Customer_Info]],FIND(",",RawSalesTable[[#This Row],[Customer_Info]])+1))) -> Consumer | V82: =VLOOKUP(RawSalesTable[[#This Row],[Product_ID]],ProductsTable[],2,FALSE) -> Standing Desk | W82: =VLOOKUP(RawSalesTable[[#This Row],[Product_ID]],ProductsTable[],3,FALSE) -> Office | X82: =VLOOKUP(RawSalesTable[[#This Row],[Product_ID]],ProductsTable[],5,FALSE) -> 45.17 | Y82: =RawSalesTable[[#This Row],[Quantity]]*RawSalesTable[[#This Row],[Unit_Price]] -> 169.3 | Z82: =RawSalesTable[[#This Row],[Gross_Sales]]*RawSalesTable[[#This Row],[Discount_Pct]] -> 0 | AA82: =RawSalesTable[[#This Row],[Gross_Sales]]-RawSalesTable[[#This Row],[Discount_Amount]] -> 169.3 | AB82: =RawSalesTable[[#This Row],[Unit_Cost]]*RawSalesTable[[#This Row],[Quantity]] -> 90.34 | AC82: =RawSalesTable[[#This Row],[Net_Sales]]-RawSalesTable[[#This Row],[Total_Cost]] -> 78.96 | AD82: =RawSalesTable[[#This Row],[Profit]]/RawSalesTable[[#This Row],[Net_Sales]] -> 0.46639102 | AE82: =IF(RawSalesTable[[#This Row],[Return_Status]]="Yes",1,0) -> 0 | AF82: =YEAR(RawSalesTable[[#This Row],[Order_Date]]) -> 2025 | AG82: =MONTH(RawSalesTable[[#This Row],[Order_Date]]) -> 12 | AH82: =TEXT(RawSalesTable[[#This Row],[Order_Date]],"mmmm") -> décembre | AI82: =IF(RawSalesTable[[#This Row],[Month_Number]]<=3,"Q1",IF(RawSalesTable[[#This Row],[Month_Number]]<=6,"Q2",IF(RawSalesTable[[#This Row],[Month_Number]]<=9,"Q3","Q4"))) -> Q4 | AJ82: =DATE(YEAR(RawSalesTable[[#This Row],[Order_Date]]),MONTH(RawSalesTable[[#This Row],[Order_Date]]),1) -> 45992 | AK82: =VLOOKUP(RawSalesTable[[#This Row],[Customer_ID_clean]],CustomersTable[],4,FALSE) -> British Columbia
A83: ORD-2025-00070 | B83: 45688 | C83: C0013 | D83: P1022 | E83: Amelia Martin, Quebec City, Small Business | F83: Toronto Downtown | G83: S. Patel | H83: Retail Store | I83: 1 | J83: 434.51 | K83: 0.1 | L83: Debit Card | M83: 3 | N83: No | O83: =SUBSTITUTE(PROPER(TRIM(RawSalesTable[[#This Row],[Channel_Raw]])), "Market Place", "Marketplace") -> Retail Store | P83: =TRIM(RawSalesTable[[#This Row],[Store_Raw]]) -> Toronto Downtown | Q83: =IF(TRIM(RawSalesTable[[#This Row],[Payment_Method_Raw]])="","Non renseigné",SUBSTITUTE(TRIM(RawSalesTable[[#This Row],[Payment_Method_Raw]]),"CC","Credit Card")) -> Debit Card | R83: =UPPER(PROPER(RawSalesTable[[#This Row],[Customer_ID]])) -> C0013 | S83: =TRIM(LEFT(RawSalesTable[[#This Row],[Customer_Info]],FIND(",",RawSalesTable[[#This Row],[Customer_Info]]) -1)) -> Amelia Martin | T83: =TRIM(MID(RawSalesTable[[#This Row],[Customer_Info]],FIND(",",RawSalesTable[[#This Row],[Customer_Info]])+1,FIND(",",RawSalesTable[[#This Row],[Customer_Info]],FIND(",",RawSalesTable[[#This Row],[Customer_Info]])+1)-FIND(",",RawSalesTable[[#This Row],[Customer_Info]])-1)) -> Quebec City | U83: =TRIM(RIGHT(RawSalesTable[[#This Row],[Customer_Info]], LEN(RawSalesTable[[#This Row],[Customer_Info]])-FIND(",",RawSalesTable[[#This Row],[Customer_Info]],FIND(",",RawSalesTable[[#This Row],[Customer_Info]])+1))) -> Small Business | V83: =VLOOKUP(RawSalesTable[[#This Row],[Product_ID]],ProductsTable[],2,FALSE) -> Humidifier | W83: =VLOOKUP(RawSalesTable[[#This Row],[Product_ID]],ProductsTable[],3,FALSE) -> Home | X83: =VLOOKUP(RawSalesTable[[#This Row],[Product_ID]],ProductsTable[],5,FALSE) -> 239.67 | Y83: =RawSalesTable[[#This Row],[Quantity]]*RawSalesTable[[#This Row],[Unit_Price]] -> 434.51 | Z83: =RawSalesTable[[#This Row],[Gross_Sales]]*RawSalesTable[[#This Row],[Discount_Pct]] -> 43.451 | AA83: =RawSalesTable[[#This Row],[Gross_Sales]]-RawSalesTable[[#This Row],[Discount_Amount]] -> 391.059 | AB83: =RawSalesTable[[#This Row],[Unit_Cost]]*RawSalesTable[[#This Row],[Quantity]] -> 239.67 | AC83: =RawSalesTable[[#This Row],[Net_Sales]]-RawSalesTable[[#This Row],[Total_Cost]] -> 151.389 | AD83: =RawSalesTable[[#This Row],[Profit]]/RawSalesTable[[#This Row],[Net_Sales]] -> 0.38712573 | AE83: =IF(RawSalesTable[[#This Row],[Return_Status]]="Yes",1,0) -> 0 | AF83: =YEAR(RawSalesTable[[#This Row],[Order_Date]]) -> 2025 | AG83: =MONTH(RawSalesTable[[#This Row],[Order_Date]]) -> 1 | AH83: =TEXT(RawSalesTable[[#This Row],[Order_Date]],"mmmm") -> janvier | AI83: =IF(RawSalesTable[[#This Row],[Month_Number]]<=3,"Q1",IF(RawSalesTable[[#This Row],[Month_Number]]<=6,"Q2",IF(RawSalesTable[[#This Row],[Month_Number]]<=9,"Q3","Q4"))) -> Q1 | AJ83: =DATE(YEAR(RawSalesTable[[#This Row],[Order_Date]]),MONTH(RawSalesTable[[#This Row],[Order_Date]]),1) -> 45658 | AK83: =VLOOKUP(RawSalesTable[[#This Row],[Customer_ID_clean]],CustomersTable[],4,FALSE) -> Quebec
A84: ORD-2025-00071 | B84: 45963 | C84: C0119 | D84: P1023 | E84: Liam Chen , Winnipeg , Consumer | F84: Montreal Central | G84: A. Morgan | H84: Retail Store | I84: 1 | J84: 351.6 | K84: 0 | L84: Credit Card | M84: 2 | N84: No | O84: =SUBSTITUTE(PROPER(TRIM(RawSalesTable[[#This Row],[Channel_Raw]])), "Market Place", "Marketplace") -> Retail Store | P84: =TRIM(RawSalesTable[[#This Row],[Store_Raw]]) -> Montreal Central | Q84: =IF(TRIM(RawSalesTable[[#This Row],[Payment_Method_Raw]])="","Non renseigné",SUBSTITUTE(TRIM(RawSalesTable[[#This Row],[Payment_Method_Raw]]),"CC","Credit Card")) -> Credit Card | R84: =UPPER(PROPER(RawSalesTable[[#This Row],[Customer_ID]])) -> C0119 | S84: =TRIM(LEFT(RawSalesTable[[#This Row],[Customer_Info]],FIND(",",RawSalesTable[[#This Row],[Customer_Info]]) -1)) -> Liam Chen | T84: =TRIM(MID(RawSalesTable[[#This Row],[Customer_Info]],FIND(",",RawSalesTable[[#This Row],[Customer_Info]])+1,FIND(",",RawSalesTable[[#This Row],[Customer_Info]],FIND(",",RawSalesTable[[#This Row],[Customer_Info]])+1)-FIND(",",RawSalesTable[[#This Row],[Customer_Info]])-1)) -> Winnipeg | U84: =TRIM(RIGHT(RawSalesTable[[#This Row],[Customer_Info]], LEN(RawSalesTable[[#This Row],[Customer_Info]])-FIND(",",RawSalesTable[[#This Row],[Customer_Info]],FIND(",",RawSalesTable[[#This Row],[Customer_Info]])+1))) -> Consumer | V84: =VLOOKUP(RawSalesTable[[#This Row],[Product_ID]],ProductsTable[],2,FALSE) -> Toaster | W84: =VLOOKUP(RawSalesTable[[#This Row],[Product_ID]],ProductsTable[],3,FALSE) -> Home | X84: =VLOOKUP(RawSalesTable[[#This Row],[Product_ID]],ProductsTable[],5,FALSE) -> 152.88 | Y84: =RawSalesTable[[#This Row],[Quantity]]*RawSalesTable[[#This Row],[Unit_Price]] -> 351.6 | Z84: =RawSalesTable[[#This Row],[Gross_Sales]]*RawSalesTable[[#This Row],[Discount_Pct]] -> 0 | AA84: =RawSalesTable[[#This Row],[Gross_Sales]]-RawSalesTable[[#This Row],[Discount_Amount]] -> 351.6 | AB84: =RawSalesTable[[#This Row],[Unit_Cost]]*RawSalesTable[[#This Row],[Quantity]] -> 152.88 | AC84: =RawSalesTable[[#This Row],[Net_Sales]]-RawSalesTable[[#This Row],[Total_Cost]] -> 198.72 | AD84: =RawSalesTable[[#This Row],[Profit]]/RawSalesTable[[#This Row],[Net_Sales]] -> 0.56518771 | AE84: =IF(RawSalesTable[[#This Row],[Return_Status]]="Yes",1,0) -> 0 | AF84: =YEAR(RawSalesTable[[#This Row],[Order_Date]]) -> 2025 | AG84: =MONTH(RawSalesTable[[#This Row],[Order_Date]]) -> 11 | AH84: =TEXT(RawSalesTable[[#This Row],[Order_Date]],"mmmm") -> novembre | AI84: =IF(RawSalesTable[[#This Row],[Month_Number]]<=3,"Q1",IF(RawSalesTable[[#This Row],[Month_Number]]<=6,"Q2",IF(RawSalesTable[[#This Row],[Month_Number]]<=9,"Q3","Q4"))) -> Q4 | AJ84: =DATE(YEAR(RawSalesTable[[#This Row],[Order_Date]]),MONTH(RawSalesTable[[#This Row],[Order_Date]]),1) -> 45962 | AK84: =VLOOKUP(RawSalesTable[[#This Row],[Customer_ID_clean]],CustomersTable[],4,FALSE) -> Manitoba
A85: ORD-2025-00072 | B85: 45712 | C85: C0092 | D85: P1018 | E85: Lucas Tremblay, Saskatoon, Consumer | F85: Vancouver West | G85: S. Patel | H85: Online | I85: 1 | J85: 31.95 | K85: 0 | L85: Credit Card | M85: 9 | N85: No | O85: =SUBSTITUTE(PROPER(TRIM(RawSalesTable[[#This Row],[Channel_Raw]])), "Market Place", "Marketplace") -> Online | P85: =TRIM(RawSalesTable[[#This Row],[Store_Raw]]) -> Vancouver West | Q85: =IF(TRIM(RawSalesTable[[#This Row],[Payment_Method_Raw]])="","Non renseigné",SUBSTITUTE(TRIM(RawSalesTable[[#This Row],[Payment_Method_Raw]]),"CC","Credit Card")) -> Credit Card | R85: =UPPER(PROPER(RawSalesTable[[#This Row],[Customer_ID]])) -> C0092 | S85: =TRIM(LEFT(RawSalesTable[[#This Row],[Customer_Info]],FIND(",",RawSalesTable[[#This Row],[Customer_Info]]) -1)) -> Lucas Tremblay | T85: =TRIM(MID(RawSalesTable[[#This Row],[Customer_Info]],FIND(",",RawSalesTable[[#This Row],[Customer_Info]])+1,FIND(",",RawSalesTable[[#This Row],[Customer_Info]],FIND(",",RawSalesTable[[#This Row],[Customer_Info]])+1)-FIND(",",RawSalesTable[[#This Row],[Customer_Info]])-1)) -> Saskatoon | U85: =TRIM(RIGHT(RawSalesTable[[#This Row],[Customer_Info]], LEN(RawSalesTable[[#This Row],[Customer_Info]])-FIND(",",RawSalesTable[[#This Row],[Customer_Info]],FIND(",",RawSalesTable[[#This Row],[Customer_Info]])+1))) -> Consumer | V85: =VLOOKUP(RawSalesTable[[#This Row],[Product_ID]],ProductsTable[],2,FALSE) -> Air Fryer | W85: =VLOOKUP(RawSalesTable[[#This Row],[Product_ID]],ProductsTable[],3,FALSE) -> Home | X85: =VLOOKUP(RawSalesTable[[#This Row],[Product_ID]],ProductsTable[],5,FALSE) -> 14.58 | Y85: =RawSalesTable[[#This Row],[Quantity]]*RawSalesTable[[#This Row],[Unit_Price]] -> 31.95 | Z85: =RawSalesTable[[#This Row],[Gross_Sales]]*RawSalesTable[[#This Row],[Discount_Pct]] -> 0 | AA85: =RawSalesTable[[#This Row],[Gross_Sales]]-RawSalesTable[[#This Row],[Discount_Amount]] -> 31.95 | AB85: =RawSalesTable[[#This Row],[Unit_Cost]]*RawSalesTable[[#This Row],[Quantity]] -> 14.58 | AC85: =RawSalesTable[[#This Row],[Net_Sales]]-RawSalesTable[[#This Row],[Total_Cost]] -> 17.37 | AD85: =RawSalesTable[[#This Row],[Profit]]/RawSalesTable[[#This Row],[Net_Sales]] -> 0.54366197 | AE85: =IF(RawSalesTable[[#This Row],[Return_Status]]="Yes",1,0) -> 0 | AF85: =YEAR(RawSalesTable[[#This Row],[Order_Date]]) -> 2025 | AG85: =MONTH(RawSalesTable[[#This Row],[Order_Date]]) -> 2 | AH85: =TEXT(RawSalesTable[[#This Row],[Order_Date]],"mmmm") -> février | AI85: =IF(RawSalesTable[[#This Row],[Month_Number]]<=3,"Q1",IF(RawSalesTable[[#This Row],[Month_Number]]<=6,"Q2",IF(RawSalesTable[[#This Row],[Month_Number]]<=9,"Q3","Q4"))) -> Q1 | AJ85: =DATE(YEAR(RawSalesTable[[#This Row],[Order_Date]]),MONTH(RawSalesTable[[#This Row],[Order_Date]]),1) -> 45689 | AK85: =VLOOKUP(RawSalesTable[[#This Row],[Customer_ID_clean]],CustomersTable[],4,FALSE) -> Saskatchewan
A86: ORD-2025-00073 | B86: 45672 | C86: C0063 | D86: P1003 | E86: Adam Singh, Laval, Small Business | F86: Toronto Downtown | G86: J. Tremblay | H86: Online | I86: 1 | J86: 152.32 | K86: 0.1 | L86: PayPal | M86: 5 | N86: No | O86: =SUBSTITUTE(PROPER(TRIM(RawSalesTable[[#This Row],[Channel_Raw]])), "Market Place", "Marketplace") -> Online | P86: =TRIM(RawSalesTable[[#This Row],[Store_Raw]]) -> Toronto Downtown | Q86: =IF(TRIM(RawSalesTable[[#This Row],[Payment_Method_Raw]])="","Non renseigné",SUBSTITUTE(TRIM(RawSalesTable[[#This Row],[Payment_Method_Raw]]),"CC","Credit Card")) -> PayPal | R86: =UPPER(PROPER(RawSalesTable[[#This Row],[Customer_ID]])) -> C0063 | S86: =TRIM(LEFT(RawSalesTable[[#This Row],[Customer_Info]],FIND(",",RawSalesTable[[#This Row],[Customer_Info]]) -1)) -> Adam Singh | T86: =TRIM(MID(RawSalesTable[[#This Row],[Customer_Info]],FIND(",",RawSalesTable[[#This Row],[Customer_Info]])+1,FIND(",",RawSalesTable[[#This Row],[Customer_Info]],FIND(",",RawSalesTable[[#This Row],[Customer_Info]])+1)-FIND(",",RawSalesTable[[#This Row],[Customer_Info]])-1)) -> Laval | U86: =TRIM(RIGHT(RawSalesTable[[#This Row],[Customer_Info]], LEN(RawSalesTable[[#This Row],[Customer_Info]])-FIND(",",RawSalesTable[[#This Row],[Customer_Info]],FIND(",",RawSalesTable[[#This Row],[Customer_Info]])+1))) -> Small Business | V86: =VLOOKUP(RawSalesTable[[#This Row],[Product_ID]],ProductsTable[],2,FALSE) -> Mouse | W86: =VLOOKUP(RawSalesTable[[#This Row],[Product_ID]],ProductsTable[],3,FALSE) -> Electronics | X86: =VLOOKUP(RawSalesTable[[#This Row],[Product_ID]],ProductsTable[],5,FALSE) -> 106.4 | Y86: =RawSalesTable[[#This Row],[Quantity]]*RawSalesTable[[#This Row],[Unit_Price]] -> 152.32 | Z86: =RawSalesTable[[#This Row],[Gross_Sales]]*RawSalesTable[[#This Row],[Discount_Pct]] -> 15.232 | AA86: =RawSalesTable[[#This Row],[Gross_Sales]]-RawSalesTable[[#This Row],[Discount_Amount]] -> 137.088 | AB86: =RawSalesTable[[#This Row],[Unit_Cost]]*RawSalesTable[[#This Row],[Quantity]] -> 106.4 | AC86: =RawSalesTable[[#This Row],[Net_Sales]]-RawSalesTable[[#This Row],[Total_Cost]] -> 30.688 | AD86: =RawSalesTable[[#This Row],[Profit]]/RawSalesTable[[#This Row],[Net_Sales]] -> 0.22385621 | AE86: =IF(RawSalesTable[[#This Row],[Return_Status]]="Yes",1,0) -> 0 | AF86: =YEAR(RawSalesTable[[#This Row],[Order_Date]]) -> 2025 | AG86: =MONTH(RawSalesTable[[#This Row],[Order_Date]]) -> 1 | AH86: =TEXT(RawSalesTable[[#This Row],[Order_Date]],"mmmm") -> janvier | AI86: =IF(RawSalesTable[[#This Row],[Month_Number]]<=3,"Q1",IF(RawSalesTable[[#This Row],[Month_Number]]<=6,"Q2",IF(RawSalesTable[[#This Row],[Month_Number]]<=9,"Q3","Q4"))) -> Q1 | AJ86: =DATE(YEAR(RawSalesTable[[#This Row],[Order_Date]]),MONTH(RawSalesTable[[#This Row],[Order_Date]]),1) -> 45658 | AK86: =VLOOKUP(RawSalesTable[[#This Row],[Customer_ID_clean]],CustomersTable[],4,FALSE) -> Quebec
A87: ORD-2025-00074 | B87: 45692 | C87: C0108 | D87: P1037 | E87: Noah Lee , Surrey , Consumer | F87: Vancouver West | G87: N. Brown | H87: Retail Store | I87: 2 | J87: 367.26 | K87: 0.2 | L87: Credit Card | M87: 0 | N87: No | O87: =SUBSTITUTE(PROPER(TRIM(RawSalesTable[[#This Row],[Channel_Raw]])), "Market Place", "Marketplace") -> Retail Store | P87: =TRIM(RawSalesTable[[#This Row],[Store_Raw]]) -> Vancouver West | Q87: =IF(TRIM(RawSalesTable[[#This Row],[Payment_Method_Raw]])="","Non renseigné",SUBSTITUTE(TRIM(RawSalesTable[[#This Row],[Payment_Method_Raw]]),"CC","Credit Card")) -> Credit Card | R87: =UPPER(PROPER(RawSalesTable[[#This Row],[Customer_ID]])) -> C0108 | S87: =TRIM(LEFT(RawSalesTable[[#This Row],[Customer_Info]],FIND(",",RawSalesTable[[#This Row],[Customer_Info]]) -1)) -> Noah Lee | T87: =TRIM(MID(RawSalesTable[[#This Row],[Customer_Info]],FIND(",",RawSalesTable[[#This Row],[Customer_Info]])+1,FIND(",",RawSalesTable[[#This Row],[Customer_Info]],FIND(",",RawSalesTable[[#This Row],[Customer_Info]])+1)-FIND(",",RawSalesTable[[#This Row],[Customer_Info]])-1)) -> Surrey | U87: =TRIM(RIGHT(RawSalesTable[[#This Row],[Customer_Info]], LEN(RawSalesTable[[#This Row],[Customer_Info]])-FIND(",",RawSalesTable[[#This Row],[Customer_Info]],FIND(",",RawSalesTable[[#This Row],[Customer_Info]])+1))) -> Consumer | V87: =VLOOKUP(RawSalesTable[[#This Row],[Product_ID]],ProductsTable[],2,FALSE) -> Cable Set | W87: =VLOOKUP(RawSalesTable[[#This Row],[Product_ID]],ProductsTable[],3,FALSE) -> Accessories | X87: =VLOOKUP(RawSalesTable[[#This Row],[Product_ID]],ProductsTable[],5,FALSE) -> 200.16 | Y87: =RawSalesTable[[#This Row],[Quantity]]*RawSalesTable[[#This Row],[Unit_Price]] -> 734.52 | Z87: =RawSalesTable[[#This Row],[Gross_Sales]]*RawSalesTable[[#This Row],[Discount_Pct]] -> 146.904 | AA87: =RawSalesTable[[#This Row],[Gross_Sales]]-RawSalesTable[[#This Row],[Discount_Amount]] -> 587.616 | AB87: =RawSalesTable[[#This Row],[Unit_Cost]]*RawSalesTable[[#This Row],[Quantity]] -> 400.32 | AC87: =RawSalesTable[[#This Row],[Net_Sales]]-RawSalesTable[[#This Row],[Total_Cost]] -> 187.296 | AD87: =RawSalesTable[[#This Row],[Profit]]/RawSalesTable[[#This Row],[Net_Sales]] -> 0.31873877 | AE87: =IF(RawSalesTable[[#This Row],[Return_Status]]="Yes",1,0) -> 0 | AF87: =YEAR(RawSalesTable[[#This Row],[Order_Date]]) -> 2025 | AG87: =MONTH(RawSalesTable[[#This Row],[Order_Date]]) -> 2 | AH87: =TEXT(RawSalesTable[[#This Row],[Order_Date]],"mmmm") -> février | AI87: =IF(RawSalesTable[[#This Row],[Month_Number]]<=3,"Q1",IF(RawSalesTable[[#This Row],[Month_Number]]<=6,"Q2",IF(RawSalesTable[[#This Row],[Month_Number]]<=9,"Q3","Q4"))) -> Q1 | AJ87: =DATE(YEAR(RawSalesTable[[#This Row],[Order_Date]]),MONTH(RawSalesTable[[#This Row],[Order_Date]]),1) -> 45689 | AK87: =VLOOKUP(RawSalesTable[[#This Row],[Customer_ID_clean]],CustomersTable[],4,FALSE) -> British Columbia
A88: ORD-2025-00075 | B88: 45706 | C88: C0073 | D88: P1010 | E88: Olivia Singh, Mississauga, Consumer | F88: Toronto Downtown | G88: L. Chen | H88: Online | I88: 2 | J88: 221.42 | K88: 0 | L88: Credit Card | M88: 8 | N88: Yes | O88: =SUBSTITUTE(PROPER(TRIM(RawSalesTable[[#This Row],[Channel_Raw]])), "Market Place", "Marketplace") -> Online | P88: =TRIM(RawSalesTable[[#This Row],[Store_Raw]]) -> Toronto Downtown | Q88: =IF(TRIM(RawSalesTable[[#This Row],[Payment_Method_Raw]])="","Non renseigné",SUBSTITUTE(TRIM(RawSalesTable[[#This Row],[Payment_Method_Raw]]),"CC","Credit Card")) -> Credit Card | R88: =UPPER(PROPER(RawSalesTable[[#This Row],[Customer_ID]])) -> C0073 | S88: =TRIM(LEFT(RawSalesTable[[#This Row],[Customer_Info]],FIND(",",RawSalesTable[[#This Row],[Customer_Info]]) -1)) -> Olivia Singh | T88: =TRIM(MID(RawSalesTable[[#This Row],[Customer_Info]],FIND(",",RawSalesTable[[#This Row],[Customer_Info]])+1,FIND(",",RawSalesTable[[#This Row],[Customer_Info]],FIND(",",RawSalesTable[[#This Row],[Customer_Info]])+1)-FIND(",",RawSalesTable[[#This Row],[Customer_Info]])-1)) -> Mississauga | U88: =TRIM(RIGHT(RawSalesTable[[#This Row],[Customer_Info]], LEN(RawSalesTable[[#This Row],[Customer_Info]])-FIND(",",RawSalesTable[[#This Row],[Customer_Info]],FIND(",",RawSalesTable[[#This Row],[Customer_Info]])+1))) -> Consumer | V88: =VLOOKUP(RawSalesTable[[#This Row],[Product_ID]],ProductsTable[],2,FALSE) -> Desk Lamp | W88: =VLOOKUP(RawSalesTable[[#This Row],[Product_ID]],ProductsTable[],3,FALSE) -> Office | X88: =VLOOKUP(RawSalesTable[[#This Row],[Product_ID]],ProductsTable[],5,FALSE) -> 127.21 | Y88: =RawSalesTable[[#This Row],[Quantity]]*RawSalesTable[[#This Row],[Unit_Price]] -> 442.84 | Z88: =RawSalesTable[[#This Row],[Gross_Sales]]*RawSalesTable[[#This Row],[Discount_Pct]] -> 0 | AA88: =RawSalesTable[[#This Row],[Gross_Sales]]-RawSalesTable[[#This Row],[Discount_Amount]] -> 442.84 | AB88: =RawSalesTable[[#This Row],[Unit_Cost]]*RawSalesTable[[#This Row],[Quantity]] -> 254.42 | AC88: =RawSalesTable[[#This Row],[Net_Sales]]-RawSalesTable[[#This Row],[Total_Cost]] -> 188.42 | AD88: =RawSalesTable[[#This Row],[Profit]]/RawSalesTable[[#This Row],[Net_Sales]] -> 0.42548099 | AE88: =IF(RawSalesTable[[#This Row],[Return_Status]]="Yes",1,0) -> 1 | AF88: =YEAR(RawSalesTable[[#This Row],[Order_Date]]) -> 2025 | AG88: =MONTH(RawSalesTable[[#This Row],[Order_Date]]) -> 2 | AH88: =TEXT(RawSalesTable[[#This Row],[Order_Date]],"mmmm") -> février | AI88: =IF(RawSalesTable[[#This Row],[Month_Number]]<=3,"Q1",IF(RawSalesTable[[#This Row],[Month_Number]]<=6,"Q2",IF(RawSalesTable[[#This Row],[Month_Number]]<=9,"Q3","Q4"))) -> Q1 | AJ88: =DATE(YEAR(RawSalesTable[[#This Row],[Order_Date]]),MONTH(RawSalesTable[[#This Row],[Order_Date]]),1) -> 45689 | AK88: =VLOOKUP(RawSalesTable[[#This Row],[Customer_ID_clean]],CustomersTable[],4,FALSE) -> Ontario
A89: ORD-2025-00076 | B89: 45963 | C89: C0085 | D89: P1027 | E89: Yasmine Clark, Calgary, Consumer | F89: Calgary North | G89: N. Brown | H89: Online | I89: 1 | J89: 58.78 | K89: 0.05 | L89: Credit Card | M89: 3 | N89: Yes | O89: =SUBSTITUTE(PROPER(TRIM(RawSalesTable[[#This Row],[Channel_Raw]])), "Market Place", "Marketplace") -> Online | P89: =TRIM(RawSalesTable[[#This Row],[Store_Raw]]) -> Calgary North | Q89: =IF(TRIM(RawSalesTable[[#This Row],[Payment_Method_Raw]])="","Non renseigné",SUBSTITUTE(TRIM(RawSalesTable[[#This Row],[Payment_Method_Raw]]),"CC","Credit Card")) -> Credit Card | R89: =UPPER(PROPER(RawSalesTable[[#This Row],[Customer_ID]])) -> C0085 | S89: =TRIM(LEFT(RawSalesTable[[#This Row],[Customer_Info]],FIND(",",RawSalesTable[[#This Row],[Customer_Info]]) -1)) -> Yasmine Clark | T89: =TRIM(MID(RawSalesTable[[#This Row],[Customer_Info]],FIND(",",RawSalesTable[[#This Row],[Customer_Info]])+1,FIND(",",RawSalesTable[[#This Row],[Customer_Info]],FIND(",",RawSalesTable[[#This Row],[Customer_Info]])+1)-FIND(",",RawSalesTable[[#This Row],[Customer_Info]])-1)) -> Calgary | U89: =TRIM(RIGHT(RawSalesTable[[#This Row],[Customer_Info]], LEN(RawSalesTable[[#This Row],[Customer_Info]])-FIND(",",RawSalesTable[[#This Row],[Customer_Info]],FIND(",",RawSalesTable[[#This Row],[Customer_Info]])+1))) -> Consumer | V89: =VLOOKUP(RawSalesTable[[#This Row],[Product_ID]],ProductsTable[],2,FALSE) -> Kettlebell | W89: =VLOOKUP(RawSalesTable[[#This Row],[Product_ID]],ProductsTable[],3,FALSE) -> Fitness | X89: =VLOOKUP(RawSalesTable[[#This Row],[Product_ID]],ProductsTable[],5,FALSE) -> 25.97 | Y89: =RawSalesTable[[#This Row],[Quantity]]*RawSalesTable[[#This Row],[Unit_Price]] -> 58.78 | Z89: =RawSalesTable[[#This Row],[Gross_Sales]]*RawSalesTable[[#This Row],[Discount_Pct]] -> 2.939 | AA89: =RawSalesTable[[#This Row],[Gross_Sales]]-RawSalesTable[[#This Row],[Discount_Amount]] -> 55.841 | AB89: =RawSalesTable[[#This Row],[Unit_Cost]]*RawSalesTable[[#This Row],[Quantity]] -> 25.97 | AC89: =RawSalesTable[[#This Row],[Net_Sales]]-RawSalesTable[[#This Row],[Total_Cost]] -> 29.871 | AD89: =RawSalesTable[[#This Row],[Profit]]/RawSalesTable[[#This Row],[Net_Sales]] -> 0.53492953 | AE89: =IF(RawSalesTable[[#This Row],[Return_Status]]="Yes",1,0) -> 1 | AF89: =YEAR(RawSalesTable[[#This Row],[Order_Date]]) -> 2025 | AG89: =MONTH(RawSalesTable[[#This Row],[Order_Date]]) -> 11 | AH89: =TEXT(RawSalesTable[[#This Row],[Order_Date]],"mmmm") -> novembre | AI89: =IF(RawSalesTable[[#This Row],[Month_Number]]<=3,"Q1",IF(RawSalesTable[[#This Row],[Month_Number]]<=6,"Q2",IF(RawSalesTable[[#This Row],[Month_Number]]<=9,"Q3","Q4"))) -> Q4 | AJ89: =DATE(YEAR(RawSalesTable[[#This Row],[Order_Date]]),MONTH(RawSalesTable[[#This Row],[Order_Date]]),1) -> 45962 | AK89: =VLOOKUP(RawSalesTable[[#This Row],[Customer_ID_clean]],CustomersTable[],4,FALSE) -> Alberta
A90: ORD-2025-00077 | B90: 45671 | C90: C0037 | D90: P1033 | E90: Lucas Scott, Victoria, Small Business | F90: Montreal Central | G90: L. Chen | H90: Online | I90: 2 | J90: 297 | K90: 0.05 | L90: PayPal | M90: 3 | N90: No | O90: =SUBSTITUTE(PROPER(TRIM(RawSalesTable[[#This Row],[Channel_Raw]])), "Market Place", "Marketplace") -> Online | P90: =TRIM(RawSalesTable[[#This Row],[Store_Raw]]) -> Montreal Central | Q90: =IF(TRIM(RawSalesTable[[#This Row],[Payment_Method_Raw]])="","Non renseigné",SUBSTITUTE(TRIM(RawSalesTable[[#This Row],[Payment_Method_Raw]]),"CC","Credit Card")) -> PayPal | R90: =UPPER(PROPER(RawSalesTable[[#This Row],[Customer_ID]])) -> C0037 | S90: =TRIM(LEFT(RawSalesTable[[#This Row],[Customer_Info]],FIND(",",RawSalesTable[[#This Row],[Customer_Info]]) -1)) -> Lucas Scott | T90: =TRIM(MID(RawSalesTable[[#This Row],[Customer_Info]],FIND(",",RawSalesTable[[#This Row],[Customer_Info]])+1,FIND(",",RawSalesTable[[#This Row],[Customer_Info]],FIND(",",RawSalesTable[[#This Row],[Customer_Info]])+1)-FIND(",",RawSalesTable[[#This Row],[Customer_Info]])-1)) -> Victoria | U90: =TRIM(RIGHT(RawSalesTable[[#This Row],[Customer_Info]], LEN(RawSalesTable[[#This Row],[Customer_Info]])-FIND(",",RawSalesTable[[#This Row],[Customer_Info]],FIND(",",RawSalesTable[[#This Row],[Customer_Info]])+1))) -> Small Business | V90: =VLOOKUP(RawSalesTable[[#This Row],[Product_ID]],ProductsTable[],2,FALSE) -> Backpack | W90: =VLOOKUP(RawSalesTable[[#This Row],[Product_ID]],ProductsTable[],3,FALSE) -> Accessories | X90: =VLOOKUP(RawSalesTable[[#This Row],[Product_ID]],ProductsTable[],5,FALSE) -> 152.55 | Y90: =RawSalesTable[[#This Row],[Quantity]]*RawSalesTable[[#This Row],[Unit_Price]] -> 594 | Z90: =RawSalesTable[[#This Row],[Gross_Sales]]*RawSalesTable[[#This Row],[Discount_Pct]] -> 29.7 | AA90: =RawSalesTable[[#This Row],[Gross_Sales]]-RawSalesTable[[#This Row],[Discount_Amount]] -> 564.3 | AB90: =RawSalesTable[[#This Row],[Unit_Cost]]*RawSalesTable[[#This Row],[Quantity]] -> 305.1 | AC90: =RawSalesTable[[#This Row],[Net_Sales]]-RawSalesTable[[#This Row],[Total_Cost]] -> 259.2 | AD90: =RawSalesTable[[#This Row],[Profit]]/RawSalesTable[[#This Row],[Net_Sales]] -> 0.45933014 | AE90: =IF(RawSalesTable[[#This Row],[Return_Status]]="Yes",1,0) -> 0 | AF90: =YEAR(RawSalesTable[[#This Row],[Order_Date]]) -> 2025 | AG90: =MONTH(RawSalesTable[[#This Row],[Order_Date]]) -> 1 | AH90: =TEXT(RawSalesTable[[#This Row],[Order_Date]],"mmmm") -> janvier | AI90: =IF(RawSalesTable[[#This Row],[Month_Number]]<=3,"Q1",IF(RawSalesTable[[#This Row],[Month_Number]]<=6,"Q2",IF(RawSalesTable[[#This Row],[Month_Number]]<=9,"Q3","Q4"))) -> Q1 | AJ90: =DATE(YEAR(RawSalesTable[[#This Row],[Order_Date]]),MONTH(RawSalesTable[[#This Row],[Order_Date]]),1) -> 45658 | AK90: =VLOOKUP(RawSalesTable[[#This Row],[Customer_ID_clean]],CustomersTable[],4,FALSE) -> British Columbia
A91: ORD-2025-00078 | B91: 45929 | C91: C0047 | D91: P1006 | E91: Amine King, Victoria, Consumer | F91: Montreal Central | G91: M. Wilson | H91: Retail Store | I91: 2 | J91: 101.43 | K91: 0.15 | L91: Debit Card | M91: 4 | N91: No | O91: =SUBSTITUTE(PROPER(TRIM(RawSalesTable[[#This Row],[Channel_Raw]])), "Market Place", "Marketplace") -> Retail Store | P91: =TRIM(RawSalesTable[[#This Row],[Store_Raw]]) -> Montreal Central | Q91: =IF(TRIM(RawSalesTable[[#This Row],[Payment_Method_Raw]])="","Non renseigné",SUBSTITUTE(TRIM(RawSalesTable[[#This Row],[Payment_Method_Raw]]),"CC","Credit Card")) -> Debit Card | R91: =UPPER(PROPER(RawSalesTable[[#This Row],[Customer_ID]])) -> C0047 | S91: =TRIM(LEFT(RawSalesTable[[#This Row],[Customer_Info]],FIND(",",RawSalesTable[[#This Row],[Customer_Info]]) -1)) -> Amine King | T91: =TRIM(MID(RawSalesTable[[#This Row],[Customer_Info]],FIND(",",RawSalesTable[[#This Row],[Customer_Info]])+1,FIND(",",RawSalesTable[[#This Row],[Customer_Info]],FIND(",",RawSalesTable[[#This Row],[Customer_Info]])+1)-FIND(",",RawSalesTable[[#This Row],[Customer_Info]])-1)) -> Victoria | U91: =TRIM(RIGHT(RawSalesTable[[#This Row],[Customer_Info]], LEN(RawSalesTable[[#This Row],[Customer_Info]])-FIND(",",RawSalesTable[[#This Row],[Customer_Info]],FIND(",",RawSalesTable[[#This Row],[Customer_Info]])+1))) -> Consumer | V91: =VLOOKUP(RawSalesTable[[#This Row],[Product_ID]],ProductsTable[],2,FALSE) -> USB-C Hub | W91: =VLOOKUP(RawSalesTable[[#This Row],[Product_ID]],ProductsTable[],3,FALSE) -> Electronics | X91: =VLOOKUP(RawSalesTable[[#This Row],[Product_ID]],ProductsTable[],5,FALSE) -> 72 | Y91: =RawSalesTable[[#This Row],[Quantity]]*RawSalesTable[[#This Row],[Unit_Price]] -> 202.86 | Z91: =RawSalesTable[[#This Row],[Gross_Sales]]*RawSalesTable[[#This Row],[Discount_Pct]] -> 30.429 | AA91: =RawSalesTable[[#This Row],[Gross_Sales]]-RawSalesTable[[#This Row],[Discount_Amount]] -> 172.431 | AB91: =RawSalesTable[[#This Row],[Unit_Cost]]*RawSalesTable[[#This Row],[Quantity]] -> 144 | AC91: =RawSalesTable[[#This Row],[Net_Sales]]-RawSalesTable[[#This Row],[Total_Cost]] -> 28.431 | AD91: =RawSalesTable[[#This Row],[Profit]]/RawSalesTable[[#This Row],[Net_Sales]] -> 0.16488334 | AE91: =IF(RawSalesTable[[#This Row],[Return_Status]]="Yes",1,0) -> 0 | AF91: =YEAR(RawSalesTable[[#This Row],[Order_Date]]) -> 2025 | AG91: =MONTH(RawSalesTable[[#This Row],[Order_Date]]) -> 9 | AH91: =TEXT(RawSalesTable[[#This Row],[Order_Date]],"mmmm") -> septembre | AI91: =IF(RawSalesTable[[#This Row],[Month_Number]]<=3,"Q1",IF(RawSalesTable[[#This Row],[Month_Number]]<=6,"Q2",IF(RawSalesTable[[#This Row],[Month_Number]]<=9,"Q3","Q4"))) -> Q3 | AJ91: =DATE(YEAR(RawSalesTable[[#This Row],[Order_Date]]),MONTH(RawSalesTable[[#This Row],[Order_Date]]),1) -> 45901 | AK91: =VLOOKUP(RawSalesTable[[#This Row],[Customer_ID_clean]],CustomersTable[],4,FALSE) -> British Columbia
A92: ORD-2025-00079 | B92: 46001 | C92: C0003 | D92: P1014 | E92: Amelia Young, Ottawa, Corporate | F92: Vancouver West | G92: E. Roy | H92: Online | I92: 1 | J92: 235.55 | K92: 0 | L92: Debit Card | M92: 5 | N92: No | O92: =SUBSTITUTE(PROPER(TRIM(RawSalesTable[[#This Row],[Channel_Raw]])), "Market Place", "Marketplace") -> Online | P92: =TRIM(RawSalesTable[[#This Row],[Store_Raw]]) -> Vancouver West | Q92: =IF(TRIM(RawSalesTable[[#This Row],[Payment_Method_Raw]])="","Non renseigné",SUBSTITUTE(TRIM(RawSalesTable[[#This Row],[Payment_Method_Raw]]),"CC","Credit Card")) -> Debit Card | R92: =UPPER(PROPER(RawSalesTable[[#This Row],[Customer_ID]])) -> C0003 | S92: =TRIM(LEFT(RawSalesTable[[#This Row],[Customer_Info]],FIND(",",RawSalesTable[[#This Row],[Customer_Info]]) -1)) -> Amelia Young | T92: =TRIM(MID(RawSalesTable[[#This Row],[Customer_Info]],FIND(",",RawSalesTable[[#This Row],[Customer_Info]])+1,FIND(",",RawSalesTable[[#This Row],[Customer_Info]],FIND(",",RawSalesTable[[#This Row],[Customer_Info]])+1)-FIND(",",RawSalesTable[[#This Row],[Customer_Info]])-1)) -> Ottawa | U92: =TRIM(RIGHT(RawSalesTable[[#This Row],[Customer_Info]], LEN(RawSalesTable[[#This Row],[Customer_Info]])-FIND(",",RawSalesTable[[#This Row],[Customer_Info]],FIND(",",RawSalesTable[[#This Row],[Customer_Info]])+1))) -> Corporate | V92: =VLOOKUP(RawSalesTable[[#This Row],[Product_ID]],ProductsTable[],2,FALSE) -> Document Shredder | W92: =VLOOKUP(RawSalesTable[[#This Row],[Product_ID]],ProductsTable[],3,FALSE) -> Office | X92: =VLOOKUP(RawSalesTable[[#This Row],[Product_ID]],ProductsTable[],5,FALSE) -> 117.65 | Y92: =RawSalesTable[[#This Row],[Quantity]]*RawSalesTable[[#This Row],[Unit_Price]] -> 235.55 | Z92: =RawSalesTable[[#This Row],[Gross_Sales]]*RawSalesTable[[#This Row],[Discount_Pct]] -> 0 | AA92: =RawSalesTable[[#This Row],[Gross_Sales]]-RawSalesTable[[#This Row],[Discount_Amount]] -> 235.55 | AB92: =RawSalesTable[[#This Row],[Unit_Cost]]*RawSalesTable[[#This Row],[Quantity]] -> 117.65 | AC92: =RawSalesTable[[#This Row],[Net_Sales]]-RawSalesTable[[#This Row],[Total_Cost]] -> 117.9 | AD92: =RawSalesTable[[#This Row],[Profit]]/RawSalesTable[[#This Row],[Net_Sales]] -> 0.50053067 | AE92: =IF(RawSalesTable[[#This Row],[Return_Status]]="Yes",1,0) -> 0 | AF92: =YEAR(RawSalesTable[[#This Row],[Order_Date]]) -> 2025 | AG92: =MONTH(RawSalesTable[[#This Row],[Order_Date]]) -> 12 | AH92: =TEXT(RawSalesTable[[#This Row],[Order_Date]],"mmmm") -> décembre | AI92: =IF(RawSalesTable[[#This Row],[Month_Number]]<=3,"Q1",IF(RawSalesTable[[#This Row],[Month_Number]]<=6,"Q2",IF(RawSalesTable[[#This Row],[Month_Number]]<=9,"Q3","Q4"))) -> Q4 | AJ92: =DATE(YEAR(RawSalesTable[[#This Row],[Order_Date]]),MONTH(RawSalesTable[[#This Row],[Order_Date]]),1) -> 45992 | AK92: =VLOOKUP(RawSalesTable[[#This Row],[Customer_ID_clean]],CustomersTable[],4,FALSE) -> Ontario
A93: ORD-2025-00080 | B93: 45685 | C93: C0014 | D93: P1007 | E93: Zoe Scott, Montreal, Small Business | F93: Online Fulfillment | G93: N. Brown | H93: Online | I93: 2 | J93: 341.19 | K93: 0.1 | L93: Credit Card | M93: 1 | N93: No | O93: =SUBSTITUTE(PROPER(TRIM(RawSalesTable[[#This Row],[Channel_Raw]])), "Market Place", "Marketplace") -> Online | P93: =TRIM(RawSalesTable[[#This Row],[Store_Raw]]) -> Online Fulfillment | Q93: =IF(TRIM(RawSalesTable[[#This Row],[Payment_Method_Raw]])="","Non renseigné",SUBSTITUTE(TRIM(RawSalesTable[[#This Row],[Payment_Method_Raw]]),"CC","Credit Card")) -> Credit Card | R93: =UPPER(PROPER(RawSalesTable[[#This Row],[Customer_ID]])) -> C0014 | S93: =TRIM(LEFT(RawSalesTable[[#This Row],[Customer_Info]],FIND(",",RawSalesTable[[#This Row],[Customer_Info]]) -1)) -> Zoe Scott | T93: =TRIM(MID(RawSalesTable[[#This Row],[Customer_Info]],FIND(",",RawSalesTable[[#This Row],[Customer_Info]])+1,FIND(",",RawSalesTable[[#This Row],[Customer_Info]],FIND(",",RawSalesTable[[#This Row],[Customer_Info]])+1)-FIND(",",RawSalesTable[[#This Row],[Customer_Info]])-1)) -> Montreal | U93: =TRIM(RIGHT(RawSalesTable[[#This Row],[Customer_Info]], LEN(RawSalesTable[[#This Row],[Customer_Info]])-FIND(",",RawSalesTable[[#This Row],[Customer_Info]],FIND(",",RawSalesTable[[#This Row],[Customer_Info]])+1))) -> Small Business | V93: =VLOOKUP(RawSalesTable[[#This Row],[Product_ID]],ProductsTable[],2,FALSE) -> Monitor | W93: =VLOOKUP(RawSalesTable[[#This Row],[Product_ID]],ProductsTable[],3,FALSE) -> Electronics | X93: =VLOOKUP(RawSalesTable[[#This Row],[Product_ID]],ProductsTable[],5,FALSE) -> 224.47 | Y93: =RawSalesTable[[#This Row],[Quantity]]*RawSalesTable[[#This Row],[Unit_Price]] -> 682.38 | Z93: =RawSalesTable[[#This Row],[Gross_Sales]]*RawSalesTable[[#This Row],[Discount_Pct]] -> 68.238 | AA93: =RawSalesTable[[#This Row],[Gross_Sales]]-RawSalesTable[[#This Row],[Discount_Amount]] -> 614.142 | AB93: =RawSalesTable[[#This Row],[Unit_Cost]]*RawSalesTable[[#This Row],[Quantity]] -> 448.94 | AC93: =RawSalesTable[[#This Row],[Net_Sales]]-RawSalesTable[[#This Row],[Total_Cost]] -> 165.202 | AD93: =RawSalesTable[[#This Row],[Profit]]/RawSalesTable[[#This Row],[Net_Sales]] -> 0.26899642 | AE93: =IF(RawSalesTable[[#This Row],[Return_Status]]="Yes",1,0) -> 0 | AF93: =YEAR(RawSalesTable[[#This Row],[Order_Date]]) -> 2025 | AG93: =MONTH(RawSalesTable[[#This Row],[Order_Date]]) -> 1 | AH93: =TEXT(RawSalesTable[[#This Row],[Order_Date]],"mmmm") -> janvier | AI93: =IF(RawSalesTable[[#This Row],[Month_Number]]<=3,"Q1",IF(RawSalesTable[[#This Row],[Month_Number]]<=6,"Q2",IF(RawSalesTable[[#This Row],[Month_Number]]<=9,"Q3","Q4"))) -> Q1 | AJ93: =DATE(YEAR(RawSalesTable[[#This Row],[Order_Date]]),MONTH(RawSalesTable[[#This Row],[Order_Date]]),1) -> 45658 | AK93: =VLOOKUP(RawSalesTable[[#This Row],[Customer_ID_clean]],CustomersTable[],4,FALSE) -> Quebec
A94: ORD-2025-00081 | B94: 45867 | C94: C0114 | D94: P1036 | E94: Olivia Johnson, Ottawa, Consumer | F94: Calgary North | G94: J. Tremblay | H94: Retail Store | I94: 1 | J94: 160.72 | K94: 0.2 | L94: Debit Card | M94: 4 | N94: No | O94: =SUBSTITUTE(PROPER(TRIM(RawSalesTable[[#This Row],[Channel_Raw]])), "Market Place", "Marketplace") -> Retail Store | P94: =TRIM(RawSalesTable[[#This Row],[Store_Raw]]) -> Calgary North | Q94: =IF(TRIM(RawSalesTable[[#This Row],[Payment_Method_Raw]])="","Non renseigné",SUBSTITUTE(TRIM(RawSalesTable[[#This Row],[Payment_Method_Raw]]),"CC","Credit Card")) -> Debit Card | R94: =UPPER(PROPER(RawSalesTable[[#This Row],[Customer_ID]])) -> C0114 | S94: =TRIM(LEFT(RawSalesTable[[#This Row],[Customer_Info]],FIND(",",RawSalesTable[[#This Row],[Customer_Info]]) -1)) -> Olivia Johnson | T94: =TRIM(MID(RawSalesTable[[#This Row],[Customer_Info]],FIND(",",RawSalesTable[[#This Row],[Customer_Info]])+1,FIND(",",RawSalesTable[[#This Row],[Customer_Info]],FIND(",",RawSalesTable[[#This Row],[Customer_Info]])+1)-FIND(",",RawSalesTable[[#This Row],[Customer_Info]])-1)) -> Ottawa | U94: =TRIM(RIGHT(RawSalesTable[[#This Row],[Customer_Info]], LEN(RawSalesTable[[#This Row],[Customer_Info]])-FIND(",",RawSalesTable[[#This Row],[Customer_Info]],FIND(",",RawSalesTable[[#This Row],[Customer_Info]])+1))) -> Consumer | V94: =VLOOKUP(RawSalesTable[[#This Row],[Product_ID]],ProductsTable[],2,FALSE) -> Power Bank | W94: =VLOOKUP(RawSalesTable[[#This Row],[Product_ID]],ProductsTable[],3,FALSE) -> Accessories | X94: =VLOOKUP(RawSalesTable[[#This Row],[Product_ID]],ProductsTable[],5,FALSE) -> 76.97 | Y94: =RawSalesTable[[#This Row],[Quantity]]*RawSalesTable[[#This Row],[Unit_Price]] -> 160.72 | Z94: =RawSalesTable[[#This Row],[Gross_Sales]]*RawSalesTable[[#This Row],[Discount_Pct]] -> 32.144 | AA94: =RawSalesTable[[#This Row],[Gross_Sales]]-RawSalesTable[[#This Row],[Discount_Amount]] -> 128.576 | AB94: =RawSalesTable[[#This Row],[Unit_Cost]]*RawSalesTable[[#This Row],[Quantity]] -> 76.97 | AC94: =RawSalesTable[[#This Row],[Net_Sales]]-RawSalesTable[[#This Row],[Total_Cost]] -> 51.606 | AD94: =RawSalesTable[[#This Row],[Profit]]/RawSalesTable[[#This Row],[Net_Sales]] -> 0.40136573 | AE94: =IF(RawSalesTable[[#This Row],[Return_Status]]="Yes",1,0) -> 0 | AF94: =YEAR(RawSalesTable[[#This Row],[Order_Date]]) -> 2025 | AG94: =MONTH(RawSalesTable[[#This Row],[Order_Date]]) -> 7 | AH94: =TEXT(RawSalesTable[[#This Row],[Order_Date]],"mmmm") -> juillet | AI94: =IF(RawSalesTable[[#This Row],[Month_Number]]<=3,"Q1",IF(RawSalesTable[[#This Row],[Month_Number]]<=6,"Q2",IF(RawSalesTable[[#This Row],[Month_Number]]<=9,"Q3","Q4"))) -> Q3 | AJ94: =DATE(YEAR(RawSalesTable[[#This Row],[Order_Date]]),MONTH(RawSalesTable[[#This Row],[Order_Date]]),1) -> 45839 | AK94: =VLOOKUP(RawSalesTable[[#This Row],[Customer_ID_clean]],CustomersTable[],4,FALSE) -> Ontario
... A350: ORD-2025-00342 | B350: 45676 | C350: C0104 | D350: P1039 | E350: Ava Scott, Edmonton, Corporate | F350: Calgary North | G350: S. Patel | H350: Marketplace | I350: 4 | J350: 344.84 | K350: 0 | L350: PayPal | M350: 7 | N350: No | O350: =SUBSTITUTE(PROPER(TRIM(RawSalesTable[[#This Row],[Channel_Raw]])), "Market Place", "Marketplace") -> Marketplace | P350: =TRIM(RawSalesTable[[#This Row],[Store_Raw]]) -> Calgary North | Q350: =IF(TRIM(RawSalesTable[[#This Row],[Payment_Method_Raw]])="","Non renseigné",SUBSTITUTE(TRIM(RawSalesTable[[#This Row],[Payment_Method_Raw]]),"CC","Credit Card")) -> PayPal | R350: =UPPER(PROPER(RawSalesTable[[#This Row],[Customer_ID]])) -> C0104 | S350: =TRIM(LEFT(RawSalesTable[[#This Row],[Customer_Info]],FIND(",",RawSalesTable[[#This Row],[Customer_Info]]) -1)) -> Ava Scott | T350: =TRIM(MID(RawSalesTable[[#This Row],[Customer_Info]],FIND(",",RawSalesTable[[#This Row],[Customer_Info]])+1,FIND(",",RawSalesTable[[#This Row],[Customer_Info]],FIND(",",RawSalesTable[[#This Row],[Customer_Info]])+1)-FIND(",",RawSalesTable[[#This Row],[Customer_Info]])-1)) -> Edmonton | U350: =TRIM(RIGHT(RawSalesTable[[#This Row],[Customer_Info]], LEN(RawSalesTable[[#This Row],[Customer_Info]])-FIND(",",RawSalesTable[[#This Row],[Customer_Info]],FIND(",",RawSalesTable[[#This Row],[Customer_Info]])+1))) -> Corporate | V350: =VLOOKUP(RawSalesTable[[#This Row],[Product_ID]],ProductsTable[],2,FALSE) -> Travel Adapter | W350: =VLOOKUP(RawSalesTable[[#This Row],[Product_ID]],ProductsTable[],3,FALSE) -> Accessories | X350: =VLOOKUP(RawSalesTable[[#This Row],[Product_ID]],ProductsTable[],5,FALSE) -> 229.86 | Y350: =RawSalesTable[[#This Row],[Quantity]]*RawSalesTable[[#This Row],[Unit_Price]] -> 1379.36 | Z350: =RawSalesTable[[#This Row],[Gross_Sales]]*RawSalesTable[[#This Row],[Discount_Pct]] -> 0 | AA350: =RawSalesTable[[#This Row],[Gross_Sales]]-RawSalesTable[[#This Row],[Discount_Amount]] -> 1379.36 | AB350: =RawSalesTable[[#This Row],[Unit_Cost]]*RawSalesTable[[#This Row],[Quantity]] -> 919.44 | AC350: =RawSalesTable[[#This Row],[Net_Sales]]-RawSalesTable[[#This Row],[Total_Cost]] -> 459.92 | AD350: =RawSalesTable[[#This Row],[Profit]]/RawSalesTable[[#This Row],[Net_Sales]] -> 0.33343 | AE350: =IF(RawSalesTable[[#This Row],[Return_Status]]="Yes",1,0) -> 0 | AF350: =YEAR(RawSalesTable[[#This Row],[Order_Date]]) -> 2025 | AG350: =MONTH(RawSalesTable[[#This Row],[Order_Date]]) -> 1 | AH350: =TEXT(RawSalesTable[[#This Row],[Order_Date]],"mmmm") -> janvier | AI350: =IF(RawSalesTable[[#This Row],[Month_Number]]<=3,"Q1",IF(RawSalesTable[[#This Row],[Month_Number]]<=6,"Q2",IF(RawSalesTable[[#This Row],[Month_Number]]<=9,"Q3","Q4"))) -> Q1 | AJ350: =DATE(YEAR(RawSalesTable[[#This Row],[Order_Date]]),MONTH(RawSalesTable[[#This Row],[Order_Date]]),1) -> 45658 | AK350: =VLOOKUP(RawSalesTable[[#This Row],[Customer_ID_clean]],CustomersTable[],4,FALSE) -> Alberta
A351: ORD-2025-00343 | B351: 45786 | C351: C0095 | D351: P1009 | E351: Maya White, Quebec City, Corporate | F351: Montreal Central | G351: M. Wilson | H351: Online | I351: 2 | J351: 309.99 | K351: 0.05 | M351: 2 | N351: No | O351: =SUBSTITUTE(PROPER(TRIM(RawSalesTable[[#This Row],[Channel_Raw]])), "Market Place", "Marketplace") -> Online | P351: =TRIM(RawSalesTable[[#This Row],[Store_Raw]]) -> Montreal Central | Q351: =IF(TRIM(RawSalesTable[[#This Row],[Payment_Method_Raw]])="","Non renseigné",SUBSTITUTE(TRIM(RawSalesTable[[#This Row],[Payment_Method_Raw]]),"CC","Credit Card")) -> Non renseigné | R351: =UPPER(PROPER(RawSalesTable[[#This Row],[Customer_ID]])) -> C0095 | S351: =TRIM(LEFT(RawSalesTable[[#This Row],[Customer_Info]],FIND(",",RawSalesTable[[#This Row],[Customer_Info]]) -1)) -> Maya White | T351: =TRIM(MID(RawSalesTable[[#This Row],[Customer_Info]],FIND(",",RawSalesTable[[#This Row],[Customer_Info]])+1,FIND(",",RawSalesTable[[#This Row],[Customer_Info]],FIND(",",RawSalesTable[[#This Row],[Customer_Info]])+1)-FIND(",",RawSalesTable[[#This Row],[Customer_Info]])-1)) -> Quebec City | U351: =TRIM(RIGHT(RawSalesTable[[#This Row],[Customer_Info]], LEN(RawSalesTable[[#This Row],[Customer_Info]])-FIND(",",RawSalesTable[[#This Row],[Customer_Info]],FIND(",",RawSalesTable[[#This Row],[Customer_Info]])+1))) -> Corporate | V351: =VLOOKUP(RawSalesTable[[#This Row],[Product_ID]],ProductsTable[],2,FALSE) -> Notebook | W351: =VLOOKUP(RawSalesTable[[#This Row],[Product_ID]],ProductsTable[],3,FALSE) -> Office | X351: =VLOOKUP(RawSalesTable[[#This Row],[Product_ID]],ProductsTable[],5,FALSE) -> 176.13 | Y351: =RawSalesTable[[#This Row],[Quantity]]*RawSalesTable[[#This Row],[Unit_Price]] -> 619.98 | Z351: =RawSalesTable[[#This Row],[Gross_Sales]]*RawSalesTable[[#This Row],[Discount_Pct]] -> 30.999 | AA351: =RawSalesTable[[#This Row],[Gross_Sales]]-RawSalesTable[[#This Row],[Discount_Amount]] -> 588.981 | AB351: =RawSalesTable[[#This Row],[Unit_Cost]]*RawSalesTable[[#This Row],[Quantity]] -> 352.26 | AC351: =RawSalesTable[[#This Row],[Net_Sales]]-RawSalesTable[[#This Row],[Total_Cost]] -> 236.721 | AD351: =RawSalesTable[[#This Row],[Profit]]/RawSalesTable[[#This Row],[Net_Sales]] -> 0.40191619 | AE351: =IF(RawSalesTable[[#This Row],[Return_Status]]="Yes",1,0) -> 0 | AF351: =YEAR(RawSalesTable[[#This Row],[Order_Date]]) -> 2025 | AG351: =MONTH(RawSalesTable[[#This Row],[Order_Date]]) -> 5 | AH351: =TEXT(RawSalesTable[[#This Row],[Order_Date]],"mmmm") -> mai | AI351: =IF(RawSalesTable[[#This Row],[Month_Number]]<=3,"Q1",IF(RawSalesTable[[#This Row],[Month_Number]]<=6,"Q2",IF(RawSalesTable[[#This Row],[Month_Number]]<=9,"Q3","Q4"))) -> Q2 | AJ351: =DATE(YEAR(RawSalesTable[[#This Row],[Order_Date]]),MONTH(RawSalesTable[[#This Row],[Order_Date]]),1) -> 45778 | AK351: =VLOOKUP(RawSalesTable[[#This Row],[Customer_ID_clean]],CustomersTable[],4,FALSE) -> Quebec
A352: ORD-2025-00344 | B352: 45703 | C352: C0034 | D352: P1028 | E352: Noah Tremblay, Toronto, Corporate | F352: Montreal Central | G352: L. Chen | H352: Online | I352: 1 | J352: 351.13 | K352: 0 | L352: Debit Card | M352: 8 | N352: No | O352: =SUBSTITUTE(PROPER(TRIM(RawSalesTable[[#This Row],[Channel_Raw]])), "Market Place", "Marketplace") -> Online | P352: =TRIM(RawSalesTable[[#This Row],[Store_Raw]]) -> Montreal Central | Q352: =IF(TRIM(RawSalesTable[[#This Row],[Payment_Method_Raw]])="","Non renseigné",SUBSTITUTE(TRIM(RawSalesTable[[#This Row],[Payment_Method_Raw]]),"CC","Credit Card")) -> Debit Card | R352: =UPPER(PROPER(RawSalesTable[[#This Row],[Customer_ID]])) -> C0034 | S352: =TRIM(LEFT(RawSalesTable[[#This Row],[Customer_Info]],FIND(",",RawSalesTable[[#This Row],[Customer_Info]]) -1)) -> Noah Tremblay | T352: =TRIM(MID(RawSalesTable[[#This Row],[Customer_Info]],FIND(",",RawSalesTable[[#This Row],[Customer_Info]])+1,FIND(",",RawSalesTable[[#This Row],[Customer_Info]],FIND(",",RawSalesTable[[#This Row],[Customer_Info]])+1)-FIND(",",RawSalesTable[[#This Row],[Customer_Info]])-1)) -> Toronto | U352: =TRIM(RIGHT(RawSalesTable[[#This Row],[Customer_Info]], LEN(RawSalesTable[[#This Row],[Customer_Info]])-FIND(",",RawSalesTable[[#This Row],[Customer_Info]],FIND(",",RawSalesTable[[#This Row],[Customer_Info]])+1))) -> Corporate | V352: =VLOOKUP(RawSalesTable[[#This Row],[Product_ID]],ProductsTable[],2,FALSE) -> Foam Roller | W352: =VLOOKUP(RawSalesTable[[#This Row],[Product_ID]],ProductsTable[],3,FALSE) -> Fitness | X352: =VLOOKUP(RawSalesTable[[#This Row],[Product_ID]],ProductsTable[],5,FALSE) -> 212.02 | Y352: =RawSalesTable[[#This Row],[Quantity]]*RawSalesTable[[#This Row],[Unit_Price]] -> 351.13 | Z352: =RawSalesTable[[#This Row],[Gross_Sales]]*RawSalesTable[[#This Row],[Discount_Pct]] -> 0 | AA352: =RawSalesTable[[#This Row],[Gross_Sales]]-RawSalesTable[[#This Row],[Discount_Amount]] -> 351.13 | AB352: =RawSalesTable[[#This Row],[Unit_Cost]]*RawSalesTable[[#This Row],[Quantity]] -> 212.02 | AC352: =RawSalesTable[[#This Row],[Net_Sales]]-RawSalesTable[[#This Row],[Total_Cost]] -> 139.11 | AD352: =RawSalesTable[[#This Row],[Profit]]/RawSalesTable[[#This Row],[Net_Sales]] -> 0.39617805 | AE352: =IF(RawSalesTable[[#This Row],[Return_Status]]="Yes",1,0) -> 0 | AF352: =YEAR(RawSalesTable[[#This Row],[Order_Date]]) -> 2025 | AG352: =MONTH(RawSalesTable[[#This Row],[Order_Date]]) -> 2 | AH352: =TEXT(RawSalesTable[[#This Row],[Order_Date]],"mmmm") -> février | AI352: =IF(RawSalesTable[[#This Row],[Month_Number]]<=3,"Q1",IF(RawSalesTable[[#This Row],[Month_Number]]<=6,"Q2",IF(RawSalesTable[[#This Row],[Month_Number]]<=9,"Q3","Q4"))) -> Q1 | AJ352: =DATE(YEAR(RawSalesTable[[#This Row],[Order_Date]]),MONTH(RawSalesTable[[#This Row],[Order_Date]]),1) -> 45689 | AK352: =VLOOKUP(RawSalesTable[[#This Row],[Customer_ID_clean]],CustomersTable[],4,FALSE) -> Ontario
A353: ORD-2025-00345 | B353: 45884 | C353: C0024 | D353: P1006 | E353: Ryan King, Mississauga, Consumer | F353: Vancouver West | G353: L. Chen | H353: Online | I353: 5 | J353: 107.3 | K353: 0 | L353: Credit Card | M353: 6 | N353: No | O353: =SUBSTITUTE(PROPER(TRIM(RawSalesTable[[#This Row],[Channel_Raw]])), "Market Place", "Marketplace") -> Online | P353: =TRIM(RawSalesTable[[#This Row],[Store_Raw]]) -> Vancouver West | Q353: =IF(TRIM(RawSalesTable[[#This Row],[Payment_Method_Raw]])="","Non renseigné",SUBSTITUTE(TRIM(RawSalesTable[[#This Row],[Payment_Method_Raw]]),"CC","Credit Card")) -> Credit Card | R353: =UPPER(PROPER(RawSalesTable[[#This Row],[Customer_ID]])) -> C0024 | S353: =TRIM(LEFT(RawSalesTable[[#This Row],[Customer_Info]],FIND(",",RawSalesTable[[#This Row],[Customer_Info]]) -1)) -> Ryan King | T353: =TRIM(MID(RawSalesTable[[#This Row],[Customer_Info]],FIND(",",RawSalesTable[[#This Row],[Customer_Info]])+1,FIND(",",RawSalesTable[[#This Row],[Customer_Info]],FIND(",",RawSalesTable[[#This Row],[Customer_Info]])+1)-FIND(",",RawSalesTable[[#This Row],[Customer_Info]])-1)) -> Mississauga | U353: =TRIM(RIGHT(RawSalesTable[[#This Row],[Customer_Info]], LEN(RawSalesTable[[#This Row],[Customer_Info]])-FIND(",",RawSalesTable[[#This Row],[Customer_Info]],FIND(",",RawSalesTable[[#This Row],[Customer_Info]])+1))) -> Consumer | V353: =VLOOKUP(RawSalesTable[[#This Row],[Product_ID]],ProductsTable[],2,FALSE) -> USB-C Hub | W353: =VLOOKUP(RawSalesTable[[#This Row],[Product_ID]],ProductsTable[],3,FALSE) -> Electronics | X353: =VLOOKUP(RawSalesTable[[#This Row],[Product_ID]],ProductsTable[],5,FALSE) -> 72 | Y353: =RawSalesTable[[#This Row],[Quantity]]*RawSalesTable[[#This Row],[Unit_Price]] -> 536.5 | Z353: =RawSalesTable[[#This Row],[Gross_Sales]]*RawSalesTable[[#This Row],[Discount_Pct]] -> 0 | AA353: =RawSalesTable[[#This Row],[Gross_Sales]]-RawSalesTable[[#This Row],[Discount_Amount]] -> 536.5 | AB353: =RawSalesTable[[#This Row],[Unit_Cost]]*RawSalesTable[[#This Row],[Quantity]] -> 360 | AC353: =RawSalesTable[[#This Row],[Net_Sales]]-RawSalesTable[[#This Row],[Total_Cost]] -> 176.5 | AD353: =RawSalesTable[[#This Row],[Profit]]/RawSalesTable[[#This Row],[Net_Sales]] -> 0.32898416 | AE353: =IF(RawSalesTable[[#This Row],[Return_Status]]="Yes",1,0) -> 0 | AF353: =YEAR(RawSalesTable[[#This Row],[Order_Date]]) -> 2025 | AG353: =MONTH(RawSalesTable[[#This Row],[Order_Date]]) -> 8 | AH353: =TEXT(RawSalesTable[[#This Row],[Order_Date]],"mmmm") -> août | AI353: =IF(RawSalesTable[[#This Row],[Month_Number]]<=3,"Q1",IF(RawSalesTable[[#This Row],[Month_Number]]<=6,"Q2",IF(RawSalesTable[[#This Row],[Month_Number]]<=9,"Q3","Q4"))) -> Q3 | AJ353: =DATE(YEAR(RawSalesTable[[#This Row],[Order_Date]]),MONTH(RawSalesTable[[#This Row],[Order_Date]]),1) -> 45870 | AK353: =VLOOKUP(RawSalesTable[[#This Row],[Customer_ID_clean]],CustomersTable[],4,FALSE) -> Ontario
A354: ORD-2025-00346 | B354: 45943 | C354: C0016 | D354: P1030 | E354: Nora Singh, Calgary, Consumer | F354: Vancouver West | G354: E. Roy | H354: Online | I354: 1 | J354: 236.69 | K354: 0.05 | L354: Debit Card | M354: 5 | N354: No | O354: =SUBSTITUTE(PROPER(TRIM(RawSalesTable[[#This Row],[Channel_Raw]])), "Market Place", "Marketplace") -> Online | P354: =TRIM(RawSalesTable[[#This Row],[Store_Raw]]) -> Vancouver West | Q354: =IF(TRIM(RawSalesTable[[#This Row],[Payment_Method_Raw]])="","Non renseigné",SUBSTITUTE(TRIM(RawSalesTable[[#This Row],[Payment_Method_Raw]]),"CC","Credit Card")) -> Debit Card | R354: =UPPER(PROPER(RawSalesTable[[#This Row],[Customer_ID]])) -> C0016 | S354: =TRIM(LEFT(RawSalesTable[[#This Row],[Customer_Info]],FIND(",",RawSalesTable[[#This Row],[Customer_Info]]) -1)) -> Nora Singh | T354: =TRIM(MID(RawSalesTable[[#This Row],[Customer_Info]],FIND(",",RawSalesTable[[#This Row],[Customer_Info]])+1,FIND(",",RawSalesTable[[#This Row],[Customer_Info]],FIND(",",RawSalesTable[[#This Row],[Customer_Info]])+1)-FIND(",",RawSalesTable[[#This Row],[Customer_Info]])-1)) -> Calgary | U354: =TRIM(RIGHT(RawSalesTable[[#This Row],[Customer_Info]], LEN(RawSalesTable[[#This Row],[Customer_Info]])-FIND(",",RawSalesTable[[#This Row],[Customer_Info]],FIND(",",RawSalesTable[[#This Row],[Customer_Info]])+1))) -> Consumer | V354: =VLOOKUP(RawSalesTable[[#This Row],[Product_ID]],ProductsTable[],2,FALSE) -> Pull-up Bar | W354: =VLOOKUP(RawSalesTable[[#This Row],[Product_ID]],ProductsTable[],3,FALSE) -> Fitness | X354: =VLOOKUP(RawSalesTable[[#This Row],[Product_ID]],ProductsTable[],5,FALSE) -> 125.4 | Y354: =RawSalesTable[[#This Row],[Quantity]]*RawSalesTable[[#This Row],[Unit_Price]] -> 236.69 | Z354: =RawSalesTable[[#This Row],[Gross_Sales]]*RawSalesTable[[#This Row],[Discount_Pct]] -> 11.8345 | AA354: =RawSalesTable[[#This Row],[Gross_Sales]]-RawSalesTable[[#This Row],[Discount_Amount]] -> 224.8555 | AB354: =RawSalesTable[[#This Row],[Unit_Cost]]*RawSalesTable[[#This Row],[Quantity]] -> 125.4 | AC354: =RawSalesTable[[#This Row],[Net_Sales]]-RawSalesTable[[#This Row],[Total_Cost]] -> 99.4555 | AD354: =RawSalesTable[[#This Row],[Profit]]/RawSalesTable[[#This Row],[Net_Sales]] -> 0.4423085 | AE354: =IF(RawSalesTable[[#This Row],[Return_Status]]="Yes",1,0) -> 0 | AF354: =YEAR(RawSalesTable[[#This Row],[Order_Date]]) -> 2025 | AG354: =MONTH(RawSalesTable[[#This Row],[Order_Date]]) -> 10 | AH354: =TEXT(RawSalesTable[[#This Row],[Order_Date]],"mmmm") -> octobre | AI354: =IF(RawSalesTable[[#This Row],[Month_Number]]<=3,"Q1",IF(RawSalesTable[[#This Row],[Month_Number]]<=6,"Q2",IF(RawSalesTable[[#This Row],[Month_Number]]<=9,"Q3","Q4"))) -> Q4 | AJ354: =DATE(YEAR(RawSalesTable[[#This Row],[Order_Date]]),MONTH(RawSalesTable[[#This Row],[Order_Date]]),1) -> 45931 | AK354: =VLOOKUP(RawSalesTable[[#This Row],[Customer_ID_clean]],CustomersTable[],4,FALSE) -> Alberta
A355: ORD-2025-00347 | B355: 45936 | C355: C0007 | D355: P1031 | E355: Lucas Wilson, Ottawa, Consumer | F355: Vancouver West | G355: N. Brown | H355: Online | I355: 2 | J355: 237.79 | K355: 0.1 | L355: Credit Card | M355: 7 | N355: No | O355: =SUBSTITUTE(PROPER(TRIM(RawSalesTable[[#This Row],[Channel_Raw]])), "Market Place", "Marketplace") -> Online | P355: =TRIM(RawSalesTable[[#This Row],[Store_Raw]]) -> Vancouver West | Q355: =IF(TRIM(RawSalesTable[[#This Row],[Payment_Method_Raw]])="","Non renseigné",SUBSTITUTE(TRIM(RawSalesTable[[#This Row],[Payment_Method_Raw]]),"CC","Credit Card")) -> Credit Card | R355: =UPPER(PROPER(RawSalesTable[[#This Row],[Customer_ID]])) -> C0007 | S355: =TRIM(LEFT(RawSalesTable[[#This Row],[Customer_Info]],FIND(",",RawSalesTable[[#This Row],[Customer_Info]]) -1)) -> Lucas Wilson | T355: =TRIM(MID(RawSalesTable[[#This Row],[Customer_Info]],FIND(",",RawSalesTable[[#This Row],[Customer_Info]])+1,FIND(",",RawSalesTable[[#This Row],[Customer_Info]],FIND(",",RawSalesTable[[#This Row],[Customer_Info]])+1)-FIND(",",RawSalesTable[[#This Row],[Customer_Info]])-1)) -> Ottawa | U355: =TRIM(RIGHT(RawSalesTable[[#This Row],[Customer_Info]], LEN(RawSalesTable[[#This Row],[Customer_Info]])-FIND(",",RawSalesTable[[#This Row],[Customer_Info]],FIND(",",RawSalesTable[[#This Row],[Customer_Info]])+1))) -> Consumer | V355: =VLOOKUP(RawSalesTable[[#This Row],[Product_ID]],ProductsTable[],2,FALSE) -> Dumbbell Set | W355: =VLOOKUP(RawSalesTable[[#This Row],[Product_ID]],ProductsTable[],3,FALSE) -> Fitness | X355: =VLOOKUP(RawSalesTable[[#This Row],[Product_ID]],ProductsTable[],5,FALSE) -> 131.73 | Y355: =RawSalesTable[[#This Row],[Quantity]]*RawSalesTable[[#This Row],[Unit_Price]] -> 475.58 | Z355: =RawSalesTable[[#This Row],[Gross_Sales]]*RawSalesTable[[#This Row],[Discount_Pct]] -> 47.558 | AA355: =RawSalesTable[[#This Row],[Gross_Sales]]-RawSalesTable[[#This Row],[Discount_Amount]] -> 428.022 | AB355: =RawSalesTable[[#This Row],[Unit_Cost]]*RawSalesTable[[#This Row],[Quantity]] -> 263.46 | AC355: =RawSalesTable[[#This Row],[Net_Sales]]-RawSalesTable[[#This Row],[Total_Cost]] -> 164.562 | AD355: =RawSalesTable[[#This Row],[Profit]]/RawSalesTable[[#This Row],[Net_Sales]] -> 0.38447089 | AE355: =IF(RawSalesTable[[#This Row],[Return_Status]]="Yes",1,0) -> 0 | AF355: =YEAR(RawSalesTable[[#This Row],[Order_Date]]) -> 2025 | AG355: =MONTH(RawSalesTable[[#This Row],[Order_Date]]) -> 10 | AH355: =TEXT(RawSalesTable[[#This Row],[Order_Date]],"mmmm") -> octobre | AI355: =IF(RawSalesTable[[#This Row],[Month_Number]]<=3,"Q1",IF(RawSalesTable[[#This Row],[Month_Number]]<=6,"Q2",IF(RawSalesTable[[#This Row],[Month_Number]]<=9,"Q3","Q4"))) -> Q4 | AJ355: =DATE(YEAR(RawSalesTable[[#This Row],[Order_Date]]),MONTH(RawSalesTable[[#This Row],[Order_Date]]),1) -> 45931 | AK355: =VLOOKUP(RawSalesTable[[#This Row],[Customer_ID_clean]],CustomersTable[],4,FALSE) -> Ontario
A356: ORD-2025-00348 | B356: 45782 | C356: C0009 | D356: P1019 | E356: Ethan Tremblay, Mississauga, Corporate | F356: Calgary North | G356: E. Roy | H356: Retail Store | I356: 4 | J356: 253.99 | K356: 0 | L356: CC | M356: 4 | N356: No | O356: =SUBSTITUTE(PROPER(TRIM(RawSalesTable[[#This Row],[Channel_Raw]])), "Market Place", "Marketplace") -> Retail Store | P356: =TRIM(RawSalesTable[[#This Row],[Store_Raw]]) -> Calgary North | Q356: =IF(TRIM(RawSalesTable[[#This Row],[Payment_Method_Raw]])="","Non renseigné",SUBSTITUTE(TRIM(RawSalesTable[[#This Row],[Payment_Method_Raw]]),"CC","Credit Card")) -> Credit Card | R356: =UPPER(PROPER(RawSalesTable[[#This Row],[Customer_ID]])) -> C0009 | S356: =TRIM(LEFT(RawSalesTable[[#This Row],[Customer_Info]],FIND(",",RawSalesTable[[#This Row],[Customer_Info]]) -1)) -> Ethan Tremblay | T356: =TRIM(MID(RawSalesTable[[#This Row],[Customer_Info]],FIND(",",RawSalesTable[[#This Row],[Customer_Info]])+1,FIND(",",RawSalesTable[[#This Row],[Customer_Info]],FIND(",",RawSalesTable[[#This Row],[Customer_Info]])+1)-FIND(",",RawSalesTable[[#This Row],[Customer_Info]])-1)) -> Mississauga | U356: =TRIM(RIGHT(RawSalesTable[[#This Row],[Customer_Info]], LEN(RawSalesTable[[#This Row],[Customer_Info]])-FIND(",",RawSalesTable[[#This Row],[Customer_Info]],FIND(",",RawSalesTable[[#This Row],[Customer_Info]])+1))) -> Corporate | V356: =VLOOKUP(RawSalesTable[[#This Row],[Product_ID]],ProductsTable[],2,FALSE) -> Vacuum | W356: =VLOOKUP(RawSalesTable[[#This Row],[Product_ID]],ProductsTable[],3,FALSE) -> Home | X356: =VLOOKUP(RawSalesTable[[#This Row],[Product_ID]],ProductsTable[],5,FALSE) -> 186.94 | Y356: =RawSalesTable[[#This Row],[Quantity]]*RawSalesTable[[#This Row],[Unit_Price]] -> 1015.96 | Z356: =RawSalesTable[[#This Row],[Gross_Sales]]*RawSalesTable[[#This Row],[Discount_Pct]] -> 0 | AA356: =RawSalesTable[[#This Row],[Gross_Sales]]-RawSalesTable[[#This Row],[Discount_Amount]] -> 1015.96 | AB356: =RawSalesTable[[#This Row],[Unit_Cost]]*RawSalesTable[[#This Row],[Quantity]] -> 747.76 | AC356: =RawSalesTable[[#This Row],[Net_Sales]]-RawSalesTable[[#This Row],[Total_Cost]] -> 268.2 | AD356: =RawSalesTable[[#This Row],[Profit]]/RawSalesTable[[#This Row],[Net_Sales]] -> 0.26398677 | AE356: =IF(RawSalesTable[[#This Row],[Return_Status]]="Yes",1,0) -> 0 | AF356: =YEAR(RawSalesTable[[#This Row],[Order_Date]]) -> 2025 | AG356: =MONTH(RawSalesTable[[#This Row],[Order_Date]]) -> 5 | AH356: =TEXT(RawSalesTable[[#This Row],[Order_Date]],"mmmm") -> mai | AI356: =IF(RawSalesTable[[#This Row],[Month_Number]]<=3,"Q1",IF(RawSalesTable[[#This Row],[Month_Number]]<=6,"Q2",IF(RawSalesTable[[#This Row],[Month_Number]]<=9,"Q3","Q4"))) -> Q2 | AJ356: =DATE(YEAR(RawSalesTable[[#This Row],[Order_Date]]),MONTH(RawSalesTable[[#This Row],[Order_Date]]),1) -> 45778 | AK356: =VLOOKUP(RawSalesTable[[#This Row],[Customer_ID_clean]],CustomersTable[],4,FALSE) -> Ontario
A357: ORD-2025-00349 | B357: 45836 | C357: C0052 | D357: P1027 | E357: Liam Bennett, Edmonton, Corporate | F357: Vancouver West | G357: J. Tremblay | H357: Online | I357: 1 | J357: 59.27 | K357: 0.1 | L357: Credit Card | M357: 1 | N357: No | O357: =SUBSTITUTE(PROPER(TRIM(RawSalesTable[[#This Row],[Channel_Raw]])), "Market Place", "Marketplace") -> Online | P357: =TRIM(RawSalesTable[[#This Row],[Store_Raw]]) -> Vancouver West | Q357: =IF(TRIM(RawSalesTable[[#This Row],[Payment_Method_Raw]])="","Non renseigné",SUBSTITUTE(TRIM(RawSalesTable[[#This Row],[Payment_Method_Raw]]),"CC","Credit Card")) -> Credit Card | R357: =UPPER(PROPER(RawSalesTable[[#This Row],[Customer_ID]])) -> C0052 | S357: =TRIM(LEFT(RawSalesTable[[#This Row],[Customer_Info]],FIND(",",RawSalesTable[[#This Row],[Customer_Info]]) -1)) -> Liam Bennett | T357: =TRIM(MID(RawSalesTable[[#This Row],[Customer_Info]],FIND(",",RawSalesTable[[#This Row],[Customer_Info]])+1,FIND(",",RawSalesTable[[#This Row],[Customer_Info]],FIND(",",RawSalesTable[[#This Row],[Customer_Info]])+1)-FIND(",",RawSalesTable[[#This Row],[Customer_Info]])-1)) -> Edmonton | U357: =TRIM(RIGHT(RawSalesTable[[#This Row],[Customer_Info]], LEN(RawSalesTable[[#This Row],[Customer_Info]])-FIND(",",RawSalesTable[[#This Row],[Customer_Info]],FIND(",",RawSalesTable[[#This Row],[Customer_Info]])+1))) -> Corporate | V357: =VLOOKUP(RawSalesTable[[#This Row],[Product_ID]],ProductsTable[],2,FALSE) -> Kettlebell | W357: =VLOOKUP(RawSalesTable[[#This Row],[Product_ID]],ProductsTable[],3,FALSE) -> Fitness | X357: =VLOOKUP(RawSalesTable[[#This Row],[Product_ID]],ProductsTable[],5,FALSE) -> 25.97 | Y357: =RawSalesTable[[#This Row],[Quantity]]*RawSalesTable[[#This Row],[Unit_Price]] -> 59.27 | Z357: =RawSalesTable[[#This Row],[Gross_Sales]]*RawSalesTable[[#This Row],[Discount_Pct]] -> 5.927 | AA357: =RawSalesTable[[#This Row],[Gross_Sales]]-RawSalesTable[[#This Row],[Discount_Amount]] -> 53.343 | AB357: =RawSalesTable[[#This Row],[Unit_Cost]]*RawSalesTable[[#This Row],[Quantity]] -> 25.97 | AC357: =RawSalesTable[[#This Row],[Net_Sales]]-RawSalesTable[[#This Row],[Total_Cost]] -> 27.373 | AD357: =RawSalesTable[[#This Row],[Profit]]/RawSalesTable[[#This Row],[Net_Sales]] -> 0.51315074 | AE357: =IF(RawSalesTable[[#This Row],[Return_Status]]="Yes",1,0) -> 0 | AF357: =YEAR(RawSalesTable[[#This Row],[Order_Date]]) -> 2025 | AG357: =MONTH(RawSalesTable[[#This Row],[Order_Date]]) -> 6 | AH357: =TEXT(RawSalesTable[[#This Row],[Order_Date]],"mmmm") -> juin | AI357: =IF(RawSalesTable[[#This Row],[Month_Number]]<=3,"Q1",IF(RawSalesTable[[#This Row],[Month_Number]]<=6,"Q2",IF(RawSalesTable[[#This Row],[Month_Number]]<=9,"Q3","Q4"))) -> Q2 | AJ357: =DATE(YEAR(RawSalesTable[[#This Row],[Order_Date]]),MONTH(RawSalesTable[[#This Row],[Order_Date]]),1) -> 45809 | AK357: =VLOOKUP(RawSalesTable[[#This Row],[Customer_ID_clean]],CustomersTable[],4,FALSE) -> Alberta
A358: ORD-2025-00350 | B358: 45896 | C358: C0096 | D358: P1005 | E358: Ryan Roy, Laval, Corporate | F358: Calgary North | G358: R. Singh | H358: Online | I358: 1 | J358: 244.01 | K358: 0.05 | L358: Credit Card | M358: 6 | N358: Yes | O358: =SUBSTITUTE(PROPER(TRIM(RawSalesTable[[#This Row],[Channel_Raw]])), "Market Place", "Marketplace") -> Online | P358: =TRIM(RawSalesTable[[#This Row],[Store_Raw]]) -> Calgary North | Q358: =IF(TRIM(RawSalesTable[[#This Row],[Payment_Method_Raw]])="","Non renseigné",SUBSTITUTE(TRIM(RawSalesTable[[#This Row],[Payment_Method_Raw]]),"CC","Credit Card")) -> Credit Card | R358: =UPPER(PROPER(RawSalesTable[[#This Row],[Customer_ID]])) -> C0096 | S358: =TRIM(LEFT(RawSalesTable[[#This Row],[Customer_Info]],FIND(",",RawSalesTable[[#This Row],[Customer_Info]]) -1)) -> Ryan Roy | T358: =TRIM(MID(RawSalesTable[[#This Row],[Customer_Info]],FIND(",",RawSalesTable[[#This Row],[Customer_Info]])+1,FIND(",",RawSalesTable[[#This Row],[Customer_Info]],FIND(",",RawSalesTable[[#This Row],[Customer_Info]])+1)-FIND(",",RawSalesTable[[#This Row],[Customer_Info]])-1)) -> Laval | U358: =TRIM(RIGHT(RawSalesTable[[#This Row],[Customer_Info]], LEN(RawSalesTable[[#This Row],[Customer_Info]])-FIND(",",RawSalesTable[[#This Row],[Customer_Info]],FIND(",",RawSalesTable[[#This Row],[Customer_Info]])+1))) -> Corporate | V358: =VLOOKUP(RawSalesTable[[#This Row],[Product_ID]],ProductsTable[],2,FALSE) -> Portable SSD | W358: =VLOOKUP(RawSalesTable[[#This Row],[Product_ID]],ProductsTable[],3,FALSE) -> Electronics | X358: =VLOOKUP(RawSalesTable[[#This Row],[Product_ID]],ProductsTable[],5,FALSE) -> 131.19 | Y358: =RawSalesTable[[#This Row],[Quantity]]*RawSalesTable[[#This Row],[Unit_Price]] -> 244.01 | Z358: =RawSalesTable[[#This Row],[Gross_Sales]]*RawSalesTable[[#This Row],[Discount_Pct]] -> 12.2005 | AA358: =RawSalesTable[[#This Row],[Gross_Sales]]-RawSalesTable[[#This Row],[Discount_Amount]] -> 231.8095 | AB358: =RawSalesTable[[#This Row],[Unit_Cost]]*RawSalesTable[[#This Row],[Quantity]] -> 131.19 | AC358: =RawSalesTable[[#This Row],[Net_Sales]]-RawSalesTable[[#This Row],[Total_Cost]] -> 100.6195 | AD358: =RawSalesTable[[#This Row],[Profit]]/RawSalesTable[[#This Row],[Net_Sales]] -> 0.43406116 | AE358: =IF(RawSalesTable[[#This Row],[Return_Status]]="Yes",1,0) -> 1 | AF358: =YEAR(RawSalesTable[[#This Row],[Order_Date]]) -> 2025 | AG358: =MONTH(RawSalesTable[[#This Row],[Order_Date]]) -> 8 | AH358: =TEXT(RawSalesTable[[#This Row],[Order_Date]],"mmmm") -> août | AI358: =IF(RawSalesTable[[#This Row],[Month_Number]]<=3,"Q1",IF(RawSalesTable[[#This Row],[Month_Number]]<=6,"Q2",IF(RawSalesTable[[#This Row],[Month_Number]]<=9,"Q3","Q4"))) -> Q3 | AJ358: =DATE(YEAR(RawSalesTable[[#This Row],[Order_Date]]),MONTH(RawSalesTable[[#This Row],[Order_Date]]),1) -> 45870 | AK358: =VLOOKUP(RawSalesTable[[#This Row],[Customer_ID_clean]],CustomersTable[],4,FALSE) -> Quebec
A359: ORD-2025-00351 | B359: 45777 | C359: C0006 | D359: P1031 | E359: Nora Wilson, Laval, Consumer | F359: Calgary North | G359: M. Wilson | H359: retail store | I359: 3 | J359: 255.82 | K359: 0 | L359: PayPal | M359: 4 | N359: No | O359: =SUBSTITUTE(PROPER(TRIM(RawSalesTable[[#This Row],[Channel_Raw]])), "Market Place", "Marketplace") -> Retail Store | P359: =TRIM(RawSalesTable[[#This Row],[Store_Raw]]) -> Calgary North | Q359: =IF(TRIM(RawSalesTable[[#This Row],[Payment_Method_Raw]])="","Non renseigné",SUBSTITUTE(TRIM(RawSalesTable[[#This Row],[Payment_Method_Raw]]),"CC","Credit Card")) -> PayPal | R359: =UPPER(PROPER(RawSalesTable[[#This Row],[Customer_ID]])) -> C0006 | S359: =TRIM(LEFT(RawSalesTable[[#This Row],[Customer_Info]],FIND(",",RawSalesTable[[#This Row],[Customer_Info]]) -1)) -> Nora Wilson | T359: =TRIM(MID(RawSalesTable[[#This Row],[Customer_Info]],FIND(",",RawSalesTable[[#This Row],[Customer_Info]])+1,FIND(",",RawSalesTable[[#This Row],[Customer_Info]],FIND(",",RawSalesTable[[#This Row],[Customer_Info]])+1)-FIND(",",RawSalesTable[[#This Row],[Customer_Info]])-1)) -> Laval | U359: =TRIM(RIGHT(RawSalesTable[[#This Row],[Customer_Info]], LEN(RawSalesTable[[#This Row],[Customer_Info]])-FIND(",",RawSalesTable[[#This Row],[Customer_Info]],FIND(",",RawSalesTable[[#This Row],[Customer_Info]])+1))) -> Consumer | V359: =VLOOKUP(RawSalesTable[[#This Row],[Product_ID]],ProductsTable[],2,FALSE) -> Dumbbell Set | W359: =VLOOKUP(RawSalesTable[[#This Row],[Product_ID]],ProductsTable[],3,FALSE) -> Fitness | X359: =VLOOKUP(RawSalesTable[[#This Row],[Product_ID]],ProductsTable[],5,FALSE) -> 131.73 | Y359: =RawSalesTable[[#This Row],[Quantity]]*RawSalesTable[[#This Row],[Unit_Price]] -> 767.46 | Z359: =RawSalesTable[[#This Row],[Gross_Sales]]*RawSalesTable[[#This Row],[Discount_Pct]] -> 0 | AA359: =RawSalesTable[[#This Row],[Gross_Sales]]-RawSalesTable[[#This Row],[Discount_Amount]] -> 767.46 | AB359: =RawSalesTable[[#This Row],[Unit_Cost]]*RawSalesTable[[#This Row],[Quantity]] -> 395.19 | AC359: =RawSalesTable[[#This Row],[Net_Sales]]-RawSalesTable[[#This Row],[Total_Cost]] -> 372.27 | AD359: =RawSalesTable[[#This Row],[Profit]]/RawSalesTable[[#This Row],[Net_Sales]] -> 0.48506763 | AE359: =IF(RawSalesTable[[#This Row],[Return_Status]]="Yes",1,0) -> 0 | AF359: =YEAR(RawSalesTable[[#This Row],[Order_Date]]) -> 2025 | AG359: =MONTH(RawSalesTable[[#This Row],[Order_Date]]) -> 4 | AH359: =TEXT(RawSalesTable[[#This Row],[Order_Date]],"mmmm") -> avril | AI359: =IF(RawSalesTable[[#This Row],[Month_Number]]<=3,"Q1",IF(RawSalesTable[[#This Row],[Month_Number]]<=6,"Q2",IF(RawSalesTable[[#This Row],[Month_Number]]<=9,"Q3","Q4"))) -> Q2 | AJ359: =DATE(YEAR(RawSalesTable[[#This Row],[Order_Date]]),MONTH(RawSalesTable[[#This Row],[Order_Date]]),1) -> 45748 | AK359: =VLOOKUP(RawSalesTable[[#This Row],[Customer_ID_clean]],CustomersTable[],4,FALSE) -> Quebec
A360: ORD-2025-00352 | B360: 45878 | C360: C0091 | D360: P1003 | E360: Leo Taylor , Victoria , Small Business | F360: Toronto Downtown | G360: N. Brown | H360: Marketplace | I360: 2 | J360: 164.5 | K360: 0 | L360: PayPal | M360: 2 | N360: No | O360: =SUBSTITUTE(PROPER(TRIM(RawSalesTable[[#This Row],[Channel_Raw]])), "Market Place", "Marketplace") -> Marketplace | P360: =TRIM(RawSalesTable[[#This Row],[Store_Raw]]) -> Toronto Downtown | Q360: =IF(TRIM(RawSalesTable[[#This Row],[Payment_Method_Raw]])="","Non renseigné",SUBSTITUTE(TRIM(RawSalesTable[[#This Row],[Payment_Method_Raw]]),"CC","Credit Card")) -> PayPal | R360: =UPPER(PROPER(RawSalesTable[[#This Row],[Customer_ID]])) -> C0091 | S360: =TRIM(LEFT(RawSalesTable[[#This Row],[Customer_Info]],FIND(",",RawSalesTable[[#This Row],[Customer_Info]]) -1)) -> Leo Taylor | T360: =TRIM(MID(RawSalesTable[[#This Row],[Customer_Info]],FIND(",",RawSalesTable[[#This Row],[Customer_Info]])+1,FIND(",",RawSalesTable[[#This Row],[Customer_Info]],FIND(",",RawSalesTable[[#This Row],[Customer_Info]])+1)-FIND(",",RawSalesTable[[#This Row],[Customer_Info]])-1)) -> Victoria | U360: =TRIM(RIGHT(RawSalesTable[[#This Row],[Customer_Info]], LEN(RawSalesTable[[#This Row],[Customer_Info]])-FIND(",",RawSalesTable[[#This Row],[Customer_Info]],FIND(",",RawSalesTable[[#This Row],[Customer_Info]])+1))) -> Small Business | V360: =VLOOKUP(RawSalesTable[[#This Row],[Product_ID]],ProductsTable[],2,FALSE) -> Mouse | W360: =VLOOKUP(RawSalesTable[[#This Row],[Product_ID]],ProductsTable[],3,FALSE) -> Electronics | X360: =VLOOKUP(RawSalesTable[[#This Row],[Product_ID]],ProductsTable[],5,FALSE) -> 106.4 | Y360: =RawSalesTable[[#This Row],[Quantity]]*RawSalesTable[[#This Row],[Unit_Price]] -> 329 | Z360: =RawSalesTable[[#This Row],[Gross_Sales]]*RawSalesTable[[#This Row],[Discount_Pct]] -> 0 | AA360: =RawSalesTable[[#This Row],[Gross_Sales]]-RawSalesTable[[#This Row],[Discount_Amount]] -> 329 | AB360: =RawSalesTable[[#This Row],[Unit_Cost]]*RawSalesTable[[#This Row],[Quantity]] -> 212.8 | AC360: =RawSalesTable[[#This Row],[Net_Sales]]-RawSalesTable[[#This Row],[Total_Cost]] -> 116.2 | AD360: =RawSalesTable[[#This Row],[Profit]]/RawSalesTable[[#This Row],[Net_Sales]] -> 0.35319149 | AE360: =IF(RawSalesTable[[#This Row],[Return_Status]]="Yes",1,0) -> 0 | AF360: =YEAR(RawSalesTable[[#This Row],[Order_Date]]) -> 2025 | AG360: =MONTH(RawSalesTable[[#This Row],[Order_Date]]) -> 8 | AH360: =TEXT(RawSalesTable[[#This Row],[Order_Date]],"mmmm") -> août | AI360: =IF(RawSalesTable[[#This Row],[Month_Number]]<=3,"Q1",IF(RawSalesTable[[#This Row],[Month_Number]]<=6,"Q2",IF(RawSalesTable[[#This Row],[Month_Number]]<=9,"Q3","Q4"))) -> Q3 | AJ360: =DATE(YEAR(RawSalesTable[[#This Row],[Order_Date]]),MONTH(RawSalesTable[[#This Row],[Order_Date]]),1) -> 45870 | AK360: =VLOOKUP(RawSalesTable[[#This Row],[Customer_ID_clean]],CustomersTable[],4,FALSE) -> British Columbia
A361: ORD-2025-00353 | B361: 45666 | C361: C0003 | D361: P1023 | E361: Amelia Young, Ottawa, Corporate | F361: Montreal Central | G361: A. Morgan | H361: Retail Store | I361: 1 | J361: 339.34 | K361: 0.05 | L361: Credit Card | M361: 0 | N361: No | O361: =SUBSTITUTE(PROPER(TRIM(RawSalesTable[[#This Row],[Channel_Raw]])), "Market Place", "Marketplace") -> Retail Store | P361: =TRIM(RawSalesTable[[#This Row],[Store_Raw]]) -> Montreal Central | Q361: =IF(TRIM(RawSalesTable[[#This Row],[Payment_Method_Raw]])="","Non renseigné",SUBSTITUTE(TRIM(RawSalesTable[[#This Row],[Payment_Method_Raw]]),"CC","Credit Card")) -> Credit Card | R361: =UPPER(PROPER(RawSalesTable[[#This Row],[Customer_ID]])) -> C0003 | S361: =TRIM(LEFT(RawSalesTable[[#This Row],[Customer_Info]],FIND(",",RawSalesTable[[#This Row],[Customer_Info]]) -1)) -> Amelia Young | T361: =TRIM(MID(RawSalesTable[[#This Row],[Customer_Info]],FIND(",",RawSalesTable[[#This Row],[Customer_Info]])+1,FIND(",",RawSalesTable[[#This Row],[Customer_Info]],FIND(",",RawSalesTable[[#This Row],[Customer_Info]])+1)-FIND(",",RawSalesTable[[#This Row],[Customer_Info]])-1)) -> Ottawa | U361: =TRIM(RIGHT(RawSalesTable[[#This Row],[Customer_Info]], LEN(RawSalesTable[[#This Row],[Customer_Info]])-FIND(",",RawSalesTable[[#This Row],[Customer_Info]],FIND(",",RawSalesTable[[#This Row],[Customer_Info]])+1))) -> Corporate | V361: =VLOOKUP(RawSalesTable[[#This Row],[Product_ID]],ProductsTable[],2,FALSE) -> Toaster | W361: =VLOOKUP(RawSalesTable[[#This Row],[Product_ID]],ProductsTable[],3,FALSE) -> Home | X361: =VLOOKUP(RawSalesTable[[#This Row],[Product_ID]],ProductsTable[],5,FALSE) -> 152.88 | Y361: =RawSalesTable[[#This Row],[Quantity]]*RawSalesTable[[#This Row],[Unit_Price]] -> 339.34 | Z361: =RawSalesTable[[#This Row],[Gross_Sales]]*RawSalesTable[[#This Row],[Discount_Pct]] -> 16.967 | AA361: =RawSalesTable[[#This Row],[Gross_Sales]]-RawSalesTable[[#This Row],[Discount_Amount]] -> 322.373 | AB361: =RawSalesTable[[#This Row],[Unit_Cost]]*RawSalesTable[[#This Row],[Quantity]] -> 152.88 | AC361: =RawSalesTable[[#This Row],[Net_Sales]]-RawSalesTable[[#This Row],[Total_Cost]] -> 169.493 | AD361: =RawSalesTable[[#This Row],[Profit]]/RawSalesTable[[#This Row],[Net_Sales]] -> 0.52576674 | AE361: =IF(RawSalesTable[[#This Row],[Return_Status]]="Yes",1,0) -> 0 | AF361: =YEAR(RawSalesTable[[#This Row],[Order_Date]]) -> 2025 | AG361: =MONTH(RawSalesTable[[#This Row],[Order_Date]]) -> 1 | AH361: =TEXT(RawSalesTable[[#This Row],[Order_Date]],"mmmm") -> janvier | AI361: =IF(RawSalesTable[[#This Row],[Month_Number]]<=3,"Q1",IF(RawSalesTable[[#This Row],[Month_Number]]<=6,"Q2",IF(RawSalesTable[[#This Row],[Month_Number]]<=9,"Q3","Q4"))) -> Q1 | AJ361: =DATE(YEAR(RawSalesTable[[#This Row],[Order_Date]]),MONTH(RawSalesTable[[#This Row],[Order_Date]]),1) -> 45658 | AK361: =VLOOKUP(RawSalesTable[[#This Row],[Customer_ID_clean]],CustomersTable[],4,FALSE) -> Ontario
A362: ORD-2025-00354 | B362: 46016 | C362: C0088 | D362: P1029 | E362: Olivia Bennett, Vancouver, Small Business | F362: Online Fulfillment | G362: M. Wilson | H362: Retail Store | I362: 2 | J362: 191.38 | K362: 0.15 | L362: PayPal | M362: 2 | N362: No | O362: =SUBSTITUTE(PROPER(TRIM(RawSalesTable[[#This Row],[Channel_Raw]])), "Market Place", "Marketplace") -> Retail Store | P362: =TRIM(RawSalesTable[[#This Row],[Store_Raw]]) -> Online Fulfillment | Q362: =IF(TRIM(RawSalesTable[[#This Row],[Payment_Method_Raw]])="","Non renseigné",SUBSTITUTE(TRIM(RawSalesTable[[#This Row],[Payment_Method_Raw]]),"CC","Credit Card")) -> PayPal | R362: =UPPER(PROPER(RawSalesTable[[#This Row],[Customer_ID]])) -> C0088 | S362: =TRIM(LEFT(RawSalesTable[[#This Row],[Customer_Info]],FIND(",",RawSalesTable[[#This Row],[Customer_Info]]) -1)) -> Olivia Bennett | T362: =TRIM(MID(RawSalesTable[[#This Row],[Customer_Info]],FIND(",",RawSalesTable[[#This Row],[Customer_Info]])+1,FIND(",",RawSalesTable[[#This Row],[Customer_Info]],FIND(",",RawSalesTable[[#This Row],[Customer_Info]])+1)-FIND(",",RawSalesTable[[#This Row],[Customer_Info]])-1)) -> Vancouver | U362: =TRIM(RIGHT(RawSalesTable[[#This Row],[Customer_Info]], LEN(RawSalesTable[[#This Row],[Customer_Info]])-FIND(",",RawSalesTable[[#This Row],[Customer_Info]],FIND(",",RawSalesTable[[#This Row],[Customer_Info]])+1))) -> Small Business | V362: =VLOOKUP(RawSalesTable[[#This Row],[Product_ID]],ProductsTable[],2,FALSE) -> Jump Rope | W362: =VLOOKUP(RawSalesTable[[#This Row],[Product_ID]],ProductsTable[],3,FALSE) -> Fitness | X362: =VLOOKUP(RawSalesTable[[#This Row],[Product_ID]],ProductsTable[],5,FALSE) -> 101 | Y362: =RawSalesTable[[#This Row],[Quantity]]*RawSalesTable[[#This Row],[Unit_Price]] -> 382.76 | Z362: =RawSalesTable[[#This Row],[Gross_Sales]]*RawSalesTable[[#This Row],[Discount_Pct]] -> 57.414 | AA362: =RawSalesTable[[#This Row],[Gross_Sales]]-RawSalesTable[[#This Row],[Discount_Amount]] -> 325.346 | AB362: =RawSalesTable[[#This Row],[Unit_Cost]]*RawSalesTable[[#This Row],[Quantity]] -> 202 | AC362: =RawSalesTable[[#This Row],[Net_Sales]]-RawSalesTable[[#This Row],[Total_Cost]] -> 123.346 | AD362: =RawSalesTable[[#This Row],[Profit]]/RawSalesTable[[#This Row],[Net_Sales]] -> 0.37912253 | AE362: =IF(RawSalesTable[[#This Row],[Return_Status]]="Yes",1,0) -> 0 | AF362: =YEAR(RawSalesTable[[#This Row],[Order_Date]]) -> 2025 | AG362: =MONTH(RawSalesTable[[#This Row],[Order_Date]]) -> 12 | AH362: =TEXT(RawSalesTable[[#This Row],[Order_Date]],"mmmm") -> décembre | AI362: =IF(RawSalesTable[[#This Row],[Month_Number]]<=3,"Q1",IF(RawSalesTable[[#This Row],[Month_Number]]<=6,"Q2",IF(RawSalesTable[[#This Row],[Month_Number]]<=9,"Q3","Q4"))) -> Q4 | AJ362: =DATE(YEAR(RawSalesTable[[#This Row],[Order_Date]]),MONTH(RawSalesTable[[#This Row],[Order_Date]]),1) -> 45992 | AK362: =VLOOKUP(RawSalesTable[[#This Row],[Customer_ID_clean]],CustomersTable[],4,FALSE) -> British Columbia
A363: ORD-2025-00355 | B363: 45771 | C363: C0010 | D363: P1019 | E363: Ethan Martin, Victoria, Corporate | F363: Toronto Downtown | G363: N. Brown | H363: Online | I363: 2 | J363: 283.28 | K363: 0.1 | L363: CC | M363: 4 | N363: Yes | O363: =SUBSTITUTE(PROPER(TRIM(RawSalesTable[[#This Row],[Channel_Raw]])), "Market Place", "Marketplace") -> Online | P363: =TRIM(RawSalesTable[[#This Row],[Store_Raw]]) -> Toronto Downtown | Q363: =IF(TRIM(RawSalesTable[[#This Row],[Payment_Method_Raw]])="","Non renseigné",SUBSTITUTE(TRIM(RawSalesTable[[#This Row],[Payment_Method_Raw]]),"CC","Credit Card")) -> Credit Card | R363: =UPPER(PROPER(RawSalesTable[[#This Row],[Customer_ID]])) -> C0010 | S363: =TRIM(LEFT(RawSalesTable[[#This Row],[Customer_Info]],FIND(",",RawSalesTable[[#This Row],[Customer_Info]]) -1)) -> Ethan Martin | T363: =TRIM(MID(RawSalesTable[[#This Row],[Customer_Info]],FIND(",",RawSalesTable[[#This Row],[Customer_Info]])+1,FIND(",",RawSalesTable[[#This Row],[Customer_Info]],FIND(",",RawSalesTable[[#This Row],[Customer_Info]])+1)-FIND(",",RawSalesTable[[#This Row],[Customer_Info]])-1)) -> Victoria | U363: =TRIM(RIGHT(RawSalesTable[[#This Row],[Customer_Info]], LEN(RawSalesTable[[#This Row],[Customer_Info]])-FIND(",",RawSalesTable[[#This Row],[Customer_Info]],FIND(",",RawSalesTable[[#This Row],[Customer_Info]])+1))) -> Corporate | V363: =VLOOKUP(RawSalesTable[[#This Row],[Product_ID]],ProductsTable[],2,FALSE) -> Vacuum | W363: =VLOOKUP(RawSalesTable[[#This Row],[Product_ID]],ProductsTable[],3,FALSE) -> Home | X363: =VLOOKUP(RawSalesTable[[#This Row],[Product_ID]],ProductsTable[],5,FALSE) -> 186.94 | Y363: =RawSalesTable[[#This Row],[Quantity]]*RawSalesTable[[#This Row],[Unit_Price]] -> 566.56 | Z363: =RawSalesTable[[#This Row],[Gross_Sales]]*RawSalesTable[[#This Row],[Discount_Pct]] -> 56.656 | AA363: =RawSalesTable[[#This Row],[Gross_Sales]]-RawSalesTable[[#This Row],[Discount_Amount]] -> 509.904 | AB363: =RawSalesTable[[#This Row],[Unit_Cost]]*RawSalesTable[[#This Row],[Quantity]] -> 373.88 | AC363: =RawSalesTable[[#This Row],[Net_Sales]]-RawSalesTable[[#This Row],[Total_Cost]] -> 136.024 | AD363: =RawSalesTable[[#This Row],[Profit]]/RawSalesTable[[#This Row],[Net_Sales]] -> 0.26676394 | AE363: =IF(RawSalesTable[[#This Row],[Return_Status]]="Yes",1,0) -> 1 | AF363: =YEAR(RawSalesTable[[#This Row],[Order_Date]]) -> 2025 | AG363: =MONTH(RawSalesTable[[#This Row],[Order_Date]]) -> 4 | AH363: =TEXT(RawSalesTable[[#This Row],[Order_Date]],"mmmm") -> avril | AI363: =IF(RawSalesTable[[#This Row],[Month_Number]]<=3,"Q1",IF(RawSalesTable[[#This Row],[Month_Number]]<=6,"Q2",IF(RawSalesTable[[#This Row],[Month_Number]]<=9,"Q3","Q4"))) -> Q2 | AJ363: =DATE(YEAR(RawSalesTable[[#This Row],[Order_Date]]),MONTH(RawSalesTable[[#This Row],[Order_Date]]),1) -> 45748 | AK363: =VLOOKUP(RawSalesTable[[#This Row],[Customer_ID_clean]],CustomersTable[],4,FALSE) -> British Columbia
... A366: ORD-2025-00358 | B366: 45878 | C366: C0096 | D366: P1012 | E366: Ryan Roy, Laval, Corporate | F366: Montreal Central | G366: N. Brown | H366: Online | I366: 2 | J366: 85.44 | K366: 0.1 | L366: Credit Card | M366: 7 | N366: Yes | O366: =SUBSTITUTE(PROPER(TRIM(RawSalesTable[[#This Row],[Channel_Raw]])), "Market Place", "Marketplace") -> Online | P366: =TRIM(RawSalesTable[[#This Row],[Store_Raw]]) -> Montreal Central | Q366: =IF(TRIM(RawSalesTable[[#This Row],[Payment_Method_Raw]])="","Non renseigné",SUBSTITUTE(TRIM(RawSalesTable[[#This Row],[Payment_Method_Raw]]),"CC","Credit Card")) -> Credit Card | R366: =UPPER(PROPER(RawSalesTable[[#This Row],[Customer_ID]])) -> C0096 | S366: =TRIM(LEFT(RawSalesTable[[#This Row],[Customer_Info]],FIND(",",RawSalesTable[[#This Row],[Customer_Info]]) -1)) -> Ryan Roy | T366: =TRIM(MID(RawSalesTable[[#This Row],[Customer_Info]],FIND(",",RawSalesTable[[#This Row],[Customer_Info]])+1,FIND(",",RawSalesTable[[#This Row],[Customer_Info]],FIND(",",RawSalesTable[[#This Row],[Customer_Info]])+1)-FIND(",",RawSalesTable[[#This Row],[Customer_Info]])-1)) -> Laval | U366: =TRIM(RIGHT(RawSalesTable[[#This Row],[Customer_Info]], LEN(RawSalesTable[[#This Row],[Customer_Info]])-FIND(",",RawSalesTable[[#This Row],[Customer_Info]],FIND(",",RawSalesTable[[#This Row],[Customer_Info]])+1))) -> Corporate | V366: =VLOOKUP(RawSalesTable[[#This Row],[Product_ID]],ProductsTable[],2,FALSE) -> Standing Desk | W366: =VLOOKUP(RawSalesTable[[#This Row],[Product_ID]],ProductsTable[],3,FALSE) -> Office | X366: =VLOOKUP(RawSalesTable[[#This Row],[Product_ID]],ProductsTable[],5,FALSE) -> 45.17 | Y366: =RawSalesTable[[#This Row],[Quantity]]*RawSalesTable[[#This Row],[Unit_Price]] -> 170.88 | Z366: =RawSalesTable[[#This Row],[Gross_Sales]]*RawSalesTable[[#This Row],[Discount_Pct]] -> 17.088 | AA366: =RawSalesTable[[#This Row],[Gross_Sales]]-RawSalesTable[[#This Row],[Discount_Amount]] -> 153.792 | AB366: =RawSalesTable[[#This Row],[Unit_Cost]]*RawSalesTable[[#This Row],[Quantity]] -> 90.34 | AC366: =RawSalesTable[[#This Row],[Net_Sales]]-RawSalesTable[[#This Row],[Total_Cost]] -> 63.452 | AD366: =RawSalesTable[[#This Row],[Profit]]/RawSalesTable[[#This Row],[Net_Sales]] -> 0.41258323 | AE366: =IF(RawSalesTable[[#This Row],[Return_Status]]="Yes",1,0) -> 1 | AF366: =YEAR(RawSalesTable[[#This Row],[Order_Date]]) -> 2025 | AG366: =MONTH(RawSalesTable[[#This Row],[Order_Date]]) -> 8 | AH366: =TEXT(RawSalesTable[[#This Row],[Order_Date]],"mmmm") -> août | AI366: =IF(RawSalesTable[[#This Row],[Month_Number]]<=3,"Q1",IF(RawSalesTable[[#This Row],[Month_Number]]<=6,"Q2",IF(RawSalesTable[[#This Row],[Month_Number]]<=9,"Q3","Q4"))) -> Q3 | AJ366: =DATE(YEAR(RawSalesTable[[#This Row],[Order_Date]]),MONTH(RawSalesTable[[#This Row],[Order_Date]]),1) -> 45870 | AK366: =VLOOKUP(RawSalesTable[[#This Row],[Customer_ID_clean]],CustomersTable[],4,FALSE) -> Quebec
A367: ORD-2025-00359 | B367: 45825 | C367: C0008 | D367: P1007 | E367: Mia Wilson, Calgary, Consumer | F367: Toronto Downtown | G367: A. Morgan | H367: Online | I367: 2 | J367: 364.57 | K367: 0.15 | M367: 1 | N367: No | O367: =SUBSTITUTE(PROPER(TRIM(RawSalesTable[[#This Row],[Channel_Raw]])), "Market Place", "Marketplace") -> Online | P367: =TRIM(RawSalesTable[[#This Row],[Store_Raw]]) -> Toronto Downtown | Q367: =IF(TRIM(RawSalesTable[[#This Row],[Payment_Method_Raw]])="","Non renseigné",SUBSTITUTE(TRIM(RawSalesTable[[#This Row],[Payment_Method_Raw]]),"CC","Credit Card")) -> Non renseigné | R367: =UPPER(PROPER(RawSalesTable[[#This Row],[Customer_ID]])) -> C0008 | S367: =TRIM(LEFT(RawSalesTable[[#This Row],[Customer_Info]],FIND(",",RawSalesTable[[#This Row],[Customer_Info]]) -1)) -> Mia Wilson | T367: =TRIM(MID(RawSalesTable[[#This Row],[Customer_Info]],FIND(",",RawSalesTable[[#This Row],[Customer_Info]])+1,FIND(",",RawSalesTable[[#This Row],[Customer_Info]],FIND(",",RawSalesTable[[#This Row],[Customer_Info]])+1)-FIND(",",RawSalesTable[[#This Row],[Customer_Info]])-1)) -> Calgary | U367: =TRIM(RIGHT(RawSalesTable[[#This Row],[Customer_Info]], LEN(RawSalesTable[[#This Row],[Customer_Info]])-FIND(",",RawSalesTable[[#This Row],[Customer_Info]],FIND(",",RawSalesTable[[#This Row],[Customer_Info]])+1))) -> Consumer | V367: =VLOOKUP(RawSalesTable[[#This Row],[Product_ID]],ProductsTable[],2,FALSE) -> Monitor | W367: =VLOOKUP(RawSalesTable[[#This Row],[Product_ID]],ProductsTable[],3,FALSE) -> Electronics | X367: =VLOOKUP(RawSalesTable[[#This Row],[Product_ID]],ProductsTable[],5,FALSE) -> 224.47 | Y367: =RawSalesTable[[#This Row],[Quantity]]*RawSalesTable[[#This Row],[Unit_Price]] -> 729.14 | Z367: =RawSalesTable[[#This Row],[Gross_Sales]]*RawSalesTable[[#This Row],[Discount_Pct]] -> 109.371 | AA367: =RawSalesTable[[#This Row],[Gross_Sales]]-RawSalesTable[[#This Row],[Discount_Amount]] -> 619.769 | AB367: =RawSalesTable[[#This Row],[Unit_Cost]]*RawSalesTable[[#This Row],[Quantity]] -> 448.94 | AC367: =RawSalesTable[[#This Row],[Net_Sales]]-RawSalesTable[[#This Row],[Total_Cost]] -> 170.829 | AD367: =RawSalesTable[[#This Row],[Profit]]/RawSalesTable[[#This Row],[Net_Sales]] -> 0.27563334 | AE367: =IF(RawSalesTable[[#This Row],[Return_Status]]="Yes",1,0) -> 0 | AF367: =YEAR(RawSalesTable[[#This Row],[Order_Date]]) -> 2025 | AG367: =MONTH(RawSalesTable[[#This Row],[Order_Date]]) -> 6 | AH367: =TEXT(RawSalesTable[[#This Row],[Order_Date]],"mmmm") -> juin | AI367: =IF(RawSalesTable[[#This Row],[Month_Number]]<=3,"Q1",IF(RawSalesTable[[#This Row],[Month_Number]]<=6,"Q2",IF(RawSalesTable[[#This Row],[Month_Number]]<=9,"Q3","Q4"))) -> Q2 | AJ367: =DATE(YEAR(RawSalesTable[[#This Row],[Order_Date]]),MONTH(RawSalesTable[[#This Row],[Order_Date]]),1) -> 45809 | AK367: =VLOOKUP(RawSalesTable[[#This Row],[Customer_ID_clean]],CustomersTable[],4,FALSE) -> Alberta
A368: ORD-2025-00360 | B368: 45756 | C368: C0091 | D368: P1018 | E368: Leo Taylor, Victoria, Small Business | F368: Toronto Downtown | G368: N. Brown | H368: Online | I368: 1 | J368: 31.76 | K368: 0.05 | L368: Credit Card | M368: 7 | N368: No | O368: =SUBSTITUTE(PROPER(TRIM(RawSalesTable[[#This Row],[Channel_Raw]])), "Market Place", "Marketplace") -> Online | P368: =TRIM(RawSalesTable[[#This Row],[Store_Raw]]) -> Toronto Downtown | Q368: =IF(TRIM(RawSalesTable[[#This Row],[Payment_Method_Raw]])="","Non renseigné",SUBSTITUTE(TRIM(RawSalesTable[[#This Row],[Payment_Method_Raw]]),"CC","Credit Card")) -> Credit Card | R368: =UPPER(PROPER(RawSalesTable[[#This Row],[Customer_ID]])) -> C0091 | S368: =TRIM(LEFT(RawSalesTable[[#This Row],[Customer_Info]],FIND(",",RawSalesTable[[#This Row],[Customer_Info]]) -1)) -> Leo Taylor | T368: =TRIM(MID(RawSalesTable[[#This Row],[Customer_Info]],FIND(",",RawSalesTable[[#This Row],[Customer_Info]])+1,FIND(",",RawSalesTable[[#This Row],[Customer_Info]],FIND(",",RawSalesTable[[#This Row],[Customer_Info]])+1)-FIND(",",RawSalesTable[[#This Row],[Customer_Info]])-1)) -> Victoria | U368: =TRIM(RIGHT(RawSalesTable[[#This Row],[Customer_Info]], LEN(RawSalesTable[[#This Row],[Customer_Info]])-FIND(",",RawSalesTable[[#This Row],[Customer_Info]],FIND(",",RawSalesTable[[#This Row],[Customer_Info]])+1))) -> Small Business | V368: =VLOOKUP(RawSalesTable[[#This Row],[Product_ID]],ProductsTable[],2,FALSE) -> Air Fryer | W368: =VLOOKUP(RawSalesTable[[#This Row],[Product_ID]],ProductsTable[],3,FALSE) -> Home | X368: =VLOOKUP(RawSalesTable[[#This Row],[Product_ID]],ProductsTable[],5,FALSE) -> 14.58 | Y368: =RawSalesTable[[#This Row],[Quantity]]*RawSalesTable[[#This Row],[Unit_Price]] -> 31.76 | Z368: =RawSalesTable[[#This Row],[Gross_Sales]]*RawSalesTable[[#This Row],[Discount_Pct]] -> 1.588 | AA368: =RawSalesTable[[#This Row],[Gross_Sales]]-RawSalesTable[[#This Row],[Discount_Amount]] -> 30.172 | AB368: =RawSalesTable[[#This Row],[Unit_Cost]]*RawSalesTable[[#This Row],[Quantity]] -> 14.58 | AC368: =RawSalesTable[[#This Row],[Net_Sales]]-RawSalesTable[[#This Row],[Total_Cost]] -> 15.592 | AD368: =RawSalesTable[[#This Row],[Profit]]/RawSalesTable[[#This Row],[Net_Sales]] -> 0.51677052 | AE368: =IF(RawSalesTable[[#This Row],[Return_Status]]="Yes",1,0) -> 0 | AF368: =YEAR(RawSalesTable[[#This Row],[Order_Date]]) -> 2025 | AG368: =MONTH(RawSalesTable[[#This Row],[Order_Date]]) -> 4 | AH368: =TEXT(RawSalesTable[[#This Row],[Order_Date]],"mmmm") -> avril | AI368: =IF(RawSalesTable[[#This Row],[Month_Number]]<=3,"Q1",IF(RawSalesTable[[#This Row],[Month_Number]]<=6,"Q2",IF(RawSalesTable[[#This Row],[Month_Number]]<=9,"Q3","Q4"))) -> Q2 | AJ368: =DATE(YEAR(RawSalesTable[[#This Row],[Order_Date]]),MONTH(RawSalesTable[[#This Row],[Order_Date]]),1) -> 45748 | AK368: =VLOOKUP(RawSalesTable[[#This Row],[Customer_ID_clean]],CustomersTable[],4,FALSE) -> British Columbia
A369: ORD-2025-00361 | B369: 45702 | C369: C0040 | D369: P1028 | E369: Ethan Young, Surrey, Consumer | F369: Vancouver West | G369: L. Chen | H369: Retail Store | I369: 4 | J369: 366.27 | K369: 0 | L369: Paypal | M369: 0 | N369: No | O369: =SUBSTITUTE(PROPER(TRIM(RawSalesTable[[#This Row],[Channel_Raw]])), "Market Place", "Marketplace") -> Retail Store | P369: =TRIM(RawSalesTable[[#This Row],[Store_Raw]]) -> Vancouver West | Q369: =IF(TRIM(RawSalesTable[[#This Row],[Payment_Method_Raw]])="","Non renseigné",SUBSTITUTE(TRIM(RawSalesTable[[#This Row],[Payment_Method_Raw]]),"CC","Credit Card")) -> Paypal | R369: =UPPER(PROPER(RawSalesTable[[#This Row],[Customer_ID]])) -> C0040 | S369: =TRIM(LEFT(RawSalesTable[[#This Row],[Customer_Info]],FIND(",",RawSalesTable[[#This Row],[Customer_Info]]) -1)) -> Ethan Young | T369: =TRIM(MID(RawSalesTable[[#This Row],[Customer_Info]],FIND(",",RawSalesTable[[#This Row],[Customer_Info]])+1,FIND(",",RawSalesTable[[#This Row],[Customer_Info]],FIND(",",RawSalesTable[[#This Row],[Customer_Info]])+1)-FIND(",",RawSalesTable[[#This Row],[Customer_Info]])-1)) -> Surrey | U369: =TRIM(RIGHT(RawSalesTable[[#This Row],[Customer_Info]], LEN(RawSalesTable[[#This Row],[Customer_Info]])-FIND(",",RawSalesTable[[#This Row],[Customer_Info]],FIND(",",RawSalesTable[[#This Row],[Customer_Info]])+1))) -> Consumer | V369: =VLOOKUP(RawSalesTable[[#This Row],[Product_ID]],ProductsTable[],2,FALSE) -> Foam Roller | W369: =VLOOKUP(RawSalesTable[[#This Row],[Product_ID]],ProductsTable[],3,FALSE) -> Fitness | X369: =VLOOKUP(RawSalesTable[[#This Row],[Product_ID]],ProductsTable[],5,FALSE) -> 212.02 | Y369: =RawSalesTable[[#This Row],[Quantity]]*RawSalesTable[[#This Row],[Unit_Price]] -> 1465.08 | Z369: =RawSalesTable[[#This Row],[Gross_Sales]]*RawSalesTable[[#This Row],[Discount_Pct]] -> 0 | AA369: =RawSalesTable[[#This Row],[Gross_Sales]]-RawSalesTable[[#This Row],[Discount_Amount]] -> 1465.08 | AB369: =RawSalesTable[[#This Row],[Unit_Cost]]*RawSalesTable[[#This Row],[Quantity]] -> 848.08 | AC369: =RawSalesTable[[#This Row],[Net_Sales]]-RawSalesTable[[#This Row],[Total_Cost]] -> 617 | AD369: =RawSalesTable[[#This Row],[Profit]]/RawSalesTable[[#This Row],[Net_Sales]] -> 0.42113741 | AE369: =IF(RawSalesTable[[#This Row],[Return_Status]]="Yes",1,0) -> 0 | AF369: =YEAR(RawSalesTable[[#This Row],[Order_Date]]) -> 2025 | AG369: =MONTH(RawSalesTable[[#This Row],[Order_Date]]) -> 2 | AH369: =TEXT(RawSalesTable[[#This Row],[Order_Date]],"mmmm") -> février | AI369: =IF(RawSalesTable[[#This Row],[Month_Number]]<=3,"Q1",IF(RawSalesTable[[#This Row],[Month_Number]]<=6,"Q2",IF(RawSalesTable[[#This Row],[Month_Number]]<=9,"Q3","Q4"))) -> Q1 | AJ369: =DATE(YEAR(RawSalesTable[[#This Row],[Order_Date]]),MONTH(RawSalesTable[[#This Row],[Order_Date]]),1) -> 45689 | AK369: =VLOOKUP(RawSalesTable[[#This Row],[Customer_ID_clean]],CustomersTable[],4,FALSE) -> British Columbia
A370: ORD-2025-00362 | B370: 45664 | C370: C0028 | D370: P1008 | E370: Mia Clark, Victoria, Consumer | F370: Toronto Downtown | G370: M. Wilson | H370: Online | I370: 1 | J370: 137 | K370: 0.15 | L370: Debit Card | M370: 1 | N370: No | O370: =SUBSTITUTE(PROPER(TRIM(RawSalesTable[[#This Row],[Channel_Raw]])), "Market Place", "Marketplace") -> Online | P370: =TRIM(RawSalesTable[[#This Row],[Store_Raw]]) -> Toronto Downtown | Q370: =IF(TRIM(RawSalesTable[[#This Row],[Payment_Method_Raw]])="","Non renseigné",SUBSTITUTE(TRIM(RawSalesTable[[#This Row],[Payment_Method_Raw]]),"CC","Credit Card")) -> Debit Card | R370: =UPPER(PROPER(RawSalesTable[[#This Row],[Customer_ID]])) -> C0028 | S370: =TRIM(LEFT(RawSalesTable[[#This Row],[Customer_Info]],FIND(",",RawSalesTable[[#This Row],[Customer_Info]]) -1)) -> Mia Clark | T370: =TRIM(MID(RawSalesTable[[#This Row],[Customer_Info]],FIND(",",RawSalesTable[[#This Row],[Customer_Info]])+1,FIND(",",RawSalesTable[[#This Row],[Customer_Info]],FIND(",",RawSalesTable[[#This Row],[Customer_Info]])+1)-FIND(",",RawSalesTable[[#This Row],[Customer_Info]])-1)) -> Victoria | U370: =TRIM(RIGHT(RawSalesTable[[#This Row],[Customer_Info]], LEN(RawSalesTable[[#This Row],[Customer_Info]])-FIND(",",RawSalesTable[[#This Row],[Customer_Info]],FIND(",",RawSalesTable[[#This Row],[Customer_Info]])+1))) -> Consumer | V370: =VLOOKUP(RawSalesTable[[#This Row],[Product_ID]],ProductsTable[],2,FALSE) -> Smart Speaker | W370: =VLOOKUP(RawSalesTable[[#This Row],[Product_ID]],ProductsTable[],3,FALSE) -> Electronics | X370: =VLOOKUP(RawSalesTable[[#This Row],[Product_ID]],ProductsTable[],5,FALSE) -> 69 | Y370: =RawSalesTable[[#This Row],[Quantity]]*RawSalesTable[[#This Row],[Unit_Price]] -> 137 | Z370: =RawSalesTable[[#This Row],[Gross_Sales]]*RawSalesTable[[#This Row],[Discount_Pct]] -> 20.55 | AA370: =RawSalesTable[[#This Row],[Gross_Sales]]-RawSalesTable[[#This Row],[Discount_Amount]] -> 116.45 | AB370: =RawSalesTable[[#This Row],[Unit_Cost]]*RawSalesTable[[#This Row],[Quantity]] -> 69 | AC370: =RawSalesTable[[#This Row],[Net_Sales]]-RawSalesTable[[#This Row],[Total_Cost]] -> 47.45 | AD370: =RawSalesTable[[#This Row],[Profit]]/RawSalesTable[[#This Row],[Net_Sales]] -> 0.40747102 | AE370: =IF(RawSalesTable[[#This Row],[Return_Status]]="Yes",1,0) -> 0 | AF370: =YEAR(RawSalesTable[[#This Row],[Order_Date]]) -> 2025 | AG370: =MONTH(RawSalesTable[[#This Row],[Order_Date]]) -> 1 | AH370: =TEXT(RawSalesTable[[#This Row],[Order_Date]],"mmmm") -> janvier | AI370: =IF(RawSalesTable[[#This Row],[Month_Number]]<=3,"Q1",IF(RawSalesTable[[#This Row],[Month_Number]]<=6,"Q2",IF(RawSalesTable[[#This Row],[Month_Number]]<=9,"Q3","Q4"))) -> Q1 | AJ370: =DATE(YEAR(RawSalesTable[[#This Row],[Order_Date]]),MONTH(RawSalesTable[[#This Row],[Order_Date]]),1) -> 45658 | AK370: =VLOOKUP(RawSalesTable[[#This Row],[Customer_ID_clean]],CustomersTable[],4,FALSE) -> British Columbia
A371: ORD-2025-00363 | B371: 45771 | C371: C0003 | D371: P1037 | E371: Amelia Young, Ottawa, Corporate | F371: Montreal Central | G371: E. Roy | H371: Retail Store | I371: 2 | J371: 346.11 | K371: 0.15 | L371: Credit Card | M371: 0 | N371: Yes | O371: =SUBSTITUTE(PROPER(TRIM(RawSalesTable[[#This Row],[Channel_Raw]])), "Market Place", "Marketplace") -> Retail Store | P371: =TRIM(RawSalesTable[[#This Row],[Store_Raw]]) -> Montreal Central | Q371: =IF(TRIM(RawSalesTable[[#This Row],[Payment_Method_Raw]])="","Non renseigné",SUBSTITUTE(TRIM(RawSalesTable[[#This Row],[Payment_Method_Raw]]),"CC","Credit Card")) -> Credit Card | R371: =UPPER(PROPER(RawSalesTable[[#This Row],[Customer_ID]])) -> C0003 | S371: =TRIM(LEFT(RawSalesTable[[#This Row],[Customer_Info]],FIND(",",RawSalesTable[[#This Row],[Customer_Info]]) -1)) -> Amelia Young | T371: =TRIM(MID(RawSalesTable[[#This Row],[Customer_Info]],FIND(",",RawSalesTable[[#This Row],[Customer_Info]])+1,FIND(",",RawSalesTable[[#This Row],[Customer_Info]],FIND(",",RawSalesTable[[#This Row],[Customer_Info]])+1)-FIND(",",RawSalesTable[[#This Row],[Customer_Info]])-1)) -> Ottawa | U371: =TRIM(RIGHT(RawSalesTable[[#This Row],[Customer_Info]], LEN(RawSalesTable[[#This Row],[Customer_Info]])-FIND(",",RawSalesTable[[#This Row],[Customer_Info]],FIND(",",RawSalesTable[[#This Row],[Customer_Info]])+1))) -> Corporate | V371: =VLOOKUP(RawSalesTable[[#This Row],[Product_ID]],ProductsTable[],2,FALSE) -> Cable Set | W371: =VLOOKUP(RawSalesTable[[#This Row],[Product_ID]],ProductsTable[],3,FALSE) -> Accessories | X371: =VLOOKUP(RawSalesTable[[#This Row],[Product_ID]],ProductsTable[],5,FALSE) -> 200.16 | Y371: =RawSalesTable[[#This Row],[Quantity]]*RawSalesTable[[#This Row],[Unit_Price]] -> 692.22 | Z371: =RawSalesTable[[#This Row],[Gross_Sales]]*RawSalesTable[[#This Row],[Discount_Pct]] -> 103.833 | AA371: =RawSalesTable[[#This Row],[Gross_Sales]]-RawSalesTable[[#This Row],[Discount_Amount]] -> 588.387 | AB371: =RawSalesTable[[#This Row],[Unit_Cost]]*RawSalesTable[[#This Row],[Quantity]] -> 400.32 | AC371: =RawSalesTable[[#This Row],[Net_Sales]]-RawSalesTable[[#This Row],[Total_Cost]] -> 188.067 | AD371: =RawSalesTable[[#This Row],[Profit]]/RawSalesTable[[#This Row],[Net_Sales]] -> 0.31963147 | AE371: =IF(RawSalesTable[[#This Row],[Return_Status]]="Yes",1,0) -> 1 | AF371: =YEAR(RawSalesTable[[#This Row],[Order_Date]]) -> 2025 | AG371: =MONTH(RawSalesTable[[#This Row],[Order_Date]]) -> 4 | AH371: =TEXT(RawSalesTable[[#This Row],[Order_Date]],"mmmm") -> avril | AI371: =IF(RawSalesTable[[#This Row],[Month_Number]]<=3,"Q1",IF(RawSalesTable[[#This Row],[Month_Number]]<=6,"Q2",IF(RawSalesTable[[#This Row],[Month_Number]]<=9,"Q3","Q4"))) -> Q2 | AJ371: =DATE(YEAR(RawSalesTable[[#This Row],[Order_Date]]),MONTH(RawSalesTable[[#This Row],[Order_Date]]),1) -> 45748 | AK371: =VLOOKUP(RawSalesTable[[#This Row],[Customer_ID_clean]],CustomersTable[],4,FALSE) -> Ontario
A372: ORD-2025-00364 | B372: 45939 | C372: C0065 | D372: P1005 | E372: Mia Wilson, Quebec City, Consumer | F372: Online Fulfillment | G372: L. Chen | H372: Online | I372: 1 | J372: 243.13 | K372: 0 | L372: PAYPAL | M372: 5 | N372: No | O372: =SUBSTITUTE(PROPER(TRIM(RawSalesTable[[#This Row],[Channel_Raw]])), "Market Place", "Marketplace") -> Online | P372: =TRIM(RawSalesTable[[#This Row],[Store_Raw]]) -> Online Fulfillment | Q372: =IF(TRIM(RawSalesTable[[#This Row],[Payment_Method_Raw]])="","Non renseigné",SUBSTITUTE(TRIM(RawSalesTable[[#This Row],[Payment_Method_Raw]]),"CC","Credit Card")) -> PAYPAL | R372: =UPPER(PROPER(RawSalesTable[[#This Row],[Customer_ID]])) -> C0065 | S372: =TRIM(LEFT(RawSalesTable[[#This Row],[Customer_Info]],FIND(",",RawSalesTable[[#This Row],[Customer_Info]]) -1)) -> Mia Wilson | T372: =TRIM(MID(RawSalesTable[[#This Row],[Customer_Info]],FIND(",",RawSalesTable[[#This Row],[Customer_Info]])+1,FIND(",",RawSalesTable[[#This Row],[Customer_Info]],FIND(",",RawSalesTable[[#This Row],[Customer_Info]])+1)-FIND(",",RawSalesTable[[#This Row],[Customer_Info]])-1)) -> Quebec City | U372: =TRIM(RIGHT(RawSalesTable[[#This Row],[Customer_Info]], LEN(RawSalesTable[[#This Row],[Customer_Info]])-FIND(",",RawSalesTable[[#This Row],[Customer_Info]],FIND(",",RawSalesTable[[#This Row],[Customer_Info]])+1))) -> Consumer | V372: =VLOOKUP(RawSalesTable[[#This Row],[Product_ID]],ProductsTable[],2,FALSE) -> Portable SSD | W372: =VLOOKUP(RawSalesTable[[#This Row],[Product_ID]],ProductsTable[],3,FALSE) -> Electronics | X372: =VLOOKUP(RawSalesTable[[#This Row],[Product_ID]],ProductsTable[],5,FALSE) -> 131.19 | Y372: =RawSalesTable[[#This Row],[Quantity]]*RawSalesTable[[#This Row],[Unit_Price]] -> 243.13 | Z372: =RawSalesTable[[#This Row],[Gross_Sales]]*RawSalesTable[[#This Row],[Discount_Pct]] -> 0 | AA372: =RawSalesTable[[#This Row],[Gross_Sales]]-RawSalesTable[[#This Row],[Discount_Amount]] -> 243.13 | AB372: =RawSalesTable[[#This Row],[Unit_Cost]]*RawSalesTable[[#This Row],[Quantity]] -> 131.19 | AC372: =RawSalesTable[[#This Row],[Net_Sales]]-RawSalesTable[[#This Row],[Total_Cost]] -> 111.94 | AD372: =RawSalesTable[[#This Row],[Profit]]/RawSalesTable[[#This Row],[Net_Sales]] -> 0.46041213 | AE372: =IF(RawSalesTable[[#This Row],[Return_Status]]="Yes",1,0) -> 0 | AF372: =YEAR(RawSalesTable[[#This Row],[Order_Date]]) -> 2025 | AG372: =MONTH(RawSalesTable[[#This Row],[Order_Date]]) -> 10 | AH372: =TEXT(RawSalesTable[[#This Row],[Order_Date]],"mmmm") -> octobre | AI372: =IF(RawSalesTable[[#This Row],[Month_Number]]<=3,"Q1",IF(RawSalesTable[[#This Row],[Month_Number]]<=6,"Q2",IF(RawSalesTable[[#This Row],[Month_Number]]<=9,"Q3","Q4"))) -> Q4 | AJ372: =DATE(YEAR(RawSalesTable[[#This Row],[Order_Date]]),MONTH(RawSalesTable[[#This Row],[Order_Date]]),1) -> 45931 | AK372: =VLOOKUP(RawSalesTable[[#This Row],[Customer_ID_clean]],CustomersTable[],4,FALSE) -> Quebec
A373: ORD-2025-00365 | B373: 45794 | C373: C0098 | D373: P1020 | E373: Nora Young, Winnipeg, Consumer | F373: Vancouver West | G373: R. Singh | H373: Online | I373: 4 | J373: 66.46 | K373: 0 | L373: Credit Card | M373: 3 | N373: No | O373: =SUBSTITUTE(PROPER(TRIM(RawSalesTable[[#This Row],[Channel_Raw]])), "Market Place", "Marketplace") -> Online | P373: =TRIM(RawSalesTable[[#This Row],[Store_Raw]]) -> Vancouver West | Q373: =IF(TRIM(RawSalesTable[[#This Row],[Payment_Method_Raw]])="","Non renseigné",SUBSTITUTE(TRIM(RawSalesTable[[#This Row],[Payment_Method_Raw]]),"CC","Credit Card")) -> Credit Card | R373: =UPPER(PROPER(RawSalesTable[[#This Row],[Customer_ID]])) -> C0098 | S373: =TRIM(LEFT(RawSalesTable[[#This Row],[Customer_Info]],FIND(",",RawSalesTable[[#This Row],[Customer_Info]]) -1)) -> Nora Young | T373: =TRIM(MID(RawSalesTable[[#This Row],[Customer_Info]],FIND(",",RawSalesTable[[#This Row],[Customer_Info]])+1,FIND(",",RawSalesTable[[#This Row],[Customer_Info]],FIND(",",RawSalesTable[[#This Row],[Customer_Info]])+1)-FIND(",",RawSalesTable[[#This Row],[Customer_Info]])-1)) -> Winnipeg | U373: =TRIM(RIGHT(RawSalesTable[[#This Row],[Customer_Info]], LEN(RawSalesTable[[#This Row],[Customer_Info]])-FIND(",",RawSalesTable[[#This Row],[Customer_Info]],FIND(",",RawSalesTable[[#This Row],[Customer_Info]])+1))) -> Consumer | V373: =VLOOKUP(RawSalesTable[[#This Row],[Product_ID]],ProductsTable[],2,FALSE) -> Blender | W373: =VLOOKUP(RawSalesTable[[#This Row],[Product_ID]],ProductsTable[],3,FALSE) -> Home | X373: =VLOOKUP(RawSalesTable[[#This Row],[Product_ID]],ProductsTable[],5,FALSE) -> 37.46 | Y373: =RawSalesTable[[#This Row],[Quantity]]*RawSalesTable[[#This Row],[Unit_Price]] -> 265.84 | Z373: =RawSalesTable[[#This Row],[Gross_Sales]]*RawSalesTable[[#This Row],[Discount_Pct]] -> 0 | AA373: =RawSalesTable[[#This Row],[Gross_Sales]]-RawSalesTable[[#This Row],[Discount_Amount]] -> 265.84 | AB373: =RawSalesTable[[#This Row],[Unit_Cost]]*RawSalesTable[[#This Row],[Quantity]] -> 149.84 | AC373: =RawSalesTable[[#This Row],[Net_Sales]]-RawSalesTable[[#This Row],[Total_Cost]] -> 116 | AD373: =RawSalesTable[[#This Row],[Profit]]/RawSalesTable[[#This Row],[Net_Sales]] -> 0.43635269 | AE373: =IF(RawSalesTable[[#This Row],[Return_Status]]="Yes",1,0) -> 0 | AF373: =YEAR(RawSalesTable[[#This Row],[Order_Date]]) -> 2025 | AG373: =MONTH(RawSalesTable[[#This Row],[Order_Date]]) -> 5 | AH373: =TEXT(RawSalesTable[[#This Row],[Order_Date]],"mmmm") -> mai | AI373: =IF(RawSalesTable[[#This Row],[Month_Number]]<=3,"Q1",IF(RawSalesTable[[#This Row],[Month_Number]]<=6,"Q2",IF(RawSalesTable[[#This Row],[Month_Number]]<=9,"Q3","Q4"))) -> Q2 | AJ373: =DATE(YEAR(RawSalesTable[[#This Row],[Order_Date]]),MONTH(RawSalesTable[[#This Row],[Order_Date]]),1) -> 45778 | AK373: =VLOOKUP(RawSalesTable[[#This Row],[Customer_ID_clean]],CustomersTable[],4,FALSE) -> Manitoba
A374: ORD-2025-00366 | B374: 45898 | C374: C0071 | D374: P1040 | E374: Ethan Lee, Surrey, Consumer | F374: Vancouver West | G374: R. Singh | H374: ONLINE | I374: 2 | J374: 320.84 | K374: 0.25 | L374: PayPal | M374: 5 | N374: No | O374: =SUBSTITUTE(PROPER(TRIM(RawSalesTable[[#This Row],[Channel_Raw]])), "Market Place", "Marketplace") -> Online | P374: =TRIM(RawSalesTable[[#This Row],[Store_Raw]]) -> Vancouver West | Q374: =IF(TRIM(RawSalesTable[[#This Row],[Payment_Method_Raw]])="","Non renseigné",SUBSTITUTE(TRIM(RawSalesTable[[#This Row],[Payment_Method_Raw]]),"CC","Credit Card")) -> PayPal | R374: =UPPER(PROPER(RawSalesTable[[#This Row],[Customer_ID]])) -> C0071 | S374: =TRIM(LEFT(RawSalesTable[[#This Row],[Customer_Info]],FIND(",",RawSalesTable[[#This Row],[Customer_Info]]) -1)) -> Ethan Lee | T374: =TRIM(MID(RawSalesTable[[#This Row],[Customer_Info]],FIND(",",RawSalesTable[[#This Row],[Customer_Info]])+1,FIND(",",RawSalesTable[[#This Row],[Customer_Info]],FIND(",",RawSalesTable[[#This Row],[Customer_Info]])+1)-FIND(",",RawSalesTable[[#This Row],[Customer_Info]])-1)) -> Surrey | U374: =TRIM(RIGHT(RawSalesTable[[#This Row],[Customer_Info]], LEN(RawSalesTable[[#This Row],[Customer_Info]])-FIND(",",RawSalesTable[[#This Row],[Customer_Info]],FIND(",",RawSalesTable[[#This Row],[Customer_Info]])+1))) -> Consumer | V374: =VLOOKUP(RawSalesTable[[#This Row],[Product_ID]],ProductsTable[],2,FALSE) -> Desk Pad | W374: =VLOOKUP(RawSalesTable[[#This Row],[Product_ID]],ProductsTable[],3,FALSE) -> Accessories | X374: =VLOOKUP(RawSalesTable[[#This Row],[Product_ID]],ProductsTable[],5,FALSE) -> 177.57 | Y374: =RawSalesTable[[#This Row],[Quantity]]*RawSalesTable[[#This Row],[Unit_Price]] -> 641.68 | Z374: =RawSalesTable[[#This Row],[Gross_Sales]]*RawSalesTable[[#This Row],[Discount_Pct]] -> 160.42 | AA374: =RawSalesTable[[#This Row],[Gross_Sales]]-RawSalesTable[[#This Row],[Discount_Amount]] -> 481.26 | AB374: =RawSalesTable[[#This Row],[Unit_Cost]]*RawSalesTable[[#This Row],[Quantity]] -> 355.14 | AC374: =RawSalesTable[[#This Row],[Net_Sales]]-RawSalesTable[[#This Row],[Total_Cost]] -> 126.12 | AD374: =RawSalesTable[[#This Row],[Profit]]/RawSalesTable[[#This Row],[Net_Sales]] -> 0.26206209 | AE374: =IF(RawSalesTable[[#This Row],[Return_Status]]="Yes",1,0) -> 0 | AF374: =YEAR(RawSalesTable[[#This Row],[Order_Date]]) -> 2025 | AG374: =MONTH(RawSalesTable[[#This Row],[Order_Date]]) -> 8 | AH374: =TEXT(RawSalesTable[[#This Row],[Order_Date]],"mmmm") -> août | AI374: =IF(RawSalesTable[[#This Row],[Month_Number]]<=3,"Q1",IF(RawSalesTable[[#This Row],[Month_Number]]<=6,"Q2",IF(RawSalesTable[[#This Row],[Month_Number]]<=9,"Q3","Q4"))) -> Q3 | AJ374: =DATE(YEAR(RawSalesTable[[#This Row],[Order_Date]]),MONTH(RawSalesTable[[#This Row],[Order_Date]]),1) -> 45870 | AK374: =VLOOKUP(RawSalesTable[[#This Row],[Customer_ID_clean]],CustomersTable[],4,FALSE) -> British Columbia
A375: ORD-2025-00367 | B375: 45877 | C375: C0018 | D375: P1003 | E375: Sophia Tremblay, Laval, Small Business | F375: Toronto Downtown | G375: M. Wilson | H375: Online | I375: 3 | J375: 165.26 | K375: 0.05 | L375: Credit Card | M375: 1 | N375: No | O375: =SUBSTITUTE(PROPER(TRIM(RawSalesTable[[#This Row],[Channel_Raw]])), "Market Place", "Marketplace") -> Online | P375: =TRIM(RawSalesTable[[#This Row],[Store_Raw]]) -> Toronto Downtown | Q375: =IF(TRIM(RawSalesTable[[#This Row],[Payment_Method_Raw]])="","Non renseigné",SUBSTITUTE(TRIM(RawSalesTable[[#This Row],[Payment_Method_Raw]]),"CC","Credit Card")) -> Credit Card | R375: =UPPER(PROPER(RawSalesTable[[#This Row],[Customer_ID]])) -> C0018 | S375: =TRIM(LEFT(RawSalesTable[[#This Row],[Customer_Info]],FIND(",",RawSalesTable[[#This Row],[Customer_Info]]) -1)) -> Sophia Tremblay | T375: =TRIM(MID(RawSalesTable[[#This Row],[Customer_Info]],FIND(",",RawSalesTable[[#This Row],[Customer_Info]])+1,FIND(",",RawSalesTable[[#This Row],[Customer_Info]],FIND(",",RawSalesTable[[#This Row],[Customer_Info]])+1)-FIND(",",RawSalesTable[[#This Row],[Customer_Info]])-1)) -> Laval | U375: =TRIM(RIGHT(RawSalesTable[[#This Row],[Customer_Info]], LEN(RawSalesTable[[#This Row],[Customer_Info]])-FIND(",",RawSalesTable[[#This Row],[Customer_Info]],FIND(",",RawSalesTable[[#This Row],[Customer_Info]])+1))) -> Small Business | V375: =VLOOKUP(RawSalesTable[[#This Row],[Product_ID]],ProductsTable[],2,FALSE) -> Mouse | W375: =VLOOKUP(RawSalesTable[[#This Row],[Product_ID]],ProductsTable[],3,FALSE) -> Electronics | X375: =VLOOKUP(RawSalesTable[[#This Row],[Product_ID]],ProductsTable[],5,FALSE) -> 106.4 | Y375: =RawSalesTable[[#This Row],[Quantity]]*RawSalesTable[[#This Row],[Unit_Price]] -> 495.78 | Z375: =RawSalesTable[[#This Row],[Gross_Sales]]*RawSalesTable[[#This Row],[Discount_Pct]] -> 24.789 | AA375: =RawSalesTable[[#This Row],[Gross_Sales]]-RawSalesTable[[#This Row],[Discount_Amount]] -> 470.991 | AB375: =RawSalesTable[[#This Row],[Unit_Cost]]*RawSalesTable[[#This Row],[Quantity]] -> 319.2 | AC375: =RawSalesTable[[#This Row],[Net_Sales]]-RawSalesTable[[#This Row],[Total_Cost]] -> 151.791 | AD375: =RawSalesTable[[#This Row],[Profit]]/RawSalesTable[[#This Row],[Net_Sales]] -> 0.32228004 | AE375: =IF(RawSalesTable[[#This Row],[Return_Status]]="Yes",1,0) -> 0 | AF375: =YEAR(RawSalesTable[[#This Row],[Order_Date]]) -> 2025 | AG375: =MONTH(RawSalesTable[[#This Row],[Order_Date]]) -> 8 | AH375: =TEXT(RawSalesTable[[#This Row],[Order_Date]],"mmmm") -> août | AI375: =IF(RawSalesTable[[#This Row],[Month_Number]]<=3,"Q1",IF(RawSalesTable[[#This Row],[Month_Number]]<=6,"Q2",IF(RawSalesTable[[#This Row],[Month_Number]]<=9,"Q3","Q4"))) -> Q3 | AJ375: =DATE(YEAR(RawSalesTable[[#This Row],[Order_Date]]),MONTH(RawSalesTable[[#This Row],[Order_Date]]),1) -> 45870 | AK375: =VLOOKUP(RawSalesTable[[#This Row],[Customer_ID_clean]],CustomersTable[],4,FALSE) -> Quebec
A376: ORD-2025-00368 | B376: 45897 | C376: C0101 | D376: P1029 | E376: Noah Martin, Saskatoon, Small Business | F376: Calgary North | G376: N. Brown | H376: Retail Store | I376: 1 | J376: 209.3 | K376: 0.1 | L376: Credit Card | M376: 2 | N376: No | O376: =SUBSTITUTE(PROPER(TRIM(RawSalesTable[[#This Row],[Channel_Raw]])), "Market Place", "Marketplace") -> Retail Store | P376: =TRIM(RawSalesTable[[#This Row],[Store_Raw]]) -> Calgary North | Q376: =IF(TRIM(RawSalesTable[[#This Row],[Payment_Method_Raw]])="","Non renseigné",SUBSTITUTE(TRIM(RawSalesTable[[#This Row],[Payment_Method_Raw]]),"CC","Credit Card")) -> Credit Card | R376: =UPPER(PROPER(RawSalesTable[[#This Row],[Customer_ID]])) -> C0101 | S376: =TRIM(LEFT(RawSalesTable[[#This Row],[Customer_Info]],FIND(",",RawSalesTable[[#This Row],[Customer_Info]]) -1)) -> Noah Martin | T376: =TRIM(MID(RawSalesTable[[#This Row],[Customer_Info]],FIND(",",RawSalesTable[[#This Row],[Customer_Info]])+1,FIND(",",RawSalesTable[[#This Row],[Customer_Info]],FIND(",",RawSalesTable[[#This Row],[Customer_Info]])+1)-FIND(",",RawSalesTable[[#This Row],[Customer_Info]])-1)) -> Saskatoon | U376: =TRIM(RIGHT(RawSalesTable[[#This Row],[Customer_Info]], LEN(RawSalesTable[[#This Row],[Customer_Info]])-FIND(",",RawSalesTable[[#This Row],[Customer_Info]],FIND(",",RawSalesTable[[#This Row],[Customer_Info]])+1))) -> Small Business | V376: =VLOOKUP(RawSalesTable[[#This Row],[Product_ID]],ProductsTable[],2,FALSE) -> Jump Rope | W376: =VLOOKUP(RawSalesTable[[#This Row],[Product_ID]],ProductsTable[],3,FALSE) -> Fitness | X376: =VLOOKUP(RawSalesTable[[#This Row],[Product_ID]],ProductsTable[],5,FALSE) -> 101 | Y376: =RawSalesTable[[#This Row],[Quantity]]*RawSalesTable[[#This Row],[Unit_Price]] -> 209.3 | Z376: =RawSalesTable[[#This Row],[Gross_Sales]]*RawSalesTable[[#This Row],[Discount_Pct]] -> 20.93 | AA376: =RawSalesTable[[#This Row],[Gross_Sales]]-RawSalesTable[[#This Row],[Discount_Amount]] -> 188.37 | AB376: =RawSalesTable[[#This Row],[Unit_Cost]]*RawSalesTable[[#This Row],[Quantity]] -> 101 | AC376: =RawSalesTable[[#This Row],[Net_Sales]]-RawSalesTable[[#This Row],[Total_Cost]] -> 87.37 | AD376: =RawSalesTable[[#This Row],[Profit]]/RawSalesTable[[#This Row],[Net_Sales]] -> 0.4638212 | AE376: =IF(RawSalesTable[[#This Row],[Return_Status]]="Yes",1,0) -> 0 | AF376: =YEAR(RawSalesTable[[#This Row],[Order_Date]]) -> 2025 | AG376: =MONTH(RawSalesTable[[#This Row],[Order_Date]]) -> 8 | AH376: =TEXT(RawSalesTable[[#This Row],[Order_Date]],"mmmm") -> août | AI376: =IF(RawSalesTable[[#This Row],[Month_Number]]<=3,"Q1",IF(RawSalesTable[[#This Row],[Month_Number]]<=6,"Q2",IF(RawSalesTable[[#This Row],[Month_Number]]<=9,"Q3","Q4"))) -> Q3 | AJ376: =DATE(YEAR(RawSalesTable[[#This Row],[Order_Date]]),MONTH(RawSalesTable[[#This Row],[Order_Date]]),1) -> 45870 | AK376: =VLOOKUP(RawSalesTable[[#This Row],[Customer_ID_clean]],CustomersTable[],4,FALSE) -> Saskatchewan
A377: ORD-2025-00369 | B377: 45923 | C377: C0050 | D377: P1016 | E377: Sarah Singh, Mississauga, Consumer | F377: Toronto Downtown | G377: J. Tremblay | H377: Retail Store | I377: 1 | J377: 308.68 | K377: 0.2 | L377: Credit Card | M377: 2 | N377: No | O377: =SUBSTITUTE(PROPER(TRIM(RawSalesTable[[#This Row],[Channel_Raw]])), "Market Place", "Marketplace") -> Retail Store | P377: =TRIM(RawSalesTable[[#This Row],[Store_Raw]]) -> Toronto Downtown | Q377: =IF(TRIM(RawSalesTable[[#This Row],[Payment_Method_Raw]])="","Non renseigné",SUBSTITUTE(TRIM(RawSalesTable[[#This Row],[Payment_Method_Raw]]),"CC","Credit Card")) -> Credit Card | R377: =UPPER(PROPER(RawSalesTable[[#This Row],[Customer_ID]])) -> C0050 | S377: =TRIM(LEFT(RawSalesTable[[#This Row],[Customer_Info]],FIND(",",RawSalesTable[[#This Row],[Customer_Info]]) -1)) -> Sarah Singh | T377: =TRIM(MID(RawSalesTable[[#This Row],[Customer_Info]],FIND(",",RawSalesTable[[#This Row],[Customer_Info]])+1,FIND(",",RawSalesTable[[#This Row],[Customer_Info]],FIND(",",RawSalesTable[[#This Row],[Customer_Info]])+1)-FIND(",",RawSalesTable[[#This Row],[Customer_Info]])-1)) -> Mississauga | U377: =TRIM(RIGHT(RawSalesTable[[#This Row],[Customer_Info]], LEN(RawSalesTable[[#This Row],[Customer_Info]])-FIND(",",RawSalesTable[[#This Row],[Customer_Info]],FIND(",",RawSalesTable[[#This Row],[Customer_Info]])+1))) -> Consumer | V377: =VLOOKUP(RawSalesTable[[#This Row],[Product_ID]],ProductsTable[],2,FALSE) -> Printer | W377: =VLOOKUP(RawSalesTable[[#This Row],[Product_ID]],ProductsTable[],3,FALSE) -> Office | X377: =VLOOKUP(RawSalesTable[[#This Row],[Product_ID]],ProductsTable[],5,FALSE) -> 156.75 | Y377: =RawSalesTable[[#This Row],[Quantity]]*RawSalesTable[[#This Row],[Unit_Price]] -> 308.68 | Z377: =RawSalesTable[[#This Row],[Gross_Sales]]*RawSalesTable[[#This Row],[Discount_Pct]] -> 61.736 | AA377: =RawSalesTable[[#This Row],[Gross_Sales]]-RawSalesTable[[#This Row],[Discount_Amount]] -> 246.944 | AB377: =RawSalesTable[[#This Row],[Unit_Cost]]*RawSalesTable[[#This Row],[Quantity]] -> 156.75 | AC377: =RawSalesTable[[#This Row],[Net_Sales]]-RawSalesTable[[#This Row],[Total_Cost]] -> 90.194 | AD377: =RawSalesTable[[#This Row],[Profit]]/RawSalesTable[[#This Row],[Net_Sales]] -> 0.3652407 | AE377: =IF(RawSalesTable[[#This Row],[Return_Status]]="Yes",1,0) -> 0 | AF377: =YEAR(RawSalesTable[[#This Row],[Order_Date]]) -> 2025 | AG377: =MONTH(RawSalesTable[[#This Row],[Order_Date]]) -> 9 | AH377: =TEXT(RawSalesTable[[#This Row],[Order_Date]],"mmmm") -> septembre | AI377: =IF(RawSalesTable[[#This Row],[Month_Number]]<=3,"Q1",IF(RawSalesTable[[#This Row],[Month_Number]]<=6,"Q2",IF(RawSalesTable[[#This Row],[Month_Number]]<=9,"Q3","Q4"))) -> Q3 | AJ377: =DATE(YEAR(RawSalesTable[[#This Row],[Order_Date]]),MONTH(RawSalesTable[[#This Row],[Order_Date]]),1) -> 45901 | AK377: =VLOOKUP(RawSalesTable[[#This Row],[Customer_ID_clean]],CustomersTable[],4,FALSE) -> Ontario
A378: ORD-2025-00370 | B378: 45887 | C378: C0042 | D378: P1010 | E378: Emma King, Quebec City, Consumer | F378: Toronto Downtown | G378: N. Brown | H378: Retail Store | I378: 3 | J378: 215.17 | K378: 0.2 | L378: Credit Card | M378: 0 | N378: No | O378: =SUBSTITUTE(PROPER(TRIM(RawSalesTable[[#This Row],[Channel_Raw]])), "Market Place", "Marketplace") -> Retail Store | P378: =TRIM(RawSalesTable[[#This Row],[Store_Raw]]) -> Toronto Downtown | Q378: =IF(TRIM(RawSalesTable[[#This Row],[Payment_Method_Raw]])="","Non renseigné",SUBSTITUTE(TRIM(RawSalesTable[[#This Row],[Payment_Method_Raw]]),"CC","Credit Card")) -> Credit Card | R378: =UPPER(PROPER(RawSalesTable[[#This Row],[Customer_ID]])) -> C0042 | S378: =TRIM(LEFT(RawSalesTable[[#This Row],[Customer_Info]],FIND(",",RawSalesTable[[#This Row],[Customer_Info]]) -1)) -> Emma King | T378: =TRIM(MID(RawSalesTable[[#This Row],[Customer_Info]],FIND(",",RawSalesTable[[#This Row],[Customer_Info]])+1,FIND(",",RawSalesTable[[#This Row],[Customer_Info]],FIND(",",RawSalesTable[[#This Row],[Customer_Info]])+1)-FIND(",",RawSalesTable[[#This Row],[Customer_Info]])-1)) -> Quebec City | U378: =TRIM(RIGHT(RawSalesTable[[#This Row],[Customer_Info]], LEN(RawSalesTable[[#This Row],[Customer_Info]])-FIND(",",RawSalesTable[[#This Row],[Customer_Info]],FIND(",",RawSalesTable[[#This Row],[Customer_Info]])+1))) -> Consumer | V378: =VLOOKUP(RawSalesTable[[#This Row],[Product_ID]],ProductsTable[],2,FALSE) -> Desk Lamp | W378: =VLOOKUP(RawSalesTable[[#This Row],[Product_ID]],ProductsTable[],3,FALSE) -> Office | X378: =VLOOKUP(RawSalesTable[[#This Row],[Product_ID]],ProductsTable[],5,FALSE) -> 127.21 | Y378: =RawSalesTable[[#This Row],[Quantity]]*RawSalesTable[[#This Row],[Unit_Price]] -> 645.51 | Z378: =RawSalesTable[[#This Row],[Gross_Sales]]*RawSalesTable[[#This Row],[Discount_Pct]] -> 129.102 | AA378: =RawSalesTable[[#This Row],[Gross_Sales]]-RawSalesTable[[#This Row],[Discount_Amount]] -> 516.408 | AB378: =RawSalesTable[[#This Row],[Unit_Cost]]*RawSalesTable[[#This Row],[Quantity]] -> 381.63 | AC378: =RawSalesTable[[#This Row],[Net_Sales]]-RawSalesTable[[#This Row],[Total_Cost]] -> 134.778 | AD378: =RawSalesTable[[#This Row],[Profit]]/RawSalesTable[[#This Row],[Net_Sales]] -> 0.26099131 | AE378: =IF(RawSalesTable[[#This Row],[Return_Status]]="Yes",1,0) -> 0 | AF378: =YEAR(RawSalesTable[[#This Row],[Order_Date]]) -> 2025 | AG378: =MONTH(RawSalesTable[[#This Row],[Order_Date]]) -> 8 | AH378: =TEXT(RawSalesTable[[#This Row],[Order_Date]],"mmmm") -> août | AI378: =IF(RawSalesTable[[#This Row],[Month_Number]]<=3,"Q1",IF(RawSalesTable[[#This Row],[Month_Number]]<=6,"Q2",IF(RawSalesTable[[#This Row],[Month_Number]]<=9,"Q3","Q4"))) -> Q3 | AJ378: =DATE(YEAR(RawSalesTable[[#This Row],[Order_Date]]),MONTH(RawSalesTable[[#This Row],[Order_Date]]),1) -> 45870 | AK378: =VLOOKUP(RawSalesTable[[#This Row],[Customer_ID_clean]],CustomersTable[],4,FALSE) -> Quebec
A379: ORD-2025-00371 | B379: 45816 | C379: C0091 | D379: P1006 | E379: Leo Taylor, Victoria, Small Business | F379: Calgary North | G379: R. Singh | H379: Retail Store | I379: 3 | J379: 111.59 | K379: 0.05 | L379: Debit Card | M379: 1 | N379: Yes | O379: =SUBSTITUTE(PROPER(TRIM(RawSalesTable[[#This Row],[Channel_Raw]])), "Market Place", "Marketplace") -> Retail Store | P379: =TRIM(RawSalesTable[[#This Row],[Store_Raw]]) -> Calgary North | Q379: =IF(TRIM(RawSalesTable[[#This Row],[Payment_Method_Raw]])="","Non renseigné",SUBSTITUTE(TRIM(RawSalesTable[[#This Row],[Payment_Method_Raw]]),"CC","Credit Card")) -> Debit Card | R379: =UPPER(PROPER(RawSalesTable[[#This Row],[Customer_ID]])) -> C0091 | S379: =TRIM(LEFT(RawSalesTable[[#This Row],[Customer_Info]],FIND(",",RawSalesTable[[#This Row],[Customer_Info]]) -1)) -> Leo Taylor | T379: =TRIM(MID(RawSalesTable[[#This Row],[Customer_Info]],FIND(",",RawSalesTable[[#This Row],[Customer_Info]])+1,FIND(",",RawSalesTable[[#This Row],[Customer_Info]],FIND(",",RawSalesTable[[#This Row],[Customer_Info]])+1)-FIND(",",RawSalesTable[[#This Row],[Customer_Info]])-1)) -> Victoria | U379: =TRIM(RIGHT(RawSalesTable[[#This Row],[Customer_Info]], LEN(RawSalesTable[[#This Row],[Customer_Info]])-FIND(",",RawSalesTable[[#This Row],[Customer_Info]],FIND(",",RawSalesTable[[#This Row],[Customer_Info]])+1))) -> Small Business | V379: =VLOOKUP(RawSalesTable[[#This Row],[Product_ID]],ProductsTable[],2,FALSE) -> USB-C Hub | W379: =VLOOKUP(RawSalesTable[[#This Row],[Product_ID]],ProductsTable[],3,FALSE) -> Electronics | X379: =VLOOKUP(RawSalesTable[[#This Row],[Product_ID]],ProductsTable[],5,FALSE) -> 72 | Y379: =RawSalesTable[[#This Row],[Quantity]]*RawSalesTable[[#This Row],[Unit_Price]] -> 334.77 | Z379: =RawSalesTable[[#This Row],[Gross_Sales]]*RawSalesTable[[#This Row],[Discount_Pct]] -> 16.7385 | AA379: =RawSalesTable[[#This Row],[Gross_Sales]]-RawSalesTable[[#This Row],[Discount_Amount]] -> 318.0315 | AB379: =RawSalesTable[[#This Row],[Unit_Cost]]*RawSalesTable[[#This Row],[Quantity]] -> 216 | AC379: =RawSalesTable[[#This Row],[Net_Sales]]-RawSalesTable[[#This Row],[Total_Cost]] -> 102.0315 | AD379: =RawSalesTable[[#This Row],[Profit]]/RawSalesTable[[#This Row],[Net_Sales]] -> 0.32082199 | AE379: =IF(RawSalesTable[[#This Row],[Return_Status]]="Yes",1,0) -> 1 | AF379: =YEAR(RawSalesTable[[#This Row],[Order_Date]]) -> 2025 | AG379: =MONTH(RawSalesTable[[#This Row],[Order_Date]]) -> 6 | AH379: =TEXT(RawSalesTable[[#This Row],[Order_Date]],"mmmm") -> juin | AI379: =IF(RawSalesTable[[#This Row],[Month_Number]]<=3,"Q1",IF(RawSalesTable[[#This Row],[Month_Number]]<=6,"Q2",IF(RawSalesTable[[#This Row],[Month_Number]]<=9,"Q3","Q4"))) -> Q2 | AJ379: =DATE(YEAR(RawSalesTable[[#This Row],[Order_Date]]),MONTH(RawSalesTable[[#This Row],[Order_Date]]),1) -> 45809 | AK379: =VLOOKUP(RawSalesTable[[#This Row],[Customer_ID_clean]],CustomersTable[],4,FALSE) -> British Columbia
... A385: ORD-2025-00377 | B385: 45670 | C385: C0080 | D385: P1019 | E385: Sarah Smith, Mississauga, Corporate | F385: Montreal Central | G385: N. Brown | H385: Marketplace | I385: 2 | J385: 262.65 | K385: 0.05 | L385: Credit Card | M385: 8 | N385: No | O385: =SUBSTITUTE(PROPER(TRIM(RawSalesTable[[#This Row],[Channel_Raw]])), "Market Place", "Marketplace") -> Marketplace | P385: =TRIM(RawSalesTable[[#This Row],[Store_Raw]]) -> Montreal Central | Q385: =IF(TRIM(RawSalesTable[[#This Row],[Payment_Method_Raw]])="","Non renseigné",SUBSTITUTE(TRIM(RawSalesTable[[#This Row],[Payment_Method_Raw]]),"CC","Credit Card")) -> Credit Card | R385: =UPPER(PROPER(RawSalesTable[[#This Row],[Customer_ID]])) -> C0080 | S385: =TRIM(LEFT(RawSalesTable[[#This Row],[Customer_Info]],FIND(",",RawSalesTable[[#This Row],[Customer_Info]]) -1)) -> Sarah Smith | T385: =TRIM(MID(RawSalesTable[[#This Row],[Customer_Info]],FIND(",",RawSalesTable[[#This Row],[Customer_Info]])+1,FIND(",",RawSalesTable[[#This Row],[Customer_Info]],FIND(",",RawSalesTable[[#This Row],[Customer_Info]])+1)-FIND(",",RawSalesTable[[#This Row],[Customer_Info]])-1)) -> Mississauga | U385: =TRIM(RIGHT(RawSalesTable[[#This Row],[Customer_Info]], LEN(RawSalesTable[[#This Row],[Customer_Info]])-FIND(",",RawSalesTable[[#This Row],[Customer_Info]],FIND(",",RawSalesTable[[#This Row],[Customer_Info]])+1))) -> Corporate | V385: =VLOOKUP(RawSalesTable[[#This Row],[Product_ID]],ProductsTable[],2,FALSE) -> Vacuum | W385: =VLOOKUP(RawSalesTable[[#This Row],[Product_ID]],ProductsTable[],3,FALSE) -> Home | X385: =VLOOKUP(RawSalesTable[[#This Row],[Product_ID]],ProductsTable[],5,FALSE) -> 186.94 | Y385: =RawSalesTable[[#This Row],[Quantity]]*RawSalesTable[[#This Row],[Unit_Price]] -> 525.3 | Z385: =RawSalesTable[[#This Row],[Gross_Sales]]*RawSalesTable[[#This Row],[Discount_Pct]] -> 26.265 | AA385: =RawSalesTable[[#This Row],[Gross_Sales]]-RawSalesTable[[#This Row],[Discount_Amount]] -> 499.035 | AB385: =RawSalesTable[[#This Row],[Unit_Cost]]*RawSalesTable[[#This Row],[Quantity]] -> 373.88 | AC385: =RawSalesTable[[#This Row],[Net_Sales]]-RawSalesTable[[#This Row],[Total_Cost]] -> 125.155 | AD385: =RawSalesTable[[#This Row],[Profit]]/RawSalesTable[[#This Row],[Net_Sales]] -> 0.25079403 | AE385: =IF(RawSalesTable[[#This Row],[Return_Status]]="Yes",1,0) -> 0 | AF385: =YEAR(RawSalesTable[[#This Row],[Order_Date]]) -> 2025 | AG385: =MONTH(RawSalesTable[[#This Row],[Order_Date]]) -> 1 | AH385: =TEXT(RawSalesTable[[#This Row],[Order_Date]],"mmmm") -> janvier | AI385: =IF(RawSalesTable[[#This Row],[Month_Number]]<=3,"Q1",IF(RawSalesTable[[#This Row],[Month_Number]]<=6,"Q2",IF(RawSalesTable[[#This Row],[Month_Number]]<=9,"Q3","Q4"))) -> Q1 | AJ385: =DATE(YEAR(RawSalesTable[[#This Row],[Order_Date]]),MONTH(RawSalesTable[[#This Row],[Order_Date]]),1) -> 45658 | AK385: =VLOOKUP(RawSalesTable[[#This Row],[Customer_ID_clean]],CustomersTable[],4,FALSE) -> Ontario
A386: ORD-2025-00378 | B386: 45891 | C386: C0099 | D386: P1004 | E386: Amine Gagnon, Laval, Small Business | F386: Calgary North | G386: N. Brown | H386: Retail Store | I386: 3 | J386: 277.93 | K386: 0.05 | M386: 2 | N386: No | O386: =SUBSTITUTE(PROPER(TRIM(RawSalesTable[[#This Row],[Channel_Raw]])), "Market Place", "Marketplace") -> Retail Store | P386: =TRIM(RawSalesTable[[#This Row],[Store_Raw]]) -> Calgary North | Q386: =IF(TRIM(RawSalesTable[[#This Row],[Payment_Method_Raw]])="","Non renseigné",SUBSTITUTE(TRIM(RawSalesTable[[#This Row],[Payment_Method_Raw]]),"CC","Credit Card")) -> Non renseigné | R386: =UPPER(PROPER(RawSalesTable[[#This Row],[Customer_ID]])) -> C0099 | S386: =TRIM(LEFT(RawSalesTable[[#This Row],[Customer_Info]],FIND(",",RawSalesTable[[#This Row],[Customer_Info]]) -1)) -> Amine Gagnon | T386: =TRIM(MID(RawSalesTable[[#This Row],[Customer_Info]],FIND(",",RawSalesTable[[#This Row],[Customer_Info]])+1,FIND(",",RawSalesTable[[#This Row],[Customer_Info]],FIND(",",RawSalesTable[[#This Row],[Customer_Info]])+1)-FIND(",",RawSalesTable[[#This Row],[Customer_Info]])-1)) -> Laval | U386: =TRIM(RIGHT(RawSalesTable[[#This Row],[Customer_Info]], LEN(RawSalesTable[[#This Row],[Customer_Info]])-FIND(",",RawSalesTable[[#This Row],[Customer_Info]],FIND(",",RawSalesTable[[#This Row],[Customer_Info]])+1))) -> Small Business | V386: =VLOOKUP(RawSalesTable[[#This Row],[Product_ID]],ProductsTable[],2,FALSE) -> Webcam | W386: =VLOOKUP(RawSalesTable[[#This Row],[Product_ID]],ProductsTable[],3,FALSE) -> Electronics | X386: =VLOOKUP(RawSalesTable[[#This Row],[Product_ID]],ProductsTable[],5,FALSE) -> 154.73 | Y386: =RawSalesTable[[#This Row],[Quantity]]*RawSalesTable[[#This Row],[Unit_Price]] -> 833.79 | Z386: =RawSalesTable[[#This Row],[Gross_Sales]]*RawSalesTable[[#This Row],[Discount_Pct]] -> 41.6895 | AA386: =RawSalesTable[[#This Row],[Gross_Sales]]-RawSalesTable[[#This Row],[Discount_Amount]] -> 792.1005 | AB386: =RawSalesTable[[#This Row],[Unit_Cost]]*RawSalesTable[[#This Row],[Quantity]] -> 464.19 | AC386: =RawSalesTable[[#This Row],[Net_Sales]]-RawSalesTable[[#This Row],[Total_Cost]] -> 327.9105 | AD386: =RawSalesTable[[#This Row],[Profit]]/RawSalesTable[[#This Row],[Net_Sales]] -> 0.41397588 | AE386: =IF(RawSalesTable[[#This Row],[Return_Status]]="Yes",1,0) -> 0 | AF386: =YEAR(RawSalesTable[[#This Row],[Order_Date]]) -> 2025 | AG386: =MONTH(RawSalesTable[[#This Row],[Order_Date]]) -> 8 | AH386: =TEXT(RawSalesTable[[#This Row],[Order_Date]],"mmmm") -> août | AI386: =IF(RawSalesTable[[#This Row],[Month_Number]]<=3,"Q1",IF(RawSalesTable[[#This Row],[Month_Number]]<=6,"Q2",IF(RawSalesTable[[#This Row],[Month_Number]]<=9,"Q3","Q4"))) -> Q3 | AJ386: =DATE(YEAR(RawSalesTable[[#This Row],[Order_Date]]),MONTH(RawSalesTable[[#This Row],[Order_Date]]),1) -> 45870 | AK386: =VLOOKUP(RawSalesTable[[#This Row],[Customer_ID_clean]],CustomersTable[],4,FALSE) -> Quebec
A387: ORD-2025-00379 | B387: 45793 | C387: C0119 | D387: P1018 | E387: Liam Chen, Winnipeg, Consumer | F387: Online Fulfillment | G387: L. Chen | H387: Online | I387: 4 | J387: 29.49 | K387: 0 | L387: PayPal | M387: 2 | N387: No | O387: =SUBSTITUTE(PROPER(TRIM(RawSalesTable[[#This Row],[Channel_Raw]])), "Market Place", "Marketplace") -> Online | P387: =TRIM(RawSalesTable[[#This Row],[Store_Raw]]) -> Online Fulfillment | Q387: =IF(TRIM(RawSalesTable[[#This Row],[Payment_Method_Raw]])="","Non renseigné",SUBSTITUTE(TRIM(RawSalesTable[[#This Row],[Payment_Method_Raw]]),"CC","Credit Card")) -> PayPal | R387: =UPPER(PROPER(RawSalesTable[[#This Row],[Customer_ID]])) -> C0119 | S387: =TRIM(LEFT(RawSalesTable[[#This Row],[Customer_Info]],FIND(",",RawSalesTable[[#This Row],[Customer_Info]]) -1)) -> Liam Chen | T387: =TRIM(MID(RawSalesTable[[#This Row],[Customer_Info]],FIND(",",RawSalesTable[[#This Row],[Customer_Info]])+1,FIND(",",RawSalesTable[[#This Row],[Customer_Info]],FIND(",",RawSalesTable[[#This Row],[Customer_Info]])+1)-FIND(",",RawSalesTable[[#This Row],[Customer_Info]])-1)) -> Winnipeg | U387: =TRIM(RIGHT(RawSalesTable[[#This Row],[Customer_Info]], LEN(RawSalesTable[[#This Row],[Customer_Info]])-FIND(",",RawSalesTable[[#This Row],[Customer_Info]],FIND(",",RawSalesTable[[#This Row],[Customer_Info]])+1))) -> Consumer | V387: =VLOOKUP(RawSalesTable[[#This Row],[Product_ID]],ProductsTable[],2,FALSE) -> Air Fryer | W387: =VLOOKUP(RawSalesTable[[#This Row],[Product_ID]],ProductsTable[],3,FALSE) -> Home | X387: =VLOOKUP(RawSalesTable[[#This Row],[Product_ID]],ProductsTable[],5,FALSE) -> 14.58 | Y387: =RawSalesTable[[#This Row],[Quantity]]*RawSalesTable[[#This Row],[Unit_Price]] -> 117.96 | Z387: =RawSalesTable[[#This Row],[Gross_Sales]]*RawSalesTable[[#This Row],[Discount_Pct]] -> 0 | AA387: =RawSalesTable[[#This Row],[Gross_Sales]]-RawSalesTable[[#This Row],[Discount_Amount]] -> 117.96 | AB387: =RawSalesTable[[#This Row],[Unit_Cost]]*RawSalesTable[[#This Row],[Quantity]] -> 58.32 | AC387: =RawSalesTable[[#This Row],[Net_Sales]]-RawSalesTable[[#This Row],[Total_Cost]] -> 59.64 | AD387: =RawSalesTable[[#This Row],[Profit]]/RawSalesTable[[#This Row],[Net_Sales]] -> 0.50559512 | AE387: =IF(RawSalesTable[[#This Row],[Return_Status]]="Yes",1,0) -> 0 | AF387: =YEAR(RawSalesTable[[#This Row],[Order_Date]]) -> 2025 | AG387: =MONTH(RawSalesTable[[#This Row],[Order_Date]]) -> 5 | AH387: =TEXT(RawSalesTable[[#This Row],[Order_Date]],"mmmm") -> mai | AI387: =IF(RawSalesTable[[#This Row],[Month_Number]]<=3,"Q1",IF(RawSalesTable[[#This Row],[Month_Number]]<=6,"Q2",IF(RawSalesTable[[#This Row],[Month_Number]]<=9,"Q3","Q4"))) -> Q2 | AJ387: =DATE(YEAR(RawSalesTable[[#This Row],[Order_Date]]),MONTH(RawSalesTable[[#This Row],[Order_Date]]),1) -> 45778 | AK387: =VLOOKUP(RawSalesTable[[#This Row],[Customer_ID_clean]],CustomersTable[],4,FALSE) -> Manitoba
A388: ORD-2025-00380 | B388: 45719 | C388: C0069 | D388: P1006 | E388: Sarah White, Ottawa, Consumer | F388: Vancouver West | G388: L. Chen | H388: Online | I388: 3 | J388: 102 | K388: 0 | L388: PayPal | M388: 8 | N388: No | O388: =SUBSTITUTE(PROPER(TRIM(RawSalesTable[[#This Row],[Channel_Raw]])), "Market Place", "Marketplace") -> Online | P388: =TRIM(RawSalesTable[[#This Row],[Store_Raw]]) -> Vancouver West | Q388: =IF(TRIM(RawSalesTable[[#This Row],[Payment_Method_Raw]])="","Non renseigné",SUBSTITUTE(TRIM(RawSalesTable[[#This Row],[Payment_Method_Raw]]),"CC","Credit Card")) -> PayPal | R388: =UPPER(PROPER(RawSalesTable[[#This Row],[Customer_ID]])) -> C0069 | S388: =TRIM(LEFT(RawSalesTable[[#This Row],[Customer_Info]],FIND(",",RawSalesTable[[#This Row],[Customer_Info]]) -1)) -> Sarah White | T388: =TRIM(MID(RawSalesTable[[#This Row],[Customer_Info]],FIND(",",RawSalesTable[[#This Row],[Customer_Info]])+1,FIND(",",RawSalesTable[[#This Row],[Customer_Info]],FIND(",",RawSalesTable[[#This Row],[Customer_Info]])+1)-FIND(",",RawSalesTable[[#This Row],[Customer_Info]])-1)) -> Ottawa | U388: =TRIM(RIGHT(RawSalesTable[[#This Row],[Customer_Info]], LEN(RawSalesTable[[#This Row],[Customer_Info]])-FIND(",",RawSalesTable[[#This Row],[Customer_Info]],FIND(",",RawSalesTable[[#This Row],[Customer_Info]])+1))) -> Consumer | V388: =VLOOKUP(RawSalesTable[[#This Row],[Product_ID]],ProductsTable[],2,FALSE) -> USB-C Hub | W388: =VLOOKUP(RawSalesTable[[#This Row],[Product_ID]],ProductsTable[],3,FALSE) -> Electronics | X388: =VLOOKUP(RawSalesTable[[#This Row],[Product_ID]],ProductsTable[],5,FALSE) -> 72 | Y388: =RawSalesTable[[#This Row],[Quantity]]*RawSalesTable[[#This Row],[Unit_Price]] -> 306 | Z388: =RawSalesTable[[#This Row],[Gross_Sales]]*RawSalesTable[[#This Row],[Discount_Pct]] -> 0 | AA388: =RawSalesTable[[#This Row],[Gross_Sales]]-RawSalesTable[[#This Row],[Discount_Amount]] -> 306 | AB388: =RawSalesTable[[#This Row],[Unit_Cost]]*RawSalesTable[[#This Row],[Quantity]] -> 216 | AC388: =RawSalesTable[[#This Row],[Net_Sales]]-RawSalesTable[[#This Row],[Total_Cost]] -> 90 | AD388: =RawSalesTable[[#This Row],[Profit]]/RawSalesTable[[#This Row],[Net_Sales]] -> 0.29411765 | AE388: =IF(RawSalesTable[[#This Row],[Return_Status]]="Yes",1,0) -> 0 | AF388: =YEAR(RawSalesTable[[#This Row],[Order_Date]]) -> 2025 | AG388: =MONTH(RawSalesTable[[#This Row],[Order_Date]]) -> 3 | AH388: =TEXT(RawSalesTable[[#This Row],[Order_Date]],"mmmm") -> mars | AI388: =IF(RawSalesTable[[#This Row],[Month_Number]]<=3,"Q1",IF(RawSalesTable[[#This Row],[Month_Number]]<=6,"Q2",IF(RawSalesTable[[#This Row],[Month_Number]]<=9,"Q3","Q4"))) -> Q1 | AJ388: =DATE(YEAR(RawSalesTable[[#This Row],[Order_Date]]),MONTH(RawSalesTable[[#This Row],[Order_Date]]),1) -> 45717 | AK388: =VLOOKUP(RawSalesTable[[#This Row],[Customer_ID_clean]],CustomersTable[],4,FALSE) -> Ontario
A389: ORD-2025-00381 | B389: 45746 | C389: C0082 | D389: P1012 | E389: Ryan King, Winnipeg, Small Business | F389: Montreal Central | G389: S. Patel | H389: Marketplace | I389: 3 | J389: 81.49 | K389: 0.05 | L389: Gift Card | M389: 2 | N389: No | O389: =SUBSTITUTE(PROPER(TRIM(RawSalesTable[[#This Row],[Channel_Raw]])), "Market Place", "Marketplace") -> Marketplace | P389: =TRIM(RawSalesTable[[#This Row],[Store_Raw]]) -> Montreal Central | Q389: =IF(TRIM(RawSalesTable[[#This Row],[Payment_Method_Raw]])="","Non renseigné",SUBSTITUTE(TRIM(RawSalesTable[[#This Row],[Payment_Method_Raw]]),"CC","Credit Card")) -> Gift Card | R389: =UPPER(PROPER(RawSalesTable[[#This Row],[Customer_ID]])) -> C0082 | S389: =TRIM(LEFT(RawSalesTable[[#This Row],[Customer_Info]],FIND(",",RawSalesTable[[#This Row],[Customer_Info]]) -1)) -> Ryan King | T389: =TRIM(MID(RawSalesTable[[#This Row],[Customer_Info]],FIND(",",RawSalesTable[[#This Row],[Customer_Info]])+1,FIND(",",RawSalesTable[[#This Row],[Customer_Info]],FIND(",",RawSalesTable[[#This Row],[Customer_Info]])+1)-FIND(",",RawSalesTable[[#This Row],[Customer_Info]])-1)) -> Winnipeg | U389: =TRIM(RIGHT(RawSalesTable[[#This Row],[Customer_Info]], LEN(RawSalesTable[[#This Row],[Customer_Info]])-FIND(",",RawSalesTable[[#This Row],[Customer_Info]],FIND(",",RawSalesTable[[#This Row],[Customer_Info]])+1))) -> Small Business | V389: =VLOOKUP(RawSalesTable[[#This Row],[Product_ID]],ProductsTable[],2,FALSE) -> Standing Desk | W389: =VLOOKUP(RawSalesTable[[#This Row],[Product_ID]],ProductsTable[],3,FALSE) -> Office | X389: =VLOOKUP(RawSalesTable[[#This Row],[Product_ID]],ProductsTable[],5,FALSE) -> 45.17 | Y389: =RawSalesTable[[#This Row],[Quantity]]*RawSalesTable[[#This Row],[Unit_Price]] -> 244.47 | Z389: =RawSalesTable[[#This Row],[Gross_Sales]]*RawSalesTable[[#This Row],[Discount_Pct]] -> 12.2235 | AA389: =RawSalesTable[[#This Row],[Gross_Sales]]-RawSalesTable[[#This Row],[Discount_Amount]] -> 232.2465 | AB389: =RawSalesTable[[#This Row],[Unit_Cost]]*RawSalesTable[[#This Row],[Quantity]] -> 135.51 | AC389: =RawSalesTable[[#This Row],[Net_Sales]]-RawSalesTable[[#This Row],[Total_Cost]] -> 96.7365 | AD389: =RawSalesTable[[#This Row],[Profit]]/RawSalesTable[[#This Row],[Net_Sales]] -> 0.41652511 | AE389: =IF(RawSalesTable[[#This Row],[Return_Status]]="Yes",1,0) -> 0 | AF389: =YEAR(RawSalesTable[[#This Row],[Order_Date]]) -> 2025 | AG389: =MONTH(RawSalesTable[[#This Row],[Order_Date]]) -> 3 | AH389: =TEXT(RawSalesTable[[#This Row],[Order_Date]],"mmmm") -> mars | AI389: =IF(RawSalesTable[[#This Row],[Month_Number]]<=3,"Q1",IF(RawSalesTable[[#This Row],[Month_Number]]<=6,"Q2",IF(RawSalesTable[[#This Row],[Month_Number]]<=9,"Q3","Q4"))) -> Q1 | AJ389: =DATE(YEAR(RawSalesTable[[#This Row],[Order_Date]]),MONTH(RawSalesTable[[#This Row],[Order_Date]]),1) -> 45717 | AK389: =VLOOKUP(RawSalesTable[[#This Row],[Customer_ID_clean]],CustomersTable[],4,FALSE) -> Manitoba
A390: ORD-2025-00382 | B390: 45786 | C390: C0009 | D390: P1012 | E390: Ethan Tremblay, Mississauga, Corporate | F390: Toronto Downtown | G390: N. Brown | H390: Retail Store | I390: 4 | J390: 82.08 | K390: 0.2 | L390: Debit Card | M390: 1 | N390: No | O390: =SUBSTITUTE(PROPER(TRIM(RawSalesTable[[#This Row],[Channel_Raw]])), "Market Place", "Marketplace") -> Retail Store | P390: =TRIM(RawSalesTable[[#This Row],[Store_Raw]]) -> Toronto Downtown | Q390: =IF(TRIM(RawSalesTable[[#This Row],[Payment_Method_Raw]])="","Non renseigné",SUBSTITUTE(TRIM(RawSalesTable[[#This Row],[Payment_Method_Raw]]),"CC","Credit Card")) -> Debit Card | R390: =UPPER(PROPER(RawSalesTable[[#This Row],[Customer_ID]])) -> C0009 | S390: =TRIM(LEFT(RawSalesTable[[#This Row],[Customer_Info]],FIND(",",RawSalesTable[[#This Row],[Customer_Info]]) -1)) -> Ethan Tremblay | T390: =TRIM(MID(RawSalesTable[[#This Row],[Customer_Info]],FIND(",",RawSalesTable[[#This Row],[Customer_Info]])+1,FIND(",",RawSalesTable[[#This Row],[Customer_Info]],FIND(",",RawSalesTable[[#This Row],[Customer_Info]])+1)-FIND(",",RawSalesTable[[#This Row],[Customer_Info]])-1)) -> Mississauga | U390: =TRIM(RIGHT(RawSalesTable[[#This Row],[Customer_Info]], LEN(RawSalesTable[[#This Row],[Customer_Info]])-FIND(",",RawSalesTable[[#This Row],[Customer_Info]],FIND(",",RawSalesTable[[#This Row],[Customer_Info]])+1))) -> Corporate | V390: =VLOOKUP(RawSalesTable[[#This Row],[Product_ID]],ProductsTable[],2,FALSE) -> Standing Desk | W390: =VLOOKUP(RawSalesTable[[#This Row],[Product_ID]],ProductsTable[],3,FALSE) -> Office | X390: =VLOOKUP(RawSalesTable[[#This Row],[Product_ID]],ProductsTable[],5,FALSE) -> 45.17 | Y390: =RawSalesTable[[#This Row],[Quantity]]*RawSalesTable[[#This Row],[Unit_Price]] -> 328.32 | Z390: =RawSalesTable[[#This Row],[Gross_Sales]]*RawSalesTable[[#This Row],[Discount_Pct]] -> 65.664 | AA390: =RawSalesTable[[#This Row],[Gross_Sales]]-RawSalesTable[[#This Row],[Discount_Amount]] -> 262.656 | AB390: =RawSalesTable[[#This Row],[Unit_Cost]]*RawSalesTable[[#This Row],[Quantity]] -> 180.68 | AC390: =RawSalesTable[[#This Row],[Net_Sales]]-RawSalesTable[[#This Row],[Total_Cost]] -> 81.976 | AD390: =RawSalesTable[[#This Row],[Profit]]/RawSalesTable[[#This Row],[Net_Sales]] -> 0.31210404 | AE390: =IF(RawSalesTable[[#This Row],[Return_Status]]="Yes",1,0) -> 0 | AF390: =YEAR(RawSalesTable[[#This Row],[Order_Date]]) -> 2025 | AG390: =MONTH(RawSalesTable[[#This Row],[Order_Date]]) -> 5 | AH390: =TEXT(RawSalesTable[[#This Row],[Order_Date]],"mmmm") -> mai | AI390: =IF(RawSalesTable[[#This Row],[Month_Number]]<=3,"Q1",IF(RawSalesTable[[#This Row],[Month_Number]]<=6,"Q2",IF(RawSalesTable[[#This Row],[Month_Number]]<=9,"Q3","Q4"))) -> Q2 | AJ390: =DATE(YEAR(RawSalesTable[[#This Row],[Order_Date]]),MONTH(RawSalesTable[[#This Row],[Order_Date]]),1) -> 45778 | AK390: =VLOOKUP(RawSalesTable[[#This Row],[Customer_ID_clean]],CustomersTable[],4,FALSE) -> Ontario
A391: ORD-2025-00383 | B391: 45947 | C391: C0043 | D391: P1007 | E391: Ava Brown, Ottawa, Small Business | F391: Calgary North | G391: N. Brown | H391: Marketplace | I391: 2 | J391: 369.15 | K391: 0 | L391: PayPal | M391: 2 | N391: No | O391: =SUBSTITUTE(PROPER(TRIM(RawSalesTable[[#This Row],[Channel_Raw]])), "Market Place", "Marketplace") -> Marketplace | P391: =TRIM(RawSalesTable[[#This Row],[Store_Raw]]) -> Calgary North | Q391: =IF(TRIM(RawSalesTable[[#This Row],[Payment_Method_Raw]])="","Non renseigné",SUBSTITUTE(TRIM(RawSalesTable[[#This Row],[Payment_Method_Raw]]),"CC","Credit Card")) -> PayPal | R391: =UPPER(PROPER(RawSalesTable[[#This Row],[Customer_ID]])) -> C0043 | S391: =TRIM(LEFT(RawSalesTable[[#This Row],[Customer_Info]],FIND(",",RawSalesTable[[#This Row],[Customer_Info]]) -1)) -> Ava Brown | T391: =TRIM(MID(RawSalesTable[[#This Row],[Customer_Info]],FIND(",",RawSalesTable[[#This Row],[Customer_Info]])+1,FIND(",",RawSalesTable[[#This Row],[Customer_Info]],FIND(",",RawSalesTable[[#This Row],[Customer_Info]])+1)-FIND(",",RawSalesTable[[#This Row],[Customer_Info]])-1)) -> Ottawa | U391: =TRIM(RIGHT(RawSalesTable[[#This Row],[Customer_Info]], LEN(RawSalesTable[[#This Row],[Customer_Info]])-FIND(",",RawSalesTable[[#This Row],[Customer_Info]],FIND(",",RawSalesTable[[#This Row],[Customer_Info]])+1))) -> Small Business | V391: =VLOOKUP(RawSalesTable[[#This Row],[Product_ID]],ProductsTable[],2,FALSE) -> Monitor | W391: =VLOOKUP(RawSalesTable[[#This Row],[Product_ID]],ProductsTable[],3,FALSE) -> Electronics | X391: =VLOOKUP(RawSalesTable[[#This Row],[Product_ID]],ProductsTable[],5,FALSE) -> 224.47 | Y391: =RawSalesTable[[#This Row],[Quantity]]*RawSalesTable[[#This Row],[Unit_Price]] -> 738.3 | Z391: =RawSalesTable[[#This Row],[Gross_Sales]]*RawSalesTable[[#This Row],[Discount_Pct]] -> 0 | AA391: =RawSalesTable[[#This Row],[Gross_Sales]]-RawSalesTable[[#This Row],[Discount_Amount]] -> 738.3 | AB391: =RawSalesTable[[#This Row],[Unit_Cost]]*RawSalesTable[[#This Row],[Quantity]] -> 448.94 | AC391: =RawSalesTable[[#This Row],[Net_Sales]]-RawSalesTable[[#This Row],[Total_Cost]] -> 289.36 | AD391: =RawSalesTable[[#This Row],[Profit]]/RawSalesTable[[#This Row],[Net_Sales]] -> 0.3919274 | AE391: =IF(RawSalesTable[[#This Row],[Return_Status]]="Yes",1,0) -> 0 | AF391: =YEAR(RawSalesTable[[#This Row],[Order_Date]]) -> 2025 | AG391: =MONTH(RawSalesTable[[#This Row],[Order_Date]]) -> 10 | AH391: =TEXT(RawSalesTable[[#This Row],[Order_Date]],"mmmm") -> octobre | AI391: =IF(RawSalesTable[[#This Row],[Month_Number]]<=3,"Q1",IF(RawSalesTable[[#This Row],[Month_Number]]<=6,"Q2",IF(RawSalesTable[[#This Row],[Month_Number]]<=9,"Q3","Q4"))) -> Q4 | AJ391: =DATE(YEAR(RawSalesTable[[#This Row],[Order_Date]]),MONTH(RawSalesTable[[#This Row],[Order_Date]]),1) -> 45931 | AK391: =VLOOKUP(RawSalesTable[[#This Row],[Customer_ID_clean]],CustomersTable[],4,FALSE) -> Ontario
A392: ORD-2025-00384 | B392: 45947 | C392: C0037 | D392: P1029 | E392: Lucas Scott, Victoria, Small Business | F392: Vancouver West | G392: S. Patel | H392: online | I392: 5 | J392: 198.14 | K392: 0.25 | L392: Paypal | M392: 6 | N392: Yes | O392: =SUBSTITUTE(PROPER(TRIM(RawSalesTable[[#This Row],[Channel_Raw]])), "Market Place", "Marketplace") -> Online | P392: =TRIM(RawSalesTable[[#This Row],[Store_Raw]]) -> Vancouver West | Q392: =IF(TRIM(RawSalesTable[[#This Row],[Payment_Method_Raw]])="","Non renseigné",SUBSTITUTE(TRIM(RawSalesTable[[#This Row],[Payment_Method_Raw]]),"CC","Credit Card")) -> Paypal | R392: =UPPER(PROPER(RawSalesTable[[#This Row],[Customer_ID]])) -> C0037 | S392: =TRIM(LEFT(RawSalesTable[[#This Row],[Customer_Info]],FIND(",",RawSalesTable[[#This Row],[Customer_Info]]) -1)) -> Lucas Scott | T392: =TRIM(MID(RawSalesTable[[#This Row],[Customer_Info]],FIND(",",RawSalesTable[[#This Row],[Customer_Info]])+1,FIND(",",RawSalesTable[[#This Row],[Customer_Info]],FIND(",",RawSalesTable[[#This Row],[Customer_Info]])+1)-FIND(",",RawSalesTable[[#This Row],[Customer_Info]])-1)) -> Victoria | U392: =TRIM(RIGHT(RawSalesTable[[#This Row],[Customer_Info]], LEN(RawSalesTable[[#This Row],[Customer_Info]])-FIND(",",RawSalesTable[[#This Row],[Customer_Info]],FIND(",",RawSalesTable[[#This Row],[Customer_Info]])+1))) -> Small Business | V392: =VLOOKUP(RawSalesTable[[#This Row],[Product_ID]],ProductsTable[],2,FALSE) -> Jump Rope | W392: =VLOOKUP(RawSalesTable[[#This Row],[Product_ID]],ProductsTable[],3,FALSE) -> Fitness | X392: =VLOOKUP(RawSalesTable[[#This Row],[Product_ID]],ProductsTable[],5,FALSE) -> 101 | Y392: =RawSalesTable[[#This Row],[Quantity]]*RawSalesTable[[#This Row],[Unit_Price]] -> 990.7 | Z392: =RawSalesTable[[#This Row],[Gross_Sales]]*RawSalesTable[[#This Row],[Discount_Pct]] -> 247.675 | AA392: =RawSalesTable[[#This Row],[Gross_Sales]]-RawSalesTable[[#This Row],[Discount_Amount]] -> 743.025 | AB392: =RawSalesTable[[#This Row],[Unit_Cost]]*RawSalesTable[[#This Row],[Quantity]] -> 505 | AC392: =RawSalesTable[[#This Row],[Net_Sales]]-RawSalesTable[[#This Row],[Total_Cost]] -> 238.025 | AD392: =RawSalesTable[[#This Row],[Profit]]/RawSalesTable[[#This Row],[Net_Sales]] -> 0.32034588 | AE392: =IF(RawSalesTable[[#This Row],[Return_Status]]="Yes",1,0) -> 1 | AF392: =YEAR(RawSalesTable[[#This Row],[Order_Date]]) -> 2025 | AG392: =MONTH(RawSalesTable[[#This Row],[Order_Date]]) -> 10 | AH392: =TEXT(RawSalesTable[[#This Row],[Order_Date]],"mmmm") -> octobre | AI392: =IF(RawSalesTable[[#This Row],[Month_Number]]<=3,"Q1",IF(RawSalesTable[[#This Row],[Month_Number]]<=6,"Q2",IF(RawSalesTable[[#This Row],[Month_Number]]<=9,"Q3","Q4"))) -> Q4 | AJ392: =DATE(YEAR(RawSalesTable[[#This Row],[Order_Date]]),MONTH(RawSalesTable[[#This Row],[Order_Date]]),1) -> 45931 | AK392: =VLOOKUP(RawSalesTable[[#This Row],[Customer_ID_clean]],CustomersTable[],4,FALSE) -> British Columbia
